Workbook
Name _Hlk127349196: 'Aprovados Recursos do Fundo'!$I$48

Sheet Consolidada com todas as notas
AG1: 204
B2: CONSELHO ESTADUAL DO IDOSO Rua Boa Vista, 170- CEP 01204-001 - São Paulo-SP Fone 11-2763-8122/2763-8035 cei@desenvolvimentosocial.sp.gov.br
B3: ORGANIZAÇÕES SOCIAIS
C4: Protocolo | D4: OSC/Prefeitura | E4: NOME DO PROPONENTE | F4: NOME DO PROJETO | G4: EIXO | H4: VALOR TOTAL DO PROJETO | I4: MUNICÍPIO | J4: DRADS | K4: Responsável - OSC | L4: EMAIL | M4: ENTREGUE DIA | N4: ETAPA da Análise | O4: PENDÊNCIA | P4: OBS | Q4: NOTA Gilberto | R4: NOTA Erica | S4: NOTA Enizal | T4: NOTA Walkyria | U4: NOTA Elisete | V4: NOTA Adriano | W4: NOTA Paulo Albano | X4: NOTA Alexandra | Y4: NOTA Priscila | Z4: NOTA Leila | AA4: NOTA Vanise | AB4: NOTA Jeverson | AC4: NOTA Cristiane | AD4: NOTA Márcio | AF4: Média | AG4: RESULTADO FINAL
B5: 1 | C5: 001/23 | D5: Organização | E5: Associação São Joaquim de Apoio à Maturidade | F5: Centro de Convivência Casa Azul | G5: Eixo I: Promoção, Assistência e Desenvolvimento Social | H5: 370460.32 | I5: Carapicuíba/SP | J5: DRADS SPO EM OSASCO | K5: Claudia Regina Ferreira | L5: saojoaquim@saojoaquim.org.br | M5: 45279 | N5: Classificado | Q5: 318 | R5: 244 | S5: 265 | T5: 247 | AE5: =COUNT(Q5:AD5) -> 4 | AF5: =AVERAGE(Q5:AD5) -> 268.5 | AG5: =IF(AF5>=$AG$1,"APROVADO","REPROVADO") -> APROVADO
B6: 2 | C6: 002/23 | D6: Organização | E6: Irmandade Padre Emanoel | F6: CriaMais - Sáude e Arte para Pessoa Idosa | G6: - | H6: 45000 | I6: Palmeira d'Oeste/SP | J6: DRADS FERNANDÓPOLIS | K6: Ludimila Bartolomeu Rodrigues | L6: lardosidosdedalas@hotmail.com | M6: 45313 | N6: Classificado | Q6: 297 | Z6: 310 | AB6: 286 | AC6: 327 | AE6: =COUNT(Q6:AD6) -> 4 | AF6: =AVERAGE(Q6:AD6) -> 305 | AG6: =IF(AF6>=$AG$1,"APROVADO","REPROVADO") -> APROVADO
B7: 3 | C7: 003/23 | D7: Prefeitura | E7: Municipal de Palmeira D'Oeste | F7: Idoso 100% Ativo – Hidroginastica | G7: Eixo I: Promoção, Assistência e Desenvolvimento Social | H7: 84000 | I7: Palmeira D'Oeste | J7: DRADS FERNANDÓPOLIS | K7: Lucinele Gabaldi Bertolassi | L7: pmpalmeira@ig.com.br | M7: 45282 | N7: Pré-Classificado | O7: Plano de trabalho sem n° de páginas | Q7: 321 | R7: 157 | AB7: 325 | AE7: =COUNT(Q7:AD7) -> 3 | AF7: =AVERAGE(Q7:AD7) -> 267.66667 | AG7: =IF(AF7>=$AG$1,"APROVADO","REPROVADO") -> APROVADO
B8: 4 | C8: 004/23 | D8: Organização | E8: Santa Casa de Misericordia de Presidente Prudente | F8: Tratamento Oftalmológico | G8: Eixo II: Sáude | H8: 1000000 | I8: Presidente Prudente/SP | J8: DRADS ALTA SOROCABANA EM PRESIDENTE PRUDENTE | K8: William Boscoli Ribeiro | L8: analista.adm@santacasaprudente.org.br | M8: 45281 | N8: Pré-Classificado | O8: Plano de Trabalho sem n° de páginas | Q8: 312 | S8: 275 | T8: 299 | AE8: =COUNT(Q8:AD8) -> 3 | AF8: =AVERAGE(Q8:AD8) -> 295.33333 | AG8: =IF(AF8>=$AG$1,"APROVADO","REPROVADO") -> APROVADO
B9: 5 | C9: 005/23 | D9: Organização | E9: Associação Santo Agostinho -ASA | F9: Saber Mais, Viver Mais | G9: Eixo III: Educação | H9: 341605 | I9: São Paulo/SP | J9: DRADS CAPITAL EM SÃO PAULO | K9: Thais Certain | L9: thais.certain@asatransforma.org.br | M9: 45288 | N9: Classificado | Q9: 272 | R9: 203 | S9: 269 | T9: 290 | AE9: =COUNT(Q9:AD9) -> 4 | AF9: =AVERAGE(Q9:AD9) -> 258.5 | AG9: =IF(AF9>=$AG$1,"APROVADO","REPROVADO") -> APROVADO
B10: 6 | C10: 006/23 | D10: Organização | E10: Congregação Israelita Paulista | F10: Núcleo de Convivência da Maturidade | G10: Eixo I: Promoção, Assistência e Desenvolvimento Social | H10: 523070 | I10: São Paulo/SP | J10: DRADS CAPITAL EM SÃO PAULO | K10: Laura Feldman | L10: acaosocial@cip.org.br | M10: 45288 | N10: Desclassificado | O10: Plano de Trabalho sem Rubricar | AF10: =AVERAGE(Q10:AD10) -> #DIV/0! | AG10: =IF(AF10>=$AG$1,"APROVADO","REPROVADO") -> #DIV/0!
B11: 7 | C11: 007/23 | D11: Organização | E11: Associação de Apoio ao Paciente Renal Cronico e Transplantado -Carim | F11: Saúde e Movimento | G11: - | H11: 364980 | I11: Presidente Prudente/SP | J11: DRADS ALTA SOROCABANA EM PRESIDENTE PRUDENTE | K11: Sumaia Cristina Zahra Zakir Pereira | L11: carimprudente@yahoo.com. br | M11: 45289 | N11: Pré-Classificado | O11: Falta de Informação do envelope | P11: Doc Word | Q11: 340 | S11: 245 | T11: 290 | AE11: =COUNT(Q11:AD11) -> 3 | AF11: =AVERAGE(Q11:AD11) -> 291.66667 | AG11: =IF(AF11>=$AG$1,"APROVADO","REPROVADO") -> APROVADO
B12: 8 | C12: 008/23 | D12: Organização | E12: Lar Fraterno da Acácia | F12: Aquisição de cadeira de rodas, cadeira de banho, cama, guarda roupa e utensílios para cozinha | G12: Eixo I: Promoção, Assistência e Desenvolvimento Social | H12: 250640 | I12: Jacareí/SP | J12: DRADS VALE DO PARAÍBA EM SÃO JOSÉ DOS CAMPOS | K12: Flávia Aparecida Gonçalves Nascimento | L12: servicosocial.Iarfa@gmail.com | M12: 45296 | N12: Pré-Classificado | O12: Documento Word (Pendrive) | R12: 170 | V12: 302 | W12: 285 | AE12: =COUNT(Q12:AD12) -> 3 | AF12: =AVERAGE(Q12:AD12) -> 252.33333 | AG12: =IF(AF12>=$AG$1,"APROVADO","REPROVADO") -> APROVADO
B13: 9 | C13: 009/23 | D13: Organização | E13: Lar Fraterno da Acácia | F13: Adequação, Acessibilidade | G13: Eixo I: Promoção, Assistência e Desenvolvimento Social | H13: 1288900 | I13: Jacareí/SP | J13: DRADS VALE DO PARAÍBA EM SÃO JOSÉ DOS CAMPOS | K13: Flávia Aparecida Gonçalves Nascimento | L13: servicosocial.Iarfa@gmail.com | M13: 45296 | N13: Pré-Classificado | O13: Documento Word (Pendrive) | R13: 164 | X13: 330 | Y13: 340 | AE13: =COUNT(Q13:AD13) -> 3 | AF13: =AVERAGE(Q13:AD13) -> 278 | AG13: =IF(AF13>=$AG$1,"APROVADO","REPROVADO") -> APROVADO
B14: 10 | C14: 010/23 | D14: Organização | E14: Lar Fraterno da Acácia | F14: Custeio | G14: Eixo I: Promoção, Assistência e Desenvolvimento Social | H14: 1086393.6 | I14: Jacareí/SP | J14: DRADS VALE DO PARAÍBA EM SÃO JOSÉ DOS CAMPOS | K14: Flávia Aparecida Gonçalves Nascimento | L14: z | M14: 45296 | N14: Pré-Classificado | O14: Documento Word (Pendrive) | R14: 146 | V14: 340 | W14: 330 | AE14: =COUNT(Q14:AD14) -> 3 | AF14: =AVERAGE(Q14:AD14) -> 272 | AG14: =IF(AF14>=$AG$1,"APROVADO","REPROVADO") -> APROVADO
B15: 11 | C15: 011/23 | D15: Organização | E15: Obra Social e Assistencial São Lucas | F15: O amor Exige Cuidado | G15: Eixo VII: Cultura, Esporte, Turismo e Lazer | H15: 193281.12 | I15: São José dos Campos/SP | J15: DRADS VALE DO PARAÍBA EM SÃO JOSÉ DOS CAMPOS | K15: Nelcira Rosa da Silva Lima | L15: obrasaolucas@terra.com.br | M15: 45296 | N15: Classificado | Q15: 312 | R15: 199 | S15: 237 | T15: 174 | AE15: =COUNT(Q15:AD15) -> 4 | AF15: =AVERAGE(Q15:AD15) -> 230.5 | AG15: =IF(AF15>=$AG$1,"APROVADO","REPROVADO") -> APROVADO
B16: 12 | C16: 012/23 | D16: Prefeitura | E16: Municipal de Boraceia | F16: Projeto Vida Ativa na Melhor Idade | G16: Eixo I: Promoção, Assistência e Desenvolvimento Social | H16: 244231.32 | I16: Boraceia | J16: DRADS BAURU | K16: Vania de Souza Melo Carlini | L16: orgestorp@hotmail.com | M16: 45296 | N16: Pré-Classificado | O16: Documentos Word (Pendrive) | Q16: 329 | V16: 340 | W16: 323 | AE16: =COUNT(Q16:AD16) -> 3 | AF16: =AVERAGE(Q16:AD16) -> 330.66667 | AG16: =IF(AF16>=$AG$1,"APROVADO","REPROVADO") -> APROVADO
B17: 13 | C17: 013/23 | D17: Organização | E17: Lar dos Velhinhos Papa João XXIII | F17: Cozinha | G17: Eixo I: Promoção, Assistência e Desenvolvimento Social | H17: 69808.08 | I17: Salto Grande/SP | J17: DRADS AVARÉ | K17: Bruna Fernandes Araujo | L17: asilosaltogrande@hotmail.com | M17: 45299 | N17: Classificado | Q17: 329 | R17: 118 | S17: 236 | T17: 200 | AE17: =COUNT(Q17:AD17) -> 4 | AF17: =AVERAGE(Q17:AD17) -> 220.75 | AG17: =IF(AF17>=$AG$1,"APROVADO","REPROVADO") -> APROVADO
B18: 14 | C18: 014/23 | D18: Organização | E18: Lar do Velhinhos Papa João XXIII | F18: Lavanderia | G18: Eixo I: Promoção, Assistência e Desenvolvimento Social | H18: 275400 | I18: Salto Grande/SP | J18: DRADS AVARÉ | K18: Bruna Fernandes Araujo | L18: asiloaltogrande@hotmail.com | M18: 45321 | N18: Classificado | P18: Verificar se não são repetidos (Protocolo 014 e 348/23) | Q18: 288 | R18: 118 | T18: 177 | AF18: =AVERAGE(Q18:AD18) -> 194.33333 | AG18: =IF(AF18>=$AG$1,"APROVADO","REPROVADO") -> REPROVADO
B19: 15 | C19: 015/23 | D19: Organização | E19: Associação Lar dos Idosos de Alvares Machado | F19: EQUIPAR II | G19: Eixo I: Promoção, Assistência e Desenvolvimento Social | H19: 40000 | I19: Álvares Machado/SP | J19: DRADS ALTA SOROCABANA EM PRESIDENTE PRUDENTE | K19: Gislaine Girotti Zanoni | L19: lardosidososdam@yahoo.com.br | M19: 45300 | N19: Classificado | Q19: 340 | R19: 215 | S19: 285 | T19: 300 | AE19: =COUNT(Q19:AD19) -> 4 | AF19: =AVERAGE(Q19:AD19) -> 285 | AG19: =IF(AF19>=$AG$1,"APROVADO","REPROVADO") -> APROVADO
B20: 16 | C20: 016/23 | D20: Organização | E20: ACBNIBRA Associação Cultural, Beneficiente e Esportiva Nipo Brasileiro de Jacupiranga | F20: Projeto Jacupiranga Melhor Idade | G20: Eixo VII: Cultura, Esporte, Turismo e Lazer | H20: 29714 | I20: Jacupiranga/SP | J20: DRADS VALE DO RIBEIRA EM REGISTRO | K20: SR. Angelo | L20: saitto@terra.combr | M20: 45300 | N20: Pré-Classificado | O20: Documento Word (Pendrive) | Q20: 340 | R20: 209 | AD20: 340 | AE20: =COUNT(Q20:AD20) -> 3 | AF20: =AVERAGE(Q20:AD20) -> 296.33333 | AG20: =IF(AF20>=$AG$1,"APROVADO","REPROVADO") -> APROVADO
B21: 17 | C21: 017/23 | D21: Organização | E21: União Espírita Cachoerense | F21: Energia do Bem | G21: Eixo I: Promoção, Assistência e Desenvolvimento Social | H21: 91857.47 | I21: Cachoeira Paulista/SP | J21: DRADS VALE DO PARAÍBA EM SÃO JOSÉ DOS CAMPOS | K21: DéboraFerreira Comonian | L21: u.e.c.1918@gmail.com | M21: 45301 | N21: Classificado | Q21: 340 | R21: 214 | S21: 253 | T21: 242 | AE21: =COUNT(Q21:AD21) -> 4 | AF21: =AVERAGE(Q21:AD21) -> 262.25 | AG21: =IF(AF21>=$AG$1,"APROVADO","REPROVADO") -> APROVADO
B22: 18 | C22: 018/23 | D22: Organização | E22: Obra Unida Lar São Vicente de Paulo de Guariba | F22: Ambiência para o bem-estar e eficiência na aplicação de recursos | G22: Eixo I: Promoção, Assistência e Desenvolvimento Social | H22: 67100 | I22: Guariba/SP | J22: DRADS RIBEIRÃO PRETO | K22: Gabriel Lopes | L22: larsvpguariba@hotmail.com | M22: 45302 | N22: Pré-Classificado | O22: PDF sem rubricas | R22: 199 | X22: 326 | Y22: 323 | AE22: =COUNT(Q22:AD22) -> 3 | AF22: =AVERAGE(Q22:AD22) -> 282.66667 | AG22: =IF(AF22>=$AG$1,"APROVADO","REPROVADO") -> APROVADO
B23: 19 | C23: 019/23 | D23: Prefeitura | E23: Municipal de Pratânia | F23: Grupo Melhor Idade | G23: Eixo I: Promoção, Assistência e Desenvolvimento Social | H23: 120000 | I23: Pratânia/SP | J23: DRADS BOTUCATU | K23: Elaine Cristina Rodrigues Honorato | L23: cras@boraceia.sp.gov.br | M23: 45302 | N23: Classificado | Q23: 297 | S23: 180 | T23: 112 | AF23: =AVERAGE(Q23:AD23) -> 196.33333 | AG23: =IF(AF23>=$AG$1,"APROVADO","REPROVADO") -> REPROVADO
B24: 20 | C24: 020/23 | D24: Prefeitura | E24: Municipal de Regente Feijó | F24: Fomento aos Direitos da Pessoa Idosa de Regente Feijó | G24: Eixo I: Promoção, Assistência e Desenvolvimento Social | H24: 267000 | I24: Regente Feijó | J24: DRADS ALTA SOROCABANA EM PRESIDENTE PRUDENTE | K24: Marcel Henrique de Mello Moraes | L24: asocial1@pratania.sp.gov.br | M24: 45302 | N24: Classificado | Q24: 330 | S24: 160 | T24: 125 | AE24: =COUNT(Q24:AD24) -> 3 | AF24: =AVERAGE(Q24:AD24) -> 205 | AG24: =IF(AF24>=$AG$1,"APROVADO","REPROVADO") -> APROVADO
B25: 21 | C25: 021/23 | D25: Organização | E25: Lar São Vicente de Paulo | F25: Revitalizar Para Melhor Viver | G25: Eixo V: Habitação e Urbanismo | H25: 192880.29 | I25: Santa Cruz do Rio Pardo/SP | J25: DRADS AVARÉ | K25: Acácio Henrique de Lima | L25: s.v.paulo@hotmail.com | M25: 45302 | N25: Desclassificado | O25: Plano de Trabalho sem Rubricar | AF25: =AVERAGE(Q25:AD25) -> #DIV/0! | AG25: =IF(AF25>=$AG$1,"APROVADO","REPROVADO") -> #DIV/0!
B26: 22 | C26: 022/23 | D26: Organização | E26: Lar São Vicente de Paulo | F26: Reforma e Ampliação da Sala de Fisioterapia do Lar São Vicente de Paulo | G26: Eixo I: Promoção, Assistência e Desenvolvimento Social | H26: 50000 | I26: Bernadino de Campo/SP | J26: DRADS BARRETOS | K26: Antônio Roberto de Oliveira | L26: Iarsaovicente@cednet. com. Br | M26: 45302 | N26: Pré-Classificado | O26: Falta de Informação do envelope | P26: Plano e Pendrive OK | Q26: 340 | R26: 178 | AD26: 340 | AE26: =COUNT(Q26:AD26) -> 3 | AF26: =AVERAGE(Q26:AD26) -> 286 | AG26: =IF(AF26>=$AG$1,"APROVADO","REPROVADO") -> APROVADO
B27: 23 | C27: 023/23 | D27: Prefeitura | E27: Municipal de São Jose do Rio Preto | F27: Oficinas e atividades artístico-culturais como instrumento de Intervenção Social Emancipatória para a pessoa idosa em situação de vulnerabilidade social | G27: Eixo VII: Cultura, Esporte, Turismo e Lazer | H27: 414308.85 | I27: São Jose do Rio Preto/SP | J27: DRADS: SÃO JOSÉ DO RIO PRETO | K27: Eliana Cristina Lechado | L27: convenio@regentefeijo.sp.gov.br | M27: 45302 | N27: Classificado | Q27: 297 | R27: 247 | S27: 249 | T27: 246 | AE27: =COUNT(Q27:AD27) -> 4 | AF27: =AVERAGE(Q27:AD27) -> 259.75 | AG27: =IF(AF27>=$AG$1,"APROVADO","REPROVADO") -> APROVADO
B28: 24 | C28: 024/23 | D28: Organização | E28: Abrigo Lar de Jesus | F28: Bem Estar na Melhor Idade de Anhumas | G28: Eixo I: Promoção, Assistência e Desenvolvimento Social | H28: 267766.51 | I28: Anhumas/SP | J28: DRADS ALTA SOROCABANA EM PRESIDENTE PRUDENTE | K28: Robson Mariano | L28: abrigolardejesus@hotmail.com | M28: 45302 | N28: Classificado | Q28: 331 | R28: 139 | S28: 178 | T28: 248 | AE28: =COUNT(Q28:AD28) -> 4 | AF28: =AVERAGE(Q28:AD28) -> 224 | AG28: =IF(AF28>=$AG$1,"APROVADO","REPROVADO") -> APROVADO
B29: 25 | C29: 025/23 | D29: Organização | E29: Associação Congregação de Santa Catarina | F29: Idoso Digital: Inclusão e Fortalecimento da Cidadania para a Pessoa Idosa | G29: Eixo I: Promoção, Assistência e Desenvolvimento Social | H29: 261777 | I29: Guarulhos/SP | J29: DRADS SPN EM GUARULHOS | K29: Mariana S Leonardo | L29: marina.leonardo@redesc.org.br | M29: 45302 | N29: Classificado | Q29: 340 | R29: 256 | S29: 262 | T29: 302 | AE29: =COUNT(Q29:AD29) -> 4 | AF29: =AVERAGE(Q29:AD29) -> 290 | AG29: =IF(AF29>=$AG$1,"APROVADO","REPROVADO") -> APROVADO
B30: 26 | C30: 026/23 | D30: Organização | E30: Associação Congregação de Santa Catarina | F30: Arte em Movimento: A Pessoa Idosa como Consumidora, Produtora e Disseminadora de Cultura | G30: Eixo VII: Cultura, Esporte, Turismo e Lazer | H30: 207810 | I30: Guarulhos/SP | J30: DRADS SPN EM GUARULHOS | K30: Mariana S. Leonardo | L30: mariana.leonardo@redesc.org.br | M30: 45321 | N30: Pré-Classificado | O30: Plano de Trabalho sem n° de páginas | Q30: 340 | R30: 254 | AD30: 340 | AE30: =COUNT(Q30:AD30) -> 3 | AF30: =AVERAGE(Q30:AD30) -> 311.33333 | AG30: =IF(AF30>=$AG$1,"APROVADO","REPROVADO") -> APROVADO
B31: 27 | C31: 027/23 | D31: Organização | E31: Lar São Vicente de Paulo de Taquarituba | F31: Acessibilidade | G31: Eixo V: Habitação e Urbanismo | H31: 150000 | I31: Taquarituba/SP | J31: DRADS AVARÉ | K31: Isabela Steinert Gabriel | L31: larsaovicente-taquarituba@hotmail.com | M31: 45303 | N31: Classificado | Q31: 306 | R31: 55 | T31: 66 | AF31: =AVERAGE(Q31:AD31) -> 142.33333 | AG31: =IF(AF31>=$AG$1,"APROVADO","REPROVADO") -> REPROVADO
B32: 28 | C32: 028/23 | D32: Organização | E32: Lar São Vicente de Paulo de Taquarituba | F32: Garantia de Bem Estar | G32: Eixo I: Promoção, Assistência e Desenvolvimento Social | H32: 120000 | I32: Taquarituba/SP | J32: DRADS AVARÉ | K32: Isabela Steinert Gabriel | L32: larsaovicente-taquarituba@hotmail.com | M32: 45303 | N32: Classificado | Q32: 340 | S32: 60 | T32: 79 | AF32: =AVERAGE(Q32:AD32) -> 159.66667 | AG32: =IF(AF32>=$AG$1,"APROVADO","REPROVADO") -> REPROVADO
B33: 29 | C33: 029/23 | D33: Organização | E33: Lar São Vicente de Paulo de Taquarituba | F33: Higiene Digna | G33: Eixo V: Habitação e Urbanismo | H33: 70000 | I33: Taquarituba/SP | J33: DRADS AVARÉ | K33: Isabela Steinert Gabriel | L33: larsaovicente-taquarituba@hotmail.com | M33: 45303 | N33: Classificado | Q33: 340 | S33: 58 | AB33: 295 | AE33: =COUNT(Q33:AD33) -> 3 | AF33: =AVERAGE(Q33:AD33) -> 231 | AG33: =IF(AF33>=$AG$1,"APROVADO","REPROVADO") -> APROVADO
B34: 30 | C34: 030/23 | D34: Prefeitura | E34: Municipal de Bastos | F34: Idoso em Movimento | G34: Eixo I: Promoção, Assistência e Desenvolvimento Social | H34: 610060.4 | I34: Bastos/SP | J34: DRADS MARÍLIA | K34: Luzia Kiyoko Honda | L34: semas@riopreto.sp.gov.br | M34: 45303 | N34: Reprovado | O34: Aquisição de Veiculo | Q34: 0 | R34: 29 | S34: 44 | AF34: =AVERAGE(Q34:AD34) -> 24.333333 | AG34: =IF(AF34>=$AG$1,"APROVADO","REPROVADO") -> REPROVADO
B35: 31 | C35: 031/23 | D35: Prefeitura | E35: Municipal de Bastos | F35: Longevidade Ativa e Protegida | G35: Eixo I: Promoção, Assistência e Desenvolvimento Social | H35: 160528.4 | I35: Bastos/SP | J35: DRADS MARÍLIA | K35: Luzia Kiyoko Honda | L35: pmbab@Bastos.sp.gov.br | M35: 45303 | N35: Reprovado | O35: Aquisição de Veiculo | Q35: 0 | R35: 169 | S35: 195 | T35: 206 | AF35: =AVERAGE(Q35:AD35) -> 142.5 | AG35: =IF(AF35>=$AG$1,"APROVADO","REPROVADO") -> REPROVADO
B36: 32 | C36: 032/23 | D36: Prefeitura | E36: Municipal São Cetano | F36: Terceira Idade em Movimento | G36: Eixo VII: Cultura, Esporte, Turismo e Lazer | H36: 344990 | I36: São Caetano do Sul/SP | J36: DRADS ABC EM SANTO ANDRÉ | K36: Tatiana | L36: pmbab@Bastos.sp.gov.br | M36: 45303 | N36: Desclassificado | O36: Plano de Trabalho sem Rubricar | AF36: =AVERAGE(Q36:AD36) -> #DIV/0! | AG36: =IF(AF36>=$AG$1,"APROVADO","REPROVADO") -> #DIV/0!
B37: 33 | C37: 033/23 | D37: Organização | E37: Asilo João kuhl Filho | F37: Colorir | G37: Eixo I: Promoção, Assistência e Desenvolvimento Social | H37: 641438.58 | I37: Limeira/SP | J37: DRADS PIRACICABA | K37: Bárbara Letícia Barbosa Pereira | L37: kuhlfilho@yahoo.com | M37: 45303 | N37: Pré-Classificado | R37: 198 | W37: 340 | Y37: 340 | AE37: =COUNT(Q37:AD37) -> 3 | AF37: =AVERAGE(Q37:AD37) -> 292.66667 | AG37: =IF(AF37>=$AG$1,"APROVADO","REPROVADO") -> APROVADO
B38: 34 | C38: 034/23 | D38: Prefeitura | E38: Municipal de Votuporanga | F38: Vida Longa com Automonia e Bem Estar | G38: Eixo I: Promoção, Assistência e Desenvolvimento Social | H38: 100000 | I38: Votuporanga/SP | J38: DRADS FERNANDÓPOLIS | K38: Meire Regina de Azevedo | L38: protecaosocialespecial@votuporanga.sp.gov.br | M38: 45303 | N38: Classificado | Q38: 337 | R38: 184 | S38: 224 | T38: 238 | AE38: =COUNT(Q38:AD38) -> 4 | AF38: =AVERAGE(Q38:AD38) -> 245.75 | AG38: =IF(AF38>=$AG$1,"APROVADO","REPROVADO") -> APROVADO
B39: 35 | C39: 035/23 | D39: Organização | E39: Associação AnhumasQuero-Quero | F39: ConVIVER: Incentivando a Plenitude na 3° Idade | G39: Eixo I: Promoção, Assistência e Desenvolvimento Social | H39: 283010 | I39: Campinas/SP | J39: DRADS CAMPINAS | K39: Felipe Brandão Teles | L39: administrativo@aaqq.org.br | M39: 45303 | N39: Classificado | Q39: 312 | R39: 121 | S39: 222 | T39: 161 | AE39: =COUNT(Q39:AD39) -> 4 | AF39: =AVERAGE(Q39:AD39) -> 204 | AG39: =IF(AF39>=$AG$1,"APROVADO","REPROVADO") -> APROVADO
B40: 36 | C40: 036/23 | D40: Organização | E40: Lar dos Velhinhos Santo Antônio de Juquiá LVSA | F40: Projeto Viver Bem | G40: Eixo I: Promoção, Assistência e Desenvolvimento Social Eixo VII: Cultura, Esporte, Turismo e Lazer | H40: 53388 | I40: Juquia/SP | J40: DRADS VALE DO RIBEIRA EM REGISTRO | K40: Rhiane Mello dos Santos Fernandes | L40: lardosidososdejuquia@gmail.com | M40: 45303 | N40: Classificado | Q40: 297 | AB40: 243 | AC40: 287 | AE40: =COUNT(Q40:AD40) -> 3 | AF40: =AVERAGE(Q40:AD40) -> 275.66667 | AG40: =IF(AF40>=$AG$1,"APROVADO","REPROVADO") -> APROVADO
B41: 37 | C41: 037/23 | D41: Organização | E41: Lar dos Velhinhos Santo Antônio de Juquiá LVSA | F41: Pintura e Reparos na Instituição | G41: Eixo I: Promoção, Assistência e Desenvolvimento Social | H41: 28000 | I41: Juquia/SP | J41: DRADS VALE DO RIBEIRA EM REGISTRO | K41: Rhiane Mello dos Santos Fernandes | L41: lardosidososdejuquia@gmail.com | M41: 45303 | N41: Classificado | Q41: 340 | Z41: 319 | AC41: 333 | AE41: =COUNT(Q41:AD41) -> 3 | AF41: =AVERAGE(Q41:AD41) -> 330.66667 | AG41: =IF(AF41>=$AG$1,"APROVADO","REPROVADO") -> APROVADO
B42: 38 | C42: 038/23 | D42: Organização | E42: Lar Fraterno São Vicente de Apiaí | F42: Mais conforto | G42: Eixo II: Sáude | H42: 180000 | I42: Apiaí/SP | J42: DRADS ITAPEVA | K42: Alaíme Yuki monteiro Takiguchi Correa | L42: asiloapiai@hotmail.com | M42: 45303 | N42: Reprovado | O42: FALTOU PREENCHER ITEM 6(metodo e dinamica do trabalho) , ITEM 10, 11 E 12 - ORÇAMENTO. | Q42: 332 | S42: 200 | T42: 0 | AF42: =AVERAGE(Q42:AD42) -> 177.33333 | AG42: =IF(AF42>=$AG$1,"APROVADO","REPROVADO") -> REPROVADO
B43: 39 | C43: 039/23 | D43: Organização | E43: Lar Fraterno São Vicente de Apiaí | F43: Buscando Qualidade de Vida | G43: Eixo II: Sáude | H43: 220000 | I43: Apiaí/SP | J43: DRADS ITAPEVA | K43: Alaíme Yuki monteiro Takiguchi Correa | L43: asiloapiai@hotmail.com | M43: 45303 | N43: Pré-Classificado | Q43: 340 | R43: 123 | AD43: 238 | AE43: =COUNT(Q43:AD43) -> 3 | AF43: =AVERAGE(Q43:AD43) -> 233.66667 | AG43: =IF(AF43>=$AG$1,"APROVADO","REPROVADO") -> APROVADO
B44: 40 | C44: 040/23 | D44: Prefeitura | E44: Municipal de Apiaí | F44: Conhecendo População de Pessoas Idosas | G44: Eixo I: Promoção, Assistência e Desenvolvimento Social | H44: 80000 | I44: Apiaí/SP | J44: DRADS ITAPEVA | K44: Sergio Victor Borges Barbosa | L44: deptosocial@nantes.sp.gov.br | M44: 45303 | N44: Pré-Classificado | Q44: 200 | R44: 133 | AB44: 157 | AF44: =AVERAGE(Q44:AD44) -> 163.33333 | AG44: =IF(AF44>=$AG$1,"APROVADO","REPROVADO") -> REPROVADO
B45: 41 | C45: 041/23 | D45: Organização | E45: Lar Fraterno São Vicente de Apiaí | F45: Em busca de um sonho | G45: VII –Turismo | H45: 50000 | I45: Apiaí/SP | J45: DRADS ITAPEVA | K45: Alaíme Yuki monteiro Takiguchi Correa | L45: asiloapiai@hotmail.com | M45: 45303 | N45: Pré-Classificado | R45: 75 | V45: 189 | W45: 164 | AF45: =AVERAGE(Q45:AD45) -> 142.66667 | AG45: =IF(AF45>=$AG$1,"APROVADO","REPROVADO") -> REPROVADO
B46: 42 | C46: 042/23 | D46: Prefeitura | E46: Municipal de Apiaí | F46: Segurança e Qualidade do Atendimento as Pessoas Idosas | G46: Eixo I: Promoção, Assistência e Desenvolvimento Social | H46: 400000 | I46: Apiaí/SP | J46: DRADS ITAPEVA | K46: Sergio Victor Borges Barbosa | L46: social.apiai@gmail.com | M46: 45303 | N46: Pré-Classificado | Q46: 277 | R46: 91 | AC46: 292 | AE46: =COUNT(Q46:AD46) -> 3 | AF46: =AVERAGE(Q46:AD46) -> 220 | AG46: =IF(AF46>=$AG$1,"APROVADO","REPROVADO") -> APROVADO
B47: 43 | C47: 043/23 | D47: Organização | E47: Sociedade Espirita Cinco de Setembro | F47: Acolhendo com Amor - Casa do Vovô - Reforma Hidráulica | G47: Eixo I: Promoção, Assistência e Desenvolvimento Social | H47: 270000 | I47: Ribeirão Preto/SP | J47: DRADS RIBEIRÃO PRETO | K47: Tatiane Tavares | L47: casadovovo@casadovovo.org.br | M47: 45303 | N47: Classificado | Q47: 340 | R47: 120 | S47: 189 | T47: 212 | AE47: =COUNT(Q47:AD47) -> 4 | AF47: =AVERAGE(Q47:AD47) -> 215.25 | AG47: =IF(AF47>=$AG$1,"APROVADO","REPROVADO") -> APROVADO
B48: 44 | C48: 044/23 | D48: Organização | E48: Sociedade Espirita Cinco de Setembro | F48: Cuidar com Excelência: Valorizando a Saúde da Pessoa Idosa | G48: Eixo II: Sáude | H48: 188640 | I48: Ribeirão Preto/SP | J48: DRADS RIBEIRÃO PRETO | K48: Tatiane Tavares | L48: casadovovo@casadovovo.org.br | M48: 45303 | N48: Classificado | Q48: 327 | S48: 190 | T48: 153 | AE48: =COUNT(Q48:AD48) -> 3 | AF48: =AVERAGE(Q48:AD48) -> 223.33333 | AG48: =IF(AF48>=$AG$1,"APROVADO","REPROVADO") -> APROVADO
B49: 45 | C49: 045/23 | D49: Organização | E49: Sociedade Espirita Cinco de Setembro | F49: Viver Ativo - Fomentando Saúde e Integração em Pessoas Idosas | G49: Eixo VII: Cultura, Esporte, Turismo e Lazer | H49: 240000 | I49: Ribeirão Preto/SP | J49: DRADS RIBEIRÃO PRETO | K49: Tatiane Tavares | L49: casadovovo@casadovovo.org.br | M49: 45303 | N49: Classificado | Q49: 333 | R49: 155 | S49: 200 | T49: 168 | AE49: =COUNT(Q49:AD49) -> 4 | AF49: =AVERAGE(Q49:AD49) -> 214 | AG49: =IF(AF49>=$AG$1,"APROVADO","REPROVADO") -> APROVADO
B50: 46 | C50: 046/23 | D50: Organização | E50: Lar dos Velhos da Igreja presbiteriana de Ribeirão Preto | F50: Tecnologia para a Terceira Idade - Inclusão Digital e Social | G50: Eixo III: Educação | H50: 252000 | I50: Ribeirão Preto/SP | J50: DRADS RIBEIRÃO PRETO | K50: Rosangela Aparecida Bellomo Minuti | L50: coordenacao@lardosvelhos.com.br | M50: 45303 | N50: Classificado | Q50: 286 | R50: 305 | S50: 284 | T50: 306 | AE50: =COUNT(Q50:AD50) -> 4 | AF50: =AVERAGE(Q50:AD50) -> 295.25 | AG50: =IF(AF50>=$AG$1,"APROVADO","REPROVADO") -> APROVADO
B51: 47 | C51: 047/23 | D51: Organização | E51: Lar dos Velhos da Igreja presbiteriana de Ribeirão Preto | F51: Adequação e Modernização do Ambiente Institucional: Acolhendo com Dignidade e Respeito | G51: Eixo I: Promoção, Assistência e Desenvolvimento Social | H51: 500000 | I51: Ribeirão Preto/SP | J51: DRADS RIBEIRÃO PRETO | K51: Rosangela Aparecida Bellomo Minuti | L51: coordenacao@lardosvelhos.com.br | M51: 45303 | N51: Classificado | O51: Projeto Duplicado (047/23 e 225/23) | Q51: 340 | R51: 159 | AC51: 333 | AE51: =COUNT(Q51:AD51) -> 3 | AF51: =AVERAGE(Q51:AD51) -> 277.33333 | AG51: =IF(AF51>=$AG$1,"APROVADO","REPROVADO") -> APROVADO
B52: 48 | C52: 048/23 | D52: Organização | E52: Circulo de Trabalhadores Cristoes de Vila Tibério | F52: Acolhendo a Melhor Idade | G52: Eixo I: Promoção, Assistência e Desenvolvimento Social | H52: 200000 | I52: Ribeirão Preto/SP | J52: DRADS RIBEIRÃO PRETO | K52: Luiz Carlos Peruchi | L52: circulooperariorp@hotmail.com | M52: 45303 | N52: Classificado | Q52: 327 | R52: 130 | S52: 224 | T52: 142 | AE52: =COUNT(Q52:AD52) -> 4 | AF52: =AVERAGE(Q52:AD52) -> 205.75 | AG52: =IF(AF52>=$AG$1,"APROVADO","REPROVADO") -> APROVADO
B53: 49 | C53: 049/23 | D53: Organização | E53: Associação Assistencial Maria de Nazaré | F53: Ambientar é Cuidar | G53: Eixo I: Promoção, Assistência e Desenvolvimento Social | H53: 37863.96 | I53: Ribeirão Preto/SP | J53: DRADS RIBEIRÃO PRETO | K53: Gislene Mazer | L53: social@vovoalbano.org.br | M53: 45303 | N53: Classificado | O53: Sem valor no plano de trabalho (apenas o valor no cronograma) | Q53: 340 | R53: 117 | T53: 265 | AE53: =COUNT(Q53:AD53) -> 3 | AF53: =AVERAGE(Q53:AD53) -> 240.66667 | AG53: =IF(AF53>=$AG$1,"APROVADO","REPROVADO") -> APROVADO
B54: 50 | C54: 050/23 | D54: Prefeitura | E54: Municipal de Nantes | F54: Bem Estar na Melhor Idade | G54: Eixo I: Promoção, Assistência e Desenvolvimento Social | H54: 331000 | I54: Nantes/SP | J54: DRADS ALTA SOROCABANA EM PRESIDENTE PRUDENTE | K54: Aline Fernanda de Jesus Souza | L54: protecaosocialespecial@votuporanga.sp.gov.br | M54: 45303 | N54: Reprovado | O54: Aquisição de Veiculo | Q54: 0 | R54: 188 | S54: 243 | T54: 0 | AF54: =AVERAGE(Q54:AD54) -> 107.75 | AG54: =IF(AF54>=$AG$1,"APROVADO","REPROVADO") -> REPROVADO
B55: 51 | C55: 051/23 | D55: Organização | E55: Abrigo de Idosos Recanto do Vovô de Presidente Epitácio-SP | F55: Adequações e melhorias dos banheiros feminino e masculino | G55: Eixo I: Promoção, Assistência e Desenvolvimento Social | H55: 345133.32 | I55: Presidente Epitácio/SP | J55: DRADS ALTA SOROCABANA EM PRESIDENTE PRUDENTE | K55: Virgínio Antonio Mechior | L55: financeiro@recantodovovo.org.br | M55: 45303 | N55: Pré-Classificado | O55: Documento Word (Pendrive) | Q55: 315 | R55: 242 | AD55: 289 | AE55: =COUNT(Q55:AD55) -> 3 | AF55: =AVERAGE(Q55:AD55) -> 282 | AG55: =IF(AF55>=$AG$1,"APROVADO","REPROVADO") -> APROVADO
B56: 52 | C56: 052/23 | D56: Organização | E56: Associação de pais e Amigos dos Excepicinais de São Paulo (Jô Clemente) | F56: Inclusão e Prevenção da Saúde da Pessoa Idosa com Deficiência Intelectual | G56: Eixo II: Sáude | H56: 1431815.8 | I56: São Paulo/SP | J56: DRADS CAPITAL EM SÃO PAULO | K56: Fabio Rubson | L56: projetos@ijc.org.br | M56: 45303 | N56: Classificado | Q56: 340 | R56: 178 | S56: 272 | T56: 288 | AE56: =COUNT(Q56:AD56) -> 4 | AF56: =AVERAGE(Q56:AD56) -> 269.5 | AG56: =IF(AF56>=$AG$1,"APROVADO","REPROVADO") -> APROVADO
B57: 53 | C57: 053/23 | D57: Organização | E57: Movimento Organizacional Vencer, Educar e Realizar - MOVER HELIPA | F57: Projeto Gastronomia e Saberes da Pessoa Idosa | G57: Eixo IV: Trabalho e Previdência Social | H57: 1111410.1 | I57: São Paulo/SP | J57: DRADS CAPITAL EM SÃO PAULO | K57: Jose Renato | L57: moverhelipa@gmail.com | M57: 45303 | N57: Pré-Classificado | O57: Plano de Trabalho sem n° de páginas | Q57: 284 | S57: 246 | T57: 172 | AE57: =COUNT(Q57:AD57) -> 3 | AF57: =AVERAGE(Q57:AD57) -> 234 | AG57: =IF(AF57>=$AG$1,"APROVADO","REPROVADO") -> APROVADO
B58: 54 | C58: 054/23 | D58: Organização | E58: Sociedade São Vicentede Paulo Nossa Senhora das Dores | F58: Cuidar, um Ato de Amor | G58: Eixo I: Promoção, Assistência e Desenvolvimento Social | H58: 88952.51 | I58: São Caeteno/SP | J58: DRADS ABC EM SANTO ANDRÉ | K58: Marli Barreto Felício | L58: sovipansd@yahoo.com.br | M58: 45306 | N58: Classificado | Q58: 340 | R58: 213 | S58: 246 | T58: 290 | AE58: =COUNT(Q58:AD58) -> 4 | AF58: =AVERAGE(Q58:AD58) -> 272.25 | AG58: =IF(AF58>=$AG$1,"APROVADO","REPROVADO") -> APROVADO
B59: 55 | C59: 055/23 | D59: Organização | E59: Lar São Vicente de Paulo | F59: Melhorias e Adequações das Condições de Habitabilidade | G59: Eixo V: Habitação e Urbanismo | H59: 388555.13 | I59: Descalvado/SP | J59: DRADS ARARAQUARA | K59: Vírginia Elaine da S. N. Guiguer | L59: larsao vicentepaulo@terra.com.br | M59: 45306 | N59: Pré-Classificado | O59: Documento Word (Pendrive) | R59: 111 | X59: 300 | Y59: 324 | AE59: =COUNT(Q59:AD59) -> 3 | AF59: =AVERAGE(Q59:AD59) -> 245 | AG59: =IF(AF59>=$AG$1,"APROVADO","REPROVADO") -> APROVADO
B60: 56 | C60: 056/23 | D60: Organização | E60: Lar São Vicente de Paulo | F60: Aquisição de camas motorizadas e colchões | G60: Eixo I: Promoção, Assistência e Desenvolvimento Social | H60: 259202 | I60: Descalvado/SP | J60: DRADS ARARAQUARA | K60: Vírginia Elaine da S. N. Guiguer | L60: larsao vicentepaulo@terra.com.br | M60: 45306 | N60: Pré-Classificado | O60: Documento Word (Pendrive) | R60: 108 | V60: 278 | W60: 39 | AF60: =AVERAGE(Q60:AD60) -> 141.66667 | AG60: =IF(AF60>=$AG$1,"APROVADO","REPROVADO") -> REPROVADO
B61: 57 | C61: 057/23 | D61: Prefeitura | E61: Municipal de Descalvado | F61: Idoso em Movimento | G61: Eixo VII: Cultura, Esporte, Turismo e Lazer | H61: 473200 | I61: Descalvado/SP | J61: DRADS ARARAQUARA | K61: Marly Colognesi Reschini | L61: social.apiai@gmail.com | M61: 45306 | N61: Classificado | Q61: 298 | R61: 82 | T61: 76 | AF61: =AVERAGE(Q61:AD61) -> 152 | AG61: =IF(AF61>=$AG$1,"APROVADO","REPROVADO") -> REPROVADO
B62: 58 | C62: 058/23 | D62: Prefeitura | E62: Municipal de Descalvado | F62: Sempre Sorrindo | G62: Eixo II: Sáude | H62: 39973 | I62: Descalvado/SP | J62: DRADS ARARAQUARA | K62: Marly Colognesi Reschini | L62: casadoidoso@descalvado.sp.gov.br | M62: 45306 | N62: Pré-Classificado | O62: Plano sem n° de páginas | Q62: 340 | R62: 103 | AC62: 340 | AE62: =COUNT(Q62:AD62) -> 3 | AF62: =AVERAGE(Q62:AD62) -> 261 | AG62: =IF(AF62>=$AG$1,"APROVADO","REPROVADO") -> APROVADO
B63: 59 | C63: 059/23 | D63: Prefeitura | E63: Municipal de Descalvado | F63: Ouvir Melhor | G63: Eixo II: Sáude | H63: 649980 | I63: Descalvado/SP | J63: DRADS ARARAQUARA | K63: Marly Colognesi Reschini | L63: casadoidoso@descalvado.sp.gov.br | M63: 45306 | N63: Pré-Classificado | O63: Plano sem n° de páginas | Q63: 340 | R63: 103 | V63: 340 | AE63: =COUNT(Q63:AD63) -> 3 | AF63: =AVERAGE(Q63:AD63) -> 261 | AG63: =IF(AF63>=$AG$1,"APROVADO","REPROVADO") -> APROVADO
B64: 60 | C64: 060/2 | D64: Prefeitura | E64: Municipal de Descalvado | F64: Plantando Semente da Longevidade | G64: Eixo II: Sáude | H64: 450000 | I64: Descalvado/SP | J64: DRADS ARARAQUARA | K64: Marly Colognesi Reschini | L64: casadoidoso@descalvado.sp.gov.br | M64: 45306 | N64: Pré-Classificado | O64: Plano sem n° de páginas | Q64: 324 | R64: 111 | W64: 340 | AE64: =COUNT(Q64:AD64) -> 3 | AF64: =AVERAGE(Q64:AD64) -> 258.33333 | AG64: =IF(AF64>=$AG$1,"APROVADO","REPROVADO") -> APROVADO
B65: 61 | C65: 061/23 | D65: Organização | E65: Lar São Vicente de Paulo | F65: Melhor Qualidade de Vida e Bem Estar dos Idosos Institucionalizados | G65: Eixo I: Promoção, Assistência e Desenvolvimento Social | H65: 50000 | I65: Barra Bonita/SP | J65: DRADS BAURU | K65: Adriana Vieira | L65: ispvbb@hotmail.com | M65: 45306 | N65: Pré-Classificado | O65: Plano de Trabalho sem rubricar | R65: 188 | X65: 340 | Y65: 340 | AE65: =COUNT(Q65:AD65) -> 3 | AF65: =AVERAGE(Q65:AD65) -> 289.33333 | AG65: =IF(AF65>=$AG$1,"APROVADO","REPROVADO") -> APROVADO
B66: 62 | C66: 062/23 | D66: Organização | E66: Centro Espírita Cristão (CEC)- Lar de Amparo a Velhice de Barra Bonita/SP | F66: CEC Bem Viver | G66: Eixo I: Promoção, Assistência e Desenvolvimento Social | H66: 34150 | I66: Barra Bonita/SP | J66: DRADS BAURU | K66: Luiz Pizzo | L66: ceclaramparo@gmail.com | M66: 45306 | N66: Pré-Classificado | O66: PDF sem assinar e rubricar | Q66: 340 | R66: 207 | AD66: 340 | AE66: =COUNT(Q66:AD66) -> 3 | AF66: =AVERAGE(Q66:AD66) -> 295.66667 | AG66: =IF(AF66>=$AG$1,"APROVADO","REPROVADO") -> APROVADO
B67: 63 | C67: 063/23 | D67: Organização | E67: Lar São Vicente de Paulo | F67: Investimento no Bem-Estar dos Idosos Institucionalizados | G67: Eixo I: Promoção, Assistência e Desenvolvimento Social | H67: 67450 | I67: Mineiros do Tietê/SP | J67: DRADS BAURU | K67: Vera Lúcia Giraldi Real | L67: asilosaovicente.mtiete@gmail.com | M67: 45306 | N67: Classificado | Q67: 340 | R67: 239 | S67: 235 | T67: 237 | AE67: =COUNT(Q67:AD67) -> 4 | AF67: =AVERAGE(Q67:AD67) -> 262.75 | AG67: =IF(AF67>=$AG$1,"APROVADO","REPROVADO") -> APROVADO
B68: 64 | C68: 064/23 | D68: Organização | E68: Assistencia Vicentina do Senhor Jesus | F68: Lar Doce Lar de Matão | G68: Eixo I: Promoção, Assistência e Desenvolvimento Social | H68: 100000 | I68: Matão/SP | J68: DRADS ARARAQUARA | K68: Marisa Albino | L68: larsaovicente@process.com.br | M68: 45306 | N68: Classificado | Q68: 340 | R68: 272 | S68: 271 | T68: 301 | AE68: =COUNT(Q68:AD68) -> 4 | AF68: =AVERAGE(Q68:AD68) -> 296 | AG68: =IF(AF68>=$AG$1,"APROVADO","REPROVADO") -> APROVADO
B69: 65 | C69: 065/23 | D69: Organização | E69: Associação Social Comunidade de Amor | F69: Construindo Laços: Um Caminho para o Bem Estar dos Idosos | G69: Eixo VII: Cultura, Esporte, Turismo e Lazer | H69: 208890 | I69: Sorocaba/SP | J69: DRADS SOROCABA | K69: Mariangela Geraldi | L69: projetoacolhe2@gmail.com | M69: 45306 | N69: Classificado | Q69: 299 | R69: 272 | S69: 281 | T69: 271 | AE69: =COUNT(Q69:AD69) -> 4 | AF69: =AVERAGE(Q69:AD69) -> 280.75 | AG69: =IF(AF69>=$AG$1,"APROVADO","REPROVADO") -> APROVADO
B70: 66 | C70: 066/23 | D70: Organização | E70: Casa do Vovô Feliz | F70: Velha história, Novos Retalhos – Resgatando Vidas | G70: Eixo VII: Cultura, Esporte, Turismo e Lazer | H70: 49800 | I70: Itapecerica da Serra/SP | J70: DRADS SPO EM OSASCO | K70: Teresa Takemura Kawasaki | L70: cvf@casadovovofeliz.or.br | M70: 45306 | N70: Pré-Classificado | O70: Documento Word (Pendrive) | R70: 191 | X70: 321 | Y70: 340 | AE70: =COUNT(Q70:AD70) -> 3 | AF70: =AVERAGE(Q70:AD70) -> 284 | AG70: =IF(AF70>=$AG$1,"APROVADO","REPROVADO") -> APROVADO
B71: 67 | C71: 067/23 | D71: Prefeitura | E71: Municipal de Cassia dos Coqueiros | F71: Saber Viver na Melhor Idade | G71: Eixo I: Promoção, Assistência e Desenvolvimento Social | H71: 188300 | I71: Cássia dos Coqueiros/SP | J71: DRADS RIBEIRÃO PRETO | K71: Silvio Santos dos Reis Faria | L71: casadoidoso@descalvado.sp.gov.br | M71: 45306 | N71: Pré-Classificado | O71: Falta de Informação do envelope | Q71: 235 | V71: 213 | W71: 212 | AE71: =COUNT(Q71:AD71) -> 3 | AF71: =AVERAGE(Q71:AD71) -> 220 | AG71: =IF(AF71>=$AG$1,"APROVADO","REPROVADO") -> APROVADO
B72: 68 | C72: 068/2 | D72: Organização | E72: Casa de Oração Amor Luz | F72: Serviço de Convivência e Fortalecimento de Vínculos — SCFV para Pessoas Idosas, com idade igual ou acima de 60 anos | G72: Eixo VII: Cultura, Esporte, Turismo e Lazer | H72: 68680 | I72: São José dos Campos/SP | J72: DRADS VALE DO PARAÍBA EM SÃO JOSÉ DOS CAMPOS | K72: Maria Cristina Sundfeld | L72: Coalsocial@gmail.com | M72: 45306 | N72: Classificado | Q72: 276 | R72: 188 | AB72: 269 | AE72: =COUNT(Q72:AD72) -> 3 | AF72: =AVERAGE(Q72:AD72) -> 244.33333 | AG72: =IF(AF72>=$AG$1,"APROVADO","REPROVADO") -> APROVADO
B73: 69 | C73: 069/23 | D73: Organização | E73: Lar dos Velhinhos São Vicente de Paulo | F73: Renovar | G73: Eixo I: Promoção, Assistência e Desenvolvimento Social | H73: 44934 | I73: Urânia/SP | J73: DRADS FERNANDÓPOLIS | K73: Zélia Souza Silva | L73: lardos velhinhos1@hotmail.com | M73: 45306 | N73: Pré-Classificado | O73: Documento Word (Pendrive) | P73: 3 planos de trabalho no mesmo pendrive | R73: 212 | X73: 307 | Y73: 298 | AE73: =COUNT(Q73:AD73) -> 3 | AF73: =AVERAGE(Q73:AD73) -> 272.33333 | AG73: =IF(AF73>=$AG$1,"APROVADO","REPROVADO") -> APROVADO
B74: 70 | C74: 070/23 | D74: Organização | E74: Lar dos Velhinhos São Vicente de Paulo | F74: Idoso Jovem | G74: Eixo I: Promoção, Assistência e Desenvolvimento Social | H74: 38337 | I74: Urânia/SP | J74: DRADS FERNANDÓPOLIS | K74: Zélia Souza Silva | L74: lardos velhinhos1@hotmail.com | M74: 45306 | N74: Desclassificado | O74: Sem Pendrive | AF74: =AVERAGE(Q74:AD74) -> #DIV/0! | AG74: =IF(AF74>=$AG$1,"APROVADO","REPROVADO") -> #DIV/0!
B75: 71 | C75: 071/23 | D75: Organização | E75: Lar dos Velhinhos São Vicente de Paulo | F75: Meu Quarto Meus Sonhos | G75: Eixo I: Promoção, Assistência e Desenvolvimento Social | H75: 78212 | I75: Urânia/SP | J75: DRADS FERNANDÓPOLIS | K75: Zélia Souza Silva | L75: lardos velhinhos1@hotmail.com | M75: 45306 | N75: Desclassificado | O75: Sem Pendrive | AF75: =AVERAGE(Q75:AD75) -> #DIV/0! | AG75: =IF(AF75>=$AG$1,"APROVADO","REPROVADO") -> #DIV/0!
B76: 72 | C76: 072/23 | D76: Organização | E76: Lar São Francisco de Assis Asilo | F76: Centro de Convivio da Pessoa Idosa | G76: Eixo I: Promoção, Assistência e Desenvolvimento Social | H76: 360000 | I76: Araraquara/SP | J76: DRADS ARARAQUARA | K76: Maria Elena Baptista | L76: azilo@uol.com.br | M76: 45306 | N76: Classificado | Q76: 324 | R76: 189 | S76: 274 | T76: 230 | AE76: =COUNT(Q76:AD76) -> 4 | AF76: =AVERAGE(Q76:AD76) -> 254.25 | AG76: =IF(AF76>=$AG$1,"APROVADO","REPROVADO") -> APROVADO
B77: 73 | C77: 073/23 | D77: Organização | E77: Registro Conselho Municipal - ARTGYM - LTDA | F77: Estímulos da Sinapse Neurológica para a Saúde física e Mental, por meio da Dança e do Movimento Ginástico Sistematizados para a Melhor Idade de Araraquara-SP | G77: Eixo VII: Cultura, Esporte, Turismo e Lazer | H77: 390000 | I77: Araraquara/SP | J77: DRADS ARARAQUARA | K77: Henrique Sanioto | L77: professorsanioto@gmail.com | M77: 45306 | N77: Reprovado | O77: Nota 0 no item 1 - CNPJ de Sociedade Empresaria Limitada (Jeverson) e ideam ao item 1 obs da Erica | R77: 34 | AB77: 0 | AF77: =AVERAGE(Q77:AD77) -> 17 | AG77: =IF(AF77>=$AG$1,"APROVADO","REPROVADO") -> REPROVADO
B78: 74 | C78: 074/23 | D78: Prefeitura | E78: Municipal D'Oeste | F78: Bem Viver | G78: Eixo I: Promoção, Assistência e Desenvolvimento Social | H78: 133070 | I78: Aparecida D'Oeste/SP | J78: DRADS FERNANDÓPOLIS | K78: Sandra Regina Penariol | L78: adm@pmaparecidadoeste.sp.gov.br | M78: 45306 | N78: Classificado | Q78: 320 | R78: 189 | S78: 252 | T78: 215 | AE78: =COUNT(Q78:AD78) -> 4 | AF78: =AVERAGE(Q78:AD78) -> 244 | AG78: =IF(AF78>=$AG$1,"APROVADO","REPROVADO") -> APROVADO
B79: 75 | C79: 075/23 | D79: Organização | E79: Associação Centros Etievan | F79: Repórter 60+ | G79: Eixo III: Educação Eixo VII: (Cultura, Esporte, Turismo e Lazer | H79: 620100 | I79: Guapiaçu/SP | J79: DRADS SÃO JOSÉ DO RIO PRETO | K79: Isabel Dsávila | L79: coordenacao@centrosetievan.com.br | M79: 45306 | N79: Classificado | P79: Verificar Comissão: plano de trabalho com 2 eixos, no envelope consta apenas 1. | Q79: 330 | R79: 187 | S79: 281 | AE79: =COUNT(Q79:AD79) -> 3 | AF79: =AVERAGE(Q79:AD79) -> 266 | AG79: =IF(AF79>=$AG$1,"APROVADO","REPROVADO") -> APROVADO
B80: 76 | C80: 076/23 | D80: Organização | E80: Lar São Vicente Obra Padre Donizetti | F80: Qualificação de Equipamentos e Ambientes Lar São Vicente - Obra Padre Donizetti | G80: Eixo I: Promoção, Assistência e Desenvolvimento Social | H80: 14757 | I80: Tambáu/SP | J80: DRADS MOGIANA EM SÃO JOÃO DA BOA VISTA | K80: Urbano Antoninho Giorgetti | L80: obrapdonizetti@hotmail.com | M80: 45307 | N80: Pré-Classificado | O80: Plano e Pendrive OK | Q80: 340 | R80: 245 | AD80: 340 | AE80: =COUNT(Q80:AD80) -> 3 | AF80: =AVERAGE(Q80:AD80) -> 308.33333 | AG80: =IF(AF80>=$AG$1,"APROVADO","REPROVADO") -> APROVADO
B81: 77 | C81: 077/23 | D81: Organização | E81: Serviço de Obras Sociais de Tambáu-S.O.S | F81: Aconchego | G81: Eixo I: Promoção, Assistência e Desenvolvimento Social | H81: 240000 | I81: Tambáu/SP | J81: DRADS MOGIANA EM SÃO JOÃO DA BOA VISTA | K81: Jose Luiz Furtado | L81: sostambau@strnet.com.br | M81: 45307 | N81: Classificado | Q81: 325 | R81: 184 | S81: 260 | T81: 263 | AE81: =COUNT(Q81:AD81) -> 4 | AF81: =AVERAGE(Q81:AD81) -> 258 | AG81: =IF(AF81>=$AG$1,"APROVADO","REPROVADO") -> APROVADO
B82: 78 | C82: 078/23 | D82: Organização | E82: Associação Franciscana de Solidariedade | F82: Bem Viver - Envelhecer com Qualidade em São Paulo | G82: Eixo VII: Cultura, Esporte, Turismo e Lazer | H82: 764968.68 | I82: São Paulo/SP | J82: DRADS CAPITAL EM SÃO PAULO | K82: Regina Pessoa | L82: Projetos@sefras.org.br | M82: 45307 | N82: Pré-Classificado | O82: Plano sem rubricar | Q82: 324 | R82: 256 | AD82: 340 | AE82: =COUNT(Q82:AD82) -> 3 | AF82: =AVERAGE(Q82:AD82) -> 306.66667 | AG82: =IF(AF82>=$AG$1,"APROVADO","REPROVADO") -> APROVADO
B83: 79 | C83: 079/23 | D83: Organização | E83: Associação Franciscana de Solidariedade | F83: Vida Plena- Envelhecer com Qualidade | G83: Eixo VII: Cultura, Esporte, Turismo e Lazer | H83: 396760.14 | I83: Pindamonhangaba/SP | J83: DRADS VALE DO PARAÍBA EM SÃO JOSÉ DOS CAMPOS | K83: Regina Pessoa | L83: Projetos@sefras.org.br | M83: 45307 | N83: Pré-Classificado | O83: Plano sem rubricar | Q83: 308 | R83: 256 | AD83: 273 | AE83: =COUNT(Q83:AD83) -> 3 | AF83: =AVERAGE(Q83:AD83) -> 279 | AG83: =IF(AF83>=$AG$1,"APROVADO","REPROVADO") -> APROVADO
B84: 80 | C84: 080/23 | D84: Organização | E84: Associação Franciscana de Solidariedade | F84: Novos Tempos - Envelhecer com Qualidade em Mogi das Cruzes | G84: Eixo VII: Cultura, Esporte, Turismo e Lazer | H84: 579789.01 | I84: Pindamonhangaba/SP | J84: DRADS VALE DO PARAÍBA EM SÃO JOSÉ DOS CAMPOS | K84: Regina Pessoa | L84: Projetos@sefras.org.br | M84: 45307 | N84: Pré-Classificado | O84: Plano sem rubricar | Q84: 315 | R84: 225 | AD84: 340 | AE84: =COUNT(Q84:AD84) -> 3 | AF84: =AVERAGE(Q84:AD84) -> 293.33333 | AG84: =IF(AF84>=$AG$1,"APROVADO","REPROVADO") -> APROVADO
B85: 81 | C85: 081/23 | D85: Organização | E85: Vila Vicentina em Brotas | F85: Entreterimento aos Idosos (Televisor de 85") | G85: Eixo I: Promoção, Assistência e Desenvolvimento Social | H85: 10000 | I85: Brotas/SP | J85: DRADS PIRACICABA | K85: Neuza Maria Pascoalotti Berto | L85: vilavicentinoembrotas@outlook.com | M85: 45307 | N85: Classificado | P85: Pendrive com 3 Projetos | Q85: 340 | S85: 274 | T85: 287 | AE85: =COUNT(Q85:AD85) -> 3 | AF85: =AVERAGE(Q85:AD85) -> 300.33333 | AG85: =IF(AF85>=$AG$1,"APROVADO","REPROVADO") -> APROVADO
B86: 82 | C86: 082/23 | D86: Organização | E86: Vila Vicentina em Brotas | F86: Bem Estar Social aos Idosos (mesas e Cadeiras) | G86: Eixo I: Promoção, Assistência e Desenvolvimento Social | H86: 10000 | I86: Brotas/SP | J86: DRADS PIRACICABA | K86: Neuza Maria Pascoalotti Berto | L86: vilavicentinoembrotas@outlook.com | M86: 45307 | N86: Desclassificado | O86: Sem Pendrive | AF86: =AVERAGE(Q86:AD86) -> #DIV/0! | AG86: =IF(AF86>=$AG$1,"APROVADO","REPROVADO") -> #DIV/0!
B87: 83 | C87: 083/23 | D87: Organização | E87: Vila Vicentina em Brotas | F87: Aconchego aos Idosos (Poltrona do Papai Reclinável) | G87: Eixo I: Promoção, Assistência e Desenvolvimento Social | H87: 10000 | I87: Brotas/SP | J87: DRADS PIRACICABA | K87: Neuza Maria Pascoalotti Berto | L87: vilavicentinoembrotas@outlook.com | M87: 45307 | N87: Desclassificado | O87: Sem Pendrive | AF87: =AVERAGE(Q87:AD87) -> #DIV/0! | AG87: =IF(AF87>=$AG$1,"APROVADO","REPROVADO") -> #DIV/0!
B88: 84 | C88: 084/23 | D88: Organização | E88: Instituto Acorde | F88: Centro Dia – Um novo olhar | G88: Eixo IV: Trabalho e Previdência Social | H88: 180000 | I88: São Carlos/SP | J88: DRADS ARARAQUARA | K88: Cleonice Lavandoski Amato | L88: acorde@institutoacorde.org.br | M88: 45307 | N88: Pré-Classificado | O88: Documento Word (Pendrive) | R88: 175 | X88: 297 | Y88: 297 | AE88: =COUNT(Q88:AD88) -> 3 | AF88: =AVERAGE(Q88:AD88) -> 256.33333 | AG88: =IF(AF88>=$AG$1,"APROVADO","REPROVADO") -> APROVADO
B89: 85 | C89: 085/23 | D89: Organização | E89: Associação Cultural Artistica Cine favela | F89: Inclusão Digital de Pessoas Idosas no Cine Favela Heliópolis | G89: Eixo I: Promoção, Assistência e Desenvolvimento Social | H89: 1111410.1 | I89: São Paulo/SP | J89: DRADS CAPITAL EM SÃO PAULO | K89: Geneci Ledo de Tulio | L89: cinefavela@gmail.com | M89: 45307 | N89: Pré-Classificado | O89: Falta de Informação do envelope | P89: Plano de Trabalho sem n° de páginas | Q89: 317 | S89: 239 | T89: 266 | AE89: =COUNT(Q89:AD89) -> 3 | AF89: =AVERAGE(Q89:AD89) -> 274 | AG89: =IF(AF89>=$AG$1,"APROVADO","REPROVADO") -> APROVADO
B90: 86 | C90: 086/23 | D90: Organização | E90: Grupo de Apoio dona Benedita | F90: Mantendo Vivos Nossos Sorrisos | G90: Eixo I: Promoção, Assistência e Desenvolvimento Social | H90: 102600 | I90: Sete Barras | J90: DRADS VALE DO RIBEIRA EM REGISTRO | K90: Micaela Oliveira | L90: casaamigosdasb@gmail.com | M90: 45307 | N90: Classificado | Q90: 309 | R90: 203 | S90: 242 | AE90: =COUNT(Q90:AD90) -> 3 | AF90: =AVERAGE(Q90:AD90) -> 251.33333 | AG90: =IF(AF90>=$AG$1,"APROVADO","REPROVADO") -> APROVADO
B91: 87 | C91: 087/23 | D91: Organização | E91: Lar dos Velhinhos da Sociedade São Vicente de Paulo | F91: Vida Plena - Cuidando do Amanhã | G91: Eixo I: Promoção, Assistência e Desenvolvimento Social | H91: 48136.8 | I91: Santo Antonio da Alegria/SP | J91: DRADS RIBEIRÃO PRETO | K91: Luiz Ricardo dos Santos | L91: lardosvelhinhossssvp2015@hotmail.com | M91: 45307 | N91: Pré-Classificado | O91: Falta de Informação do envelope | P91: Plano e Pendrive OK (verificar o formato do Plano de Trabalho) | Q91: 305 | R91: 191 | AD91: 340 | AE91: =COUNT(Q91:AD91) -> 3 | AF91: =AVERAGE(Q91:AD91) -> 278.66667 | AG91: =IF(AF91>=$AG$1,"APROVADO","REPROVADO") -> APROVADO
B92: 88 | C92: 088/23 | D92: Prefeitura | E92: Municipal de Itapira | F92: Assistência Fisioterapêutica Domiciliar em Idosos Acamadoa | G92: - | H92: 394820 | I92: Itapira/SP | J92: DRADS MOGIANA EM SÃO JOÃO DA BOA VISTA | K92: Márcia de Jesus de Oliveira | L92: adm@pmaparecidadoeste.sp.gov.br | M92: 45307 | N92: Reprovado | O92: Aquisição de Veiculo | AF92: =AVERAGE(Q92:AD92) -> #DIV/0! | AG92: =IF(AF92>=$AG$1,"APROVADO","REPROVADO") -> #DIV/0!
B93: 89 | C93: 089/23 | D93: Prefeitura | E93: Municipal Santa Cruz da Esperança | F93: Trilhas das Memorias | G93: Eixo VII: Cultura, Esporte, Turismo e Lazer | H93: 434000 | I93: Santa Cruz da Esperança/SP | J93: DRADS RIBEIRÃO PRETO | K93: Celia Cristina Cestari | L93: gabinetedoprefeito@itapira.sp.gov.br | M93: 45307 | N93: Pré-Classificado | O93: PDF sem assinatura e rubrica | Q93: 259 | V93: 258 | W93: 220 | AE93: =COUNT(Q93:AD93) -> 3 | AF93: =AVERAGE(Q93:AD93) -> 245.66667 | AG93: =IF(AF93>=$AG$1,"APROVADO","REPROVADO") -> APROVADO
B94: 90 | C94: 090/23 | D94: Organização | E94: Associação Cultural e Social do Idoso Criança e Adolescente | F94: Exposição do Samba - Velha Guarda | G94: Eixo VII: Cultura, Esporte, Turismo e Lazer | H94: 630000 | I94: São Paulo/SP | J94: DRADS CAPITAL EM SÃO PAULO | K94: Emerson de Godoy Costas dos Santos | L94: coordenacaoacsica@hotmail.com | M94: 45307 | N94: Desclassificado | O94: Plano de Trabalho sem Rubricar | AF94: =AVERAGE(Q94:AD94) -> #DIV/0! | AG94: =IF(AF94>=$AG$1,"APROVADO","REPROVADO") -> #DIV/0!
B95: 91 | C95: 091/23 | D95: Organização | E95: Associação Beneficiente Bom Jesus | F95: Viver Bem | G95: Eixo VII: Cultura, Esporte, Turismo e Lazer | H95: 50000 | I95: Pilar do Sul/SP | J95: DRADS SOROCABA | K95: Sergio Luis Ribeiro | L95: larbomjesus.pilardosul@gmail.com | M95: 45307 | N95: Desclassificado | O95: Plano de Trabalho sem Rubricar | AF95: =AVERAGE(Q95:AD95) -> #DIV/0! | AG95: =IF(AF95>=$AG$1,"APROVADO","REPROVADO") -> #DIV/0!
B96: 92 | C96: 092/23 | D96: Organização | E96: Projeto Gente Nova | F96: Envelhecência: Envelhecer com Dignidade | G96: Eixo I: Promoção, Assistência e Desenvolvimento Social | H96: 500000 | I96: Campinas/SP | J96: DRADS CAMPINAS | K96: Claudio Raizaro | L96: progen@progen.gor.vbr | M96: 45307 | N96: Classificado | Q96: 295 | R96: 175 | S96: 241 | AE96: =COUNT(Q96:AD96) -> 3 | AF96: =AVERAGE(Q96:AD96) -> 237 | AG96: =IF(AF96>=$AG$1,"APROVADO","REPROVADO") -> APROVADO
B97: 93 | C97: 093/23 | D97: Organização | E97: Associação Comunidade em Ação êxodo | F97: Sênior healt: espaço de práticas integrativas | G97: Eixo VII: Cultura, Esporte, Turismo e Lazer | H97: 88496 | I97: Bauru/SP | J97: DRADS BAURU | K97: Arianni Pereira Milano | L97: instituicaoacae@yahoo.com.br | M97: 45307 | N97: Pré-Classificado | O97: PDF sem assinar e rubricar | Q97: 313 | R97: 239 | AD97: 340 | AE97: =COUNT(Q97:AD97) -> 3 | AF97: =AVERAGE(Q97:AD97) -> 297.33333 | AG97: =IF(AF97>=$AG$1,"APROVADO","REPROVADO") -> APROVADO
B98: 94 | C98: 094/23 | D98: Organização | E98: Caritas Diocesana de Bauru | F98: Saúde na Melhor Idade | G98: Eixo VII: Cultura, Esporte, Turismo e Lazer | H98: 60000 | I98: Bauru/SP | J98: DRADS BAURU | K98: Osvaldo Aparecido Hudinik | L98: coordenacao@caritasbauru.org.br | M98: 45307 | N98: Pré-Classificado | O98: Falta de Informação do envelope | P98: Plano de Trabalho sem n° de páginas | Q98: 310 | S98: 248 | T98: 262 | AE98: =COUNT(Q98:AD98) -> 3 | AF98: =AVERAGE(Q98:AD98) -> 273.33333 | AG98: =IF(AF98>=$AG$1,"APROVADO","REPROVADO") -> APROVADO
B99: 95 | C99: 095/23 | D99: Organização | E99: Associação Bauruense de Apoio e Assistência ao Renal Crônico - ABREC | F99: Apoio e Cuidado para Viver Melhor | G99: Eixo I: Promoção, Assistência e Desenvolvimento Social | H99: 40000 | I99: Bauru/SP | J99: DRADS BAURU | K99: Daiane Cordeiro de Mattos Souza | L99: abrec.seid@gmail.com | M99: 45307 | N99: Classificado | Q99: 273 | R99: 275 | S99: 270 | AE99: =COUNT(Q99:AD99) -> 3 | AF99: =AVERAGE(Q99:AD99) -> 272.66667 | AG99: =IF(AF99>=$AG$1,"APROVADO","REPROVADO") -> APROVADO
B100: 96 | C100: 096/23 | D100: Organização | E100: Rede do Câncer de Lençois Paulista | F100: Projetos que contemplem o fornecimento de próteses, órteses e outros recursos relativos ao tratamento, habilitação ou reabilitação de pessoas idosas, conforme artigo 15, 2º da lei federal nº 10.741/2003 e suas alterações | G100: Eixo II: Sáude | H100: 73150 | I100: Lençois Paulista/SP | J100: DRADS BAURU | K100: Angela Silvana Fermino | L100: rededocancerrlp@Gmail.com | M100: 45307 | N100: Classificado | Q100: 340 | R100: 265 | S100: 264 | AE100: =COUNT(Q100:AD100) -> 3 | AF100: =AVERAGE(Q100:AD100) -> 289.66667 | AG100: =IF(AF100>=$AG$1,"APROVADO","REPROVADO") -> APROVADO
...

Sheet Consolidada
AG1: 204
B2: CONSELHO ESTADUAL DO IDOSO Rua Boa Vista, 170 - CEP 01204-001 - São Paulo-SP Fone 11-2763-8122/2763-8035 cei@desenvolvimentosocial.sp.gov.br
B3: ORGANIZAÇÕES SOCIAIS
C4: Protocolo | D4: OSC/Prefeitura | E4: NOME DO PROPONENTE | F4: NOME DO PROJETO | G4: EIXO | H4: VALOR TOTAL DO PROJETO | I4: MUNICÍPIO | J4: DRADS | K4: Responsável - OSC | L4: EMAIL | M4: ENTREGUE DIA | N4: ETAPA da Análise | O4: PENDÊNCIA | P4: OBS | Q4: NOTA Gilberto | R4: NOTA Erica | S4: NOTA Enizal | T4: NOTA Walkyria | U4: NOTA Elisete | V4: NOTA Adriano | W4: NOTA Paulo Albano | X4: NOTA Alexandra | Y4: NOTA Priscila | Z4: NOTA Leila | AA4: NOTA Vanise | AB4: NOTA Jeverson | AC4: NOTA Cristiane | AD4: NOTA Márcio | AF4: Média | AG4: RESULTADO FINAL
B5: 1 | C5: 001/23 | D5: Organização | E5: Associação São Joaquim de Apoio à Maturidade | F5: Centro de Convivência Casa Azul | G5: Eixo I: Promoção, Assistência e Desenvolvimento Social | H5: 370460.32 | I5: Carapicuíba/SP | J5: DRADS SPO EM OSASCO | K5: Claudia Regina Ferreira | L5: saojoaquim@saojoaquim.org.br | M5: 45279 | N5: Classificado | Q5: 318 | S5: 265 | T5: 247 | AE5: =COUNT(Q5:AD5) -> 3 | AF5: =AVERAGE(Q5:AD5) -> 276.66667 | AG5: =IF(AF5>=$AG$1,"APROVADO","REPROVADO") -> APROVADO
B6: 2 | C6: 002/23 | D6: Organização | E6: Irmandade Padre Emanoel | F6: CriaMais - Sáude e Arte para Pessoa Idosa | G6: - | H6: 45000 | I6: Palmeira d'Oeste/SP | J6: DRADS FERNANDÓPOLIS | K6: Ludimila Bartolomeu Rodrigues | L6: lardosidosdedalas@hotmail.com | M6: 45313 | N6: Classificado | Q6: 297 | Z6: 310 | AC6: 327 | AE6: =COUNT(Q6:AD6) -> 3 | AF6: =AVERAGE(Q6:AD6) -> 311.33333 | AG6: =IF(AF6>=$AG$1,"APROVADO","REPROVADO") -> APROVADO
B7: 3 | C7: 003/23 | D7: Prefeitura | E7: Municipal de Palmeira D'Oeste | F7: Idoso 100% Ativo – Hidroginastica | G7: Eixo I: Promoção, Assistência e Desenvolvimento Social | H7: 84000 | I7: Palmeira D'Oeste | J7: DRADS FERNANDÓPOLIS | K7: Lucinele Gabaldi Bertolassi | L7: pmpalmeira@ig.com.br | M7: 45282 | N7: Pré-Classificado | O7: Plano de trabalho sem n° de páginas | Q7: 321 | R7: 157 | AB7: 325 | AE7: =COUNT(Q7:AD7) -> 3 | AF7: =AVERAGE(Q7:AD7) -> 267.66667 | AG7: =IF(AF7>=$AG$1,"APROVADO","REPROVADO") -> APROVADO
B8: 4 | C8: 004/23 | D8: Organização | E8: Santa Casa de Misericordia de Presidente Prudente | F8: Tratamento Oftalmológico | G8: Eixo II: Sáude | H8: 1000000 | I8: Presidente Prudente/SP | J8: DRADS ALTA SOROCABANA EM PRESIDENTE PRUDENTE | K8: William Boscoli Ribeiro | L8: analista.adm@santacasaprudente.org.br | M8: 45281 | N8: Pré-Classificado | O8: Plano de Trabalho sem n° de páginas | Q8: 312 | S8: 275 | T8: 299 | AE8: =COUNT(Q8:AD8) -> 3 | AF8: =AVERAGE(Q8:AD8) -> 295.33333 | AG8: =IF(AF8>=$AG$1,"APROVADO","REPROVADO") -> APROVADO
B9: 5 | C9: 005/23 | D9: Organização | E9: Associação Santo Agostinho -ASA | F9: Saber Mais, Viver Mais | G9: Eixo III: Educação | H9: 341605 | I9: São Paulo/SP | J9: DRADS CAPITAL EM SÃO PAULO | K9: Thais Certain | L9: thais.certain@asatransforma.org.br | M9: 45288 | N9: Classificado | Q9: 272 | S9: 269 | T9: 290 | AE9: =COUNT(Q9:AD9) -> 3 | AF9: =AVERAGE(Q9:AD9) -> 277 | AG9: =IF(AF9>=$AG$1,"APROVADO","REPROVADO") -> APROVADO
B10: 6 | C10: 006/23 | D10: Organização | E10: Congregação Israelita Paulista | F10: Núcleo de Convivência da Maturidade | G10: Eixo I: Promoção, Assistência e Desenvolvimento Social | H10: 523070 | I10: São Paulo/SP | J10: DRADS CAPITAL EM SÃO PAULO | K10: Laura Feldman | L10: acaosocial@cip.org.br | M10: 45288 | N10: Desclassificado | O10: Plano de Trabalho sem Rubricar | AF10: =AVERAGE(Q10:AD10) -> #DIV/0! | AG10: =IF(AF10>=$AG$1,"APROVADO","REPROVADO") -> #DIV/0!
B11: 7 | C11: 007/23 | D11: Organização | E11: Associação de Apoio ao Paciente Renal Cronico e Transplantado -Carim | F11: Saúde e Movimento | G11: - | H11: 364980 | I11: Presidente Prudente/SP | J11: DRADS ALTA SOROCABANA EM PRESIDENTE PRUDENTE | K11: Sumaia Cristina Zahra Zakir Pereira | L11: carimprudente@yahoo.com. br | M11: 45289 | N11: Pré-Classificado | O11: Falta de Informação do envelope | P11: Doc Word | Q11: 340 | S11: 245 | T11: 290 | AE11: =COUNT(Q11:AD11) -> 3 | AF11: =AVERAGE(Q11:AD11) -> 291.66667 | AG11: =IF(AF11>=$AG$1,"APROVADO","REPROVADO") -> APROVADO
B12: 8 | C12: 008/23 | D12: Organização | E12: Lar Fraterno da Acácia | F12: Aquisição de cadeira de rodas, cadeira de banho, cama, guarda roupa e utensílios para cozinha | G12: Eixo I: Promoção, Assistência e Desenvolvimento Social | H12: 250640 | I12: Jacareí/SP | J12: DRADS VALE DO PARAÍBA EM SÃO JOSÉ DOS CAMPOS | K12: Flávia Aparecida Gonçalves Nascimento | L12: servicosocial.Iarfa@gmail.com | M12: 45296 | N12: Pré-Classificado | O12: Documento Word (Pendrive) | R12: 170 | V12: 302 | W12: 285 | AE12: =COUNT(Q12:AD12) -> 3 | AF12: =AVERAGE(Q12:AD12) -> 252.33333 | AG12: =IF(AF12>=$AG$1,"APROVADO","REPROVADO") -> APROVADO
B13: 9 | C13: 009/23 | D13: Organização | E13: Lar Fraterno da Acácia | F13: Adequação, Acessibilidade | G13: Eixo I: Promoção, Assistência e Desenvolvimento Social | H13: 1288900 | I13: Jacareí/SP | J13: DRADS VALE DO PARAÍBA EM SÃO JOSÉ DOS CAMPOS | K13: Flávia Aparecida Gonçalves Nascimento | L13: servicosocial.Iarfa@gmail.com | M13: 45296 | N13: Pré-Classificado | O13: Documento Word (Pendrive) | R13: 164 | X13: 330 | Y13: 340 | AE13: =COUNT(Q13:AD13) -> 3 | AF13: =AVERAGE(Q13:AD13) -> 278 | AG13: =IF(AF13>=$AG$1,"APROVADO","REPROVADO") -> APROVADO
B14: 10 | C14: 010/23 | D14: Organização | E14: Lar Fraterno da Acácia | F14: Custeio | G14: Eixo I: Promoção, Assistência e Desenvolvimento Social | H14: 1086393.6 | I14: Jacareí/SP | J14: DRADS VALE DO PARAÍBA EM SÃO JOSÉ DOS CAMPOS | K14: Flávia Aparecida Gonçalves Nascimento | L14: z | M14: 45296 | N14: Pré-Classificado | O14: Documento Word (Pendrive) | R14: 146 | V14: 340 | W14: 330 | AE14: =COUNT(Q14:AD14) -> 3 | AF14: =AVERAGE(Q14:AD14) -> 272 | AG14: =IF(AF14>=$AG$1,"APROVADO","REPROVADO") -> APROVADO
B15: 11 | C15: 011/23 | D15: Organização | E15: Obra Social e Assistencial São Lucas | F15: O amor Exige Cuidado | G15: Eixo VII: Cultura, Esporte, Turismo e Lazer | H15: 193281.12 | I15: São José dos Campos/SP | J15: DRADS VALE DO PARAÍBA EM SÃO JOSÉ DOS CAMPOS | K15: Nelcira Rosa da Silva Lima | L15: obrasaolucas@terra.com.br | M15: 45296 | N15: Classificado | Q15: 312 | S15: 237 | T15: 174 | AE15: =COUNT(Q15:AD15) -> 3 | AF15: =AVERAGE(Q15:AD15) -> 241 | AG15: =IF(AF15>=$AG$1,"APROVADO","REPROVADO") -> APROVADO
B16: 12 | C16: 012/23 | D16: Prefeitura | E16: Municipal de Boraceia | F16: Projeto Vida Ativa na Melhor Idade | G16: Eixo I: Promoção, Assistência e Desenvolvimento Social | H16: 244231.32 | I16: Boraceia | J16: DRADS BAURU | K16: Vania de Souza Melo Carlini | L16: orgestorp@hotmail.com | M16: 45296 | N16: Pré-Classificado | O16: Documentos Word (Pendrive) | Q16: 329 | V16: 340 | W16: 323 | AE16: =COUNT(Q16:AD16) -> 3 | AF16: =AVERAGE(Q16:AD16) -> 330.66667 | AG16: =IF(AF16>=$AG$1,"APROVADO","REPROVADO") -> APROVADO
B17: 13 | C17: 013/23 | D17: Organização | E17: Lar dos Velhinhos Papa João XXIII | F17: Cozinha | G17: Eixo I: Promoção, Assistência e Desenvolvimento Social | H17: 69808.08 | I17: Salto Grande/SP | J17: DRADS AVARÉ | K17: Bruna Fernandes Araujo | L17: asilosaltogrande@hotmail.com | M17: 45299 | N17: Classificado | Q17: 329 | S17: 236 | T17: 200 | AE17: =COUNT(Q17:AD17) -> 3 | AF17: =AVERAGE(Q17:AD17) -> 255 | AG17: =IF(AF17>=$AG$1,"APROVADO","REPROVADO") -> APROVADO
B18: 14 | C18: 014/23 | D18: Organização | E18: Lar do Velhinhos Papa João XXIII | F18: Lavanderia | G18: Eixo I: Promoção, Assistência e Desenvolvimento Social | H18: 275400 | I18: Salto Grande/SP | J18: DRADS AVARÉ | K18: Bruna Fernandes Araujo | L18: asiloaltogrande@hotmail.com | M18: 45321 | N18: Classificado | P18: Verificar se não são repetidos (Protocolo 014 e 348/23) | Q18: 288 | R18: 118 | T18: 177 | AE18: =COUNT(Q18:AD18) -> 3 | AF18: =AVERAGE(Q18:AD18) -> 194.33333 | AG18: =IF(AF18>=$AG$1,"APROVADO","REPROVADO") -> REPROVADO
B19: 15 | C19: 015/23 | D19: Organização | E19: Associação Lar dos Idosos de Alvares Machado | F19: EQUIPAR II | G19: Eixo I: Promoção, Assistência e Desenvolvimento Social | H19: 40000 | I19: Álvares Machado/SP | J19: DRADS ALTA SOROCABANA EM PRESIDENTE PRUDENTE | K19: Gislaine Girotti Zanoni | L19: lardosidososdam@yahoo.com.br | M19: 45300 | N19: Classificado | Q19: 340 | S19: 285 | T19: 300 | AE19: =COUNT(Q19:AD19) -> 3 | AF19: =AVERAGE(Q19:AD19) -> 308.33333 | AG19: =IF(AF19>=$AG$1,"APROVADO","REPROVADO") -> APROVADO
B20: 16 | C20: 016/23 | D20: Organização | E20: ACBNIBRA Associação Cultural, Beneficiente e Esportiva Nipo Brasileiro de Jacupiranga | F20: Projeto Jacupiranga Melhor Idade | G20: Eixo VII: Cultura, Esporte, Turismo e Lazer | H20: 29714 | I20: Jacupiranga/SP | J20: DRADS VALE DO RIBEIRA EM REGISTRO | K20: SR. Angelo | L20: saitto@terra.combr | M20: 45300 | N20: Pré-Classificado | O20: Documento Word (Pendrive) | Q20: 340 | R20: 209 | AD20: 340 | AE20: =COUNT(Q20:AD20) -> 3 | AF20: =AVERAGE(Q20:AD20) -> 296.33333 | AG20: =IF(AF20>=$AG$1,"APROVADO","REPROVADO") -> APROVADO
B21: 17 | C21: 017/23 | D21: Organização | E21: União Espírita Cachoerense | F21: Energia do Bem | G21: Eixo I: Promoção, Assistência e Desenvolvimento Social | H21: 91857.47 | I21: Cachoeira Paulista/SP | J21: DRADS VALE DO PARAÍBA EM SÃO JOSÉ DOS CAMPOS | K21: DéboraFerreira Comonian | L21: u.e.c.1918@gmail.com | M21: 45301 | N21: Classificado | Q21: 340 | S21: 253 | T21: 242 | AE21: =COUNT(Q21:AD21) -> 3 | AF21: =AVERAGE(Q21:AD21) -> 278.33333 | AG21: =IF(AF21>=$AG$1,"APROVADO","REPROVADO") -> APROVADO
B22: 18 | C22: 018/23 | D22: Organização | E22: Obra Unida Lar São Vicente de Paulo de Guariba | F22: Ambiência para o bem-estar e eficiência na aplicação de recursos | G22: Eixo I: Promoção, Assistência e Desenvolvimento Social | H22: 67100 | I22: Guariba/SP | J22: DRADS RIBEIRÃO PRETO | K22: Gabriel Lopes | L22: larsvpguariba@hotmail.com | M22: 45302 | N22: Pré-Classificado | O22: PDF sem rubricas | R22: 199 | X22: 326 | Y22: 323 | AE22: =COUNT(Q22:AD22) -> 3 | AF22: =AVERAGE(Q22:AD22) -> 282.66667 | AG22: =IF(AF22>=$AG$1,"APROVADO","REPROVADO") -> APROVADO
B23: 19 | C23: 019/23 | D23: Prefeitura | E23: Municipal de Pratânia | F23: Grupo Melhor Idade | G23: Eixo I: Promoção, Assistência e Desenvolvimento Social | H23: 120000 | I23: Pratânia/SP | J23: DRADS BOTUCATU | K23: Elaine Cristina Rodrigues Honorato | L23: cras@boraceia.sp.gov.br | M23: 45302 | N23: Classificado | Q23: 297 | S23: 180 | T23: 112 | AE23: =COUNT(Q23:AD23) -> 3 | AF23: =AVERAGE(Q23:AD23) -> 196.33333 | AG23: =IF(AF23>=$AG$1,"APROVADO","REPROVADO") -> REPROVADO
B24: 20 | C24: 020/23 | D24: Prefeitura | E24: Municipal de Regente Feijó | F24: Fomento aos Direitos da Pessoa Idosa de Regente Feijó | G24: Eixo I: Promoção, Assistência e Desenvolvimento Social | H24: 267000 | I24: Regente Feijó | J24: DRADS ALTA SOROCABANA EM PRESIDENTE PRUDENTE | K24: Marcel Henrique de Mello Moraes | L24: asocial1@pratania.sp.gov.br | M24: 45302 | N24: Classificado | Q24: 330 | S24: 160 | T24: 125 | AE24: =COUNT(Q24:AD24) -> 3 | AF24: =AVERAGE(Q24:AD24) -> 205 | AG24: =IF(AF24>=$AG$1,"APROVADO","REPROVADO") -> APROVADO
B25: 21 | C25: 021/23 | D25: Organização | E25: Lar São Vicente de Paulo | F25: Revitalizar Para Melhor Viver | G25: Eixo V: Habitação e Urbanismo | H25: 192880.29 | I25: Santa Cruz do Rio Pardo/SP | J25: DRADS AVARÉ | K25: Acácio Henrique de Lima | L25: s.v.paulo@hotmail.com | M25: 45302 | N25: Desclassificado | O25: Plano de Trabalho sem Rubricar | AF25: =AVERAGE(Q25:AD25) -> #DIV/0! | AG25: =IF(AF25>=$AG$1,"APROVADO","REPROVADO") -> #DIV/0!
B26: 22 | C26: 022/23 | D26: Organização | E26: Lar São Vicente de Paulo | F26: Reforma e Ampliação da Sala de Fisioterapia do Lar São Vicente de Paulo | G26: Eixo I: Promoção, Assistência e Desenvolvimento Social | H26: 50000 | I26: Bernadino de Campo/SP | J26: DRADS BARRETOS | K26: Antônio Roberto de Oliveira | L26: Iarsaovicente@cednet. com. Br | M26: 45302 | N26: Pré-Classificado | O26: Falta de Informação do envelope | P26: Plano e Pendrive OK | Q26: 340 | R26: 178 | AD26: 340 | AE26: =COUNT(Q26:AD26) -> 3 | AF26: =AVERAGE(Q26:AD26) -> 286 | AG26: =IF(AF26>=$AG$1,"APROVADO","REPROVADO") -> APROVADO
B27: 23 | C27: 023/23 | D27: Prefeitura | E27: Municipal de São Jose do Rio Preto | F27: Oficinas e atividades artístico-culturais como instrumento de Intervenção Social Emancipatória para a pessoa idosa em situação de vulnerabilidade social | G27: Eixo VII: Cultura, Esporte, Turismo e Lazer | H27: 414308.85 | I27: São Jose do Rio Preto/SP | J27: DRADS: SÃO JOSÉ DO RIO PRETO | K27: Eliana Cristina Lechado | L27: convenio@regentefeijo.sp.gov.br | M27: 45302 | N27: Classificado | Q27: 297 | R27: 247 | S27: 249 | AE27: =COUNT(Q27:AD27) -> 3 | AF27: =AVERAGE(Q27:AD27) -> 264.33333 | AG27: =IF(AF27>=$AG$1,"APROVADO","REPROVADO") -> APROVADO
B28: 24 | C28: 024/23 | D28: Organização | E28: Abrigo Lar de Jesus | F28: Bem Estar na Melhor Idade de Anhumas | G28: Eixo I: Promoção, Assistência e Desenvolvimento Social | H28: 267766.51 | I28: Anhumas/SP | J28: DRADS ALTA SOROCABANA EM PRESIDENTE PRUDENTE | K28: Robson Mariano | L28: abrigolardejesus@hotmail.com | M28: 45302 | N28: Classificado | Q28: 331 | S28: 178 | T28: 248 | AE28: =COUNT(Q28:AD28) -> 3 | AF28: =AVERAGE(Q28:AD28) -> 252.33333 | AG28: =IF(AF28>=$AG$1,"APROVADO","REPROVADO") -> APROVADO
B29: 25 | C29: 025/23 | D29: Organização | E29: Associação Congregação de Santa Catarina | F29: Idoso Digital: Inclusão e Fortalecimento da Cidadania para a Pessoa Idosa | G29: Eixo I: Promoção, Assistência e Desenvolvimento Social | H29: 261777 | I29: Guarulhos/SP | J29: DRADS SPN EM GUARULHOS | K29: Mariana S Leonardo | L29: marina.leonardo@redesc.org.br | M29: 45302 | N29: Classificado | Q29: 340 | S29: 262 | T29: 302 | AE29: =COUNT(Q29:AD29) -> 3 | AF29: =AVERAGE(Q29:AD29) -> 301.33333 | AG29: =IF(AF29>=$AG$1,"APROVADO","REPROVADO") -> APROVADO
B30: 26 | C30: 026/23 | D30: Organização | E30: Associação Congregação de Santa Catarina | F30: Arte em Movimento: A Pessoa Idosa como Consumidora, Produtora e Disseminadora de Cultura | G30: Eixo VII: Cultura, Esporte, Turismo e Lazer | H30: 207810 | I30: Guarulhos/SP | J30: DRADS SPN EM GUARULHOS | K30: Mariana S. Leonardo | L30: mariana.leonardo@redesc.org.br | M30: 45321 | N30: Pré-Classificado | O30: Plano de Trabalho sem n° de páginas | Q30: 340 | R30: 254 | AD30: 340 | AE30: =COUNT(Q30:AD30) -> 3 | AF30: =AVERAGE(Q30:AD30) -> 311.33333 | AG30: =IF(AF30>=$AG$1,"APROVADO","REPROVADO") -> APROVADO
B31: 27 | C31: 027/23 | D31: Organização | E31: Lar São Vicente de Paulo de Taquarituba | F31: Acessibilidade | G31: Eixo V: Habitação e Urbanismo | H31: 150000 | I31: Taquarituba/SP | J31: DRADS AVARÉ | K31: Isabela Steinert Gabriel | L31: larsaovicente-taquarituba@hotmail.com | M31: 45303 | N31: Classificado | Q31: 306 | R31: 55 | T31: 66 | AE31: =COUNT(Q31:AD31) -> 3 | AF31: =AVERAGE(Q31:AD31) -> 142.33333 | AG31: =IF(AF31>=$AG$1,"APROVADO","REPROVADO") -> REPROVADO
B32: 28 | C32: 028/23 | D32: Organização | E32: Lar São Vicente de Paulo de Taquarituba | F32: Garantia de Bem Estar | G32: Eixo I: Promoção, Assistência e Desenvolvimento Social | H32: 120000 | I32: Taquarituba/SP | J32: DRADS AVARÉ | K32: Isabela Steinert Gabriel | L32: larsaovicente-taquarituba@hotmail.com | M32: 45303 | N32: Classificado | Q32: 340 | S32: 60 | T32: 79 | AE32: =COUNT(Q32:AD32) -> 3 | AF32: =AVERAGE(Q32:AD32) -> 159.66667 | AG32: =IF(AF32>=$AG$1,"APROVADO","REPROVADO") -> REPROVADO
B33: 29 | C33: 029/23 | D33: Organização | E33: Lar São Vicente de Paulo de Taquarituba | F33: Higiene Digna | G33: Eixo V: Habitação e Urbanismo | H33: 70000 | I33: Taquarituba/SP | J33: DRADS AVARÉ | K33: Isabela Steinert Gabriel | L33: larsaovicente-taquarituba@hotmail.com | M33: 45303 | N33: Classificado | Q33: 340 | S33: 58 | AB33: 295 | AE33: =COUNT(Q33:AD33) -> 3 | AF33: =AVERAGE(Q33:AD33) -> 231 | AG33: =IF(AF33>=$AG$1,"APROVADO","REPROVADO") -> APROVADO
B34: 30 | C34: 030/23 | D34: Prefeitura | E34: Municipal de Bastos | F34: Idoso em Movimento | G34: Eixo I: Promoção, Assistência e Desenvolvimento Social | H34: 610060.4 | I34: Bastos/SP | J34: DRADS MARÍLIA | K34: Luzia Kiyoko Honda | L34: semas@riopreto.sp.gov.br | M34: 45303 | N34: Reprovado | O34: Aquisição de Veiculo | Q34: 0 | R34: 29 | S34: 44 | AF34: =AVERAGE(Q34:AD34) -> 24.333333 | AG34: =IF(AF34>=$AG$1,"APROVADO","REPROVADO") -> REPROVADO
B35: 31 | C35: 031/23 | D35: Prefeitura | E35: Municipal de Bastos | F35: Longevidade Ativa e Protegida | G35: Eixo I: Promoção, Assistência e Desenvolvimento Social | H35: 160528.4 | I35: Bastos/SP | J35: DRADS MARÍLIA | K35: Luzia Kiyoko Honda | L35: pmbab@Bastos.sp.gov.br | M35: 45303 | N35: Reprovado | O35: Aquisição de Veiculo | Q35: 0 | R35: 169 | S35: 195 | T35: 206 | AF35: =AVERAGE(Q35:AD35) -> 142.5 | AG35: =IF(AF35>=$AG$1,"APROVADO","REPROVADO") -> REPROVADO
B36: 32 | C36: 032/23 | D36: Prefeitura | E36: Municipal São Cetano | F36: Terceira Idade em Movimento | G36: Eixo VII: Cultura, Esporte, Turismo e Lazer | H36: 344990 | I36: São Caetano do Sul/SP | J36: DRADS ABC EM SANTO ANDRÉ | K36: Tatiana | L36: pmbab@Bastos.sp.gov.br | M36: 45303 | N36: Desclassificado | O36: Plano de Trabalho sem Rubricar | AF36: =AVERAGE(Q36:AD36) -> #DIV/0! | AG36: =IF(AF36>=$AG$1,"APROVADO","REPROVADO") -> #DIV/0!
B37: 33 | C37: 033/23 | D37: Organização | E37: Asilo João kuhl Filho | F37: Colorir | G37: Eixo I: Promoção, Assistência e Desenvolvimento Social | H37: 641438.58 | I37: Limeira/SP | J37: DRADS PIRACICABA | K37: Bárbara Letícia Barbosa Pereira | L37: kuhlfilho@yahoo.com | M37: 45303 | N37: Pré-Classificado | R37: 198 | W37: 340 | Y37: 340 | AE37: =COUNT(Q37:AD37) -> 3 | AF37: =AVERAGE(Q37:AD37) -> 292.66667 | AG37: =IF(AF37>=$AG$1,"APROVADO","REPROVADO") -> APROVADO
B38: 34 | C38: 034/23 | D38: Prefeitura | E38: Municipal de Votuporanga | F38: Vida Longa com Automonia e Bem Estar | G38: Eixo I: Promoção, Assistência e Desenvolvimento Social | H38: 100000 | I38: Votuporanga/SP | J38: DRADS FERNANDÓPOLIS | K38: Meire Regina de Azevedo | L38: protecaosocialespecial@votuporanga.sp.gov.br | M38: 45303 | N38: Classificado | Q38: 337 | S38: 224 | T38: 238 | AE38: =COUNT(Q38:AD38) -> 3 | AF38: =AVERAGE(Q38:AD38) -> 266.33333 | AG38: =IF(AF38>=$AG$1,"APROVADO","REPROVADO") -> APROVADO
B39: 35 | C39: 035/23 | D39: Organização | E39: Associação AnhumasQuero-Quero | F39: ConVIVER: Incentivando a Plenitude na 3° Idade | G39: Eixo I: Promoção, Assistência e Desenvolvimento Social | H39: 283010 | I39: Campinas/SP | J39: DRADS CAMPINAS | K39: Felipe Brandão Teles | L39: administrativo@aaqq.org.br | M39: 45303 | N39: Classificado | Q39: 312 | S39: 222 | T39: 161 | AE39: =COUNT(Q39:AD39) -> 3 | AF39: =AVERAGE(Q39:AD39) -> 231.66667 | AG39: =IF(AF39>=$AG$1,"APROVADO","REPROVADO") -> APROVADO
B40: 36 | C40: 036/23 | D40: Organização | E40: Lar dos Velhinhos Santo Antônio de Juquiá LVSA | F40: Projeto Viver Bem | G40: Eixo I: Promoção, Assistência e Desenvolvimento Social Eixo VII: Cultura, Esporte, Turismo e Lazer | H40: 53388 | I40: Juquia/SP | J40: DRADS VALE DO RIBEIRA EM REGISTRO | K40: Rhiane Mello dos Santos Fernandes | L40: lardosidososdejuquia@gmail.com | M40: 45303 | N40: Classificado | Q40: 297 | AB40: 243 | AC40: 287 | AE40: =COUNT(Q40:AD40) -> 3 | AF40: =AVERAGE(Q40:AD40) -> 275.66667 | AG40: =IF(AF40>=$AG$1,"APROVADO","REPROVADO") -> APROVADO
B41: 37 | C41: 037/23 | D41: Organização | E41: Lar dos Velhinhos Santo Antônio de Juquiá LVSA | F41: Pintura e Reparos na Instituição | G41: Eixo I: Promoção, Assistência e Desenvolvimento Social | H41: 28000 | I41: Juquia/SP | J41: DRADS VALE DO RIBEIRA EM REGISTRO | K41: Rhiane Mello dos Santos Fernandes | L41: lardosidososdejuquia@gmail.com | M41: 45303 | N41: Classificado | Q41: 340 | Z41: 319 | AC41: 333 | AE41: =COUNT(Q41:AD41) -> 3 | AF41: =AVERAGE(Q41:AD41) -> 330.66667 | AG41: =IF(AF41>=$AG$1,"APROVADO","REPROVADO") -> APROVADO
B42: 38 | C42: 038/23 | D42: Organização | E42: Lar Fraterno São Vicente de Apiaí | F42: Mais conforto | G42: Eixo II: Sáude | H42: 180000 | I42: Apiaí/SP | J42: DRADS ITAPEVA | K42: Alaíme Yuki monteiro Takiguchi Correa | L42: asiloapiai@hotmail.com | M42: 45303 | N42: Reprovado | O42: FALTOU PREENCHER ITEM 6(metodo e dinamica do trabalho) , ITEM 10, 11 E 12 - ORÇAMENTO. | Q42: 332 | S42: 200 | T42: 0 | AF42: =AVERAGE(Q42:AD42) -> 177.33333 | AG42: =IF(AF42>=$AG$1,"APROVADO","REPROVADO") -> REPROVADO
B43: 39 | C43: 039/23 | D43: Organização | E43: Lar Fraterno São Vicente de Apiaí | F43: Buscando Qualidade de Vida | G43: Eixo II: Sáude | H43: 220000 | I43: Apiaí/SP | J43: DRADS ITAPEVA | K43: Alaíme Yuki monteiro Takiguchi Correa | L43: asiloapiai@hotmail.com | M43: 45303 | N43: Pré-Classificado | Q43: 340 | R43: 123 | AD43: 238 | AE43: =COUNT(Q43:AD43) -> 3 | AF43: =AVERAGE(Q43:AD43) -> 233.66667 | AG43: =IF(AF43>=$AG$1,"APROVADO","REPROVADO") -> APROVADO
B44: 40 | C44: 040/23 | D44: Prefeitura | E44: Municipal de Apiaí | F44: Conhecendo População de Pessoas Idosas | G44: Eixo I: Promoção, Assistência e Desenvolvimento Social | H44: 80000 | I44: Apiaí/SP | J44: DRADS ITAPEVA | K44: Sergio Victor Borges Barbosa | L44: deptosocial@nantes.sp.gov.br | M44: 45303 | N44: Pré-Classificado | Q44: 200 | R44: 133 | AB44: 157 | AE44: =COUNT(Q44:AD44) -> 3 | AF44: =AVERAGE(Q44:AD44) -> 163.33333 | AG44: =IF(AF44>=$AG$1,"APROVADO","REPROVADO") -> REPROVADO
B45: 41 | C45: 041/23 | D45: Organização | E45: Lar Fraterno São Vicente de Apiaí | F45: Em busca de um sonho | G45: VII –Turismo | H45: 50000 | I45: Apiaí/SP | J45: DRADS ITAPEVA | K45: Alaíme Yuki monteiro Takiguchi Correa | L45: asiloapiai@hotmail.com | M45: 45303 | N45: Pré-Classificado | R45: 75 | V45: 189 | W45: 164 | AE45: =COUNT(Q45:AD45) -> 3 | AF45: =AVERAGE(Q45:AD45) -> 142.66667 | AG45: =IF(AF45>=$AG$1,"APROVADO","REPROVADO") -> REPROVADO
B46: 42 | C46: 042/23 | D46: Prefeitura | E46: Municipal de Apiaí | F46: Segurança e Qualidade do Atendimento as Pessoas Idosas | G46: Eixo I: Promoção, Assistência e Desenvolvimento Social | H46: 400000 | I46: Apiaí/SP | J46: DRADS ITAPEVA | K46: Sergio Victor Borges Barbosa | L46: social.apiai@gmail.com | M46: 45303 | N46: Pré-Classificado | Q46: 277 | R46: 91 | AC46: 292 | AE46: =COUNT(Q46:AD46) -> 3 | AF46: =AVERAGE(Q46:AD46) -> 220 | AG46: =IF(AF46>=$AG$1,"APROVADO","REPROVADO") -> APROVADO
B47: 43 | C47: 043/23 | D47: Organização | E47: Sociedade Espirita Cinco de Setembro | F47: Acolhendo com Amor - Casa do Vovô - Reforma Hidráulica | G47: Eixo I: Promoção, Assistência e Desenvolvimento Social | H47: 270000 | I47: Ribeirão Preto/SP | J47: DRADS RIBEIRÃO PRETO | K47: Tatiane Tavares | L47: casadovovo@casadovovo.org.br | M47: 45303 | N47: Classificado | Q47: 340 | S47: 189 | T47: 212 | AE47: =COUNT(Q47:AD47) -> 3 | AF47: =AVERAGE(Q47:AD47) -> 247 | AG47: =IF(AF47>=$AG$1,"APROVADO","REPROVADO") -> APROVADO
B48: 44 | C48: 044/23 | D48: Organização | E48: Sociedade Espirita Cinco de Setembro | F48: Cuidar com Excelência: Valorizando a Saúde da Pessoa Idosa | G48: Eixo II: Sáude | H48: 188640 | I48: Ribeirão Preto/SP | J48: DRADS RIBEIRÃO PRETO | K48: Tatiane Tavares | L48: casadovovo@casadovovo.org.br | M48: 45303 | N48: Classificado | Q48: 327 | S48: 190 | T48: 153 | AE48: =COUNT(Q48:AD48) -> 3 | AF48: =AVERAGE(Q48:AD48) -> 223.33333 | AG48: =IF(AF48>=$AG$1,"APROVADO","REPROVADO") -> APROVADO
B49: 45 | C49: 045/23 | D49: Organização | E49: Sociedade Espirita Cinco de Setembro | F49: Viver Ativo - Fomentando Saúde e Integração em Pessoas Idosas | G49: Eixo VII: Cultura, Esporte, Turismo e Lazer | H49: 240000 | I49: Ribeirão Preto/SP | J49: DRADS RIBEIRÃO PRETO | K49: Tatiane Tavares | L49: casadovovo@casadovovo.org.br | M49: 45303 | N49: Classificado | Q49: 333 | S49: 200 | T49: 168 | AE49: =COUNT(Q49:AD49) -> 3 | AF49: =AVERAGE(Q49:AD49) -> 233.66667 | AG49: =IF(AF49>=$AG$1,"APROVADO","REPROVADO") -> APROVADO
B50: 46 | C50: 046/23 | D50: Organização | E50: Lar dos Velhos da Igreja presbiteriana de Ribeirão Preto | F50: Tecnologia para a Terceira Idade - Inclusão Digital e Social | G50: Eixo III: Educação | H50: 252000 | I50: Ribeirão Preto/SP | J50: DRADS RIBEIRÃO PRETO | K50: Rosangela Aparecida Bellomo Minuti | L50: coordenacao@lardosvelhos.com.br | M50: 45303 | N50: Classificado | Q50: 286 | R50: 305 | T50: 306 | AE50: =COUNT(Q50:AD50) -> 3 | AF50: =AVERAGE(Q50:AD50) -> 299 | AG50: =IF(AF50>=$AG$1,"APROVADO","REPROVADO") -> APROVADO
B51: 47 | C51: 047/23 | D51: Organização | E51: Lar dos Velhos da Igreja presbiteriana de Ribeirão Preto | F51: Adequação e Modernização do Ambiente Institucional: Acolhendo com Dignidade e Respeito | G51: Eixo I: Promoção, Assistência e Desenvolvimento Social | H51: 500000 | I51: Ribeirão Preto/SP | J51: DRADS RIBEIRÃO PRETO | K51: Rosangela Aparecida Bellomo Minuti | L51: coordenacao@lardosvelhos.com.br | M51: 45303 | N51: Classificado | O51: Projeto Duplicado (047/23 e 225/23) | Q51: 340 | R51: 159 | AC51: 333 | AE51: =COUNT(Q51:AD51) -> 3 | AF51: =AVERAGE(Q51:AD51) -> 277.33333 | AG51: =IF(AF51>=$AG$1,"APROVADO","REPROVADO") -> APROVADO
B52: 48 | C52: 048/23 | D52: Organização | E52: Circulo de Trabalhadores Cristoes de Vila Tibério | F52: Acolhendo a Melhor Idade | G52: Eixo I: Promoção, Assistência e Desenvolvimento Social | H52: 200000 | I52: Ribeirão Preto/SP | J52: DRADS RIBEIRÃO PRETO | K52: Luiz Carlos Peruchi | L52: circulooperariorp@hotmail.com | M52: 45303 | N52: Classificado | Q52: 327 | S52: 224 | T52: 142 | AE52: =COUNT(Q52:AD52) -> 3 | AF52: =AVERAGE(Q52:AD52) -> 231 | AG52: =IF(AF52>=$AG$1,"APROVADO","REPROVADO") -> APROVADO
B53: 49 | C53: 049/23 | D53: Organização | E53: Associação Assistencial Maria de Nazaré | F53: Ambientar é Cuidar | G53: Eixo I: Promoção, Assistência e Desenvolvimento Social | H53: 37863.96 | I53: Ribeirão Preto/SP | J53: DRADS RIBEIRÃO PRETO | K53: Gislene Mazer | L53: social@vovoalbano.org.br | M53: 45303 | N53: Classificado | O53: Sem valor no plano de trabalho (apenas o valor no cronograma) | Q53: 340 | R53: 117 | T53: 265 | AE53: =COUNT(Q53:AD53) -> 3 | AF53: =AVERAGE(Q53:AD53) -> 240.66667 | AG53: =IF(AF53>=$AG$1,"APROVADO","REPROVADO") -> APROVADO
B54: 50 | C54: 050/23 | D54: Prefeitura | E54: Municipal de Nantes | F54: Bem Estar na Melhor Idade | G54: Eixo I: Promoção, Assistência e Desenvolvimento Social | H54: 331000 | I54: Nantes/SP | J54: DRADS ALTA SOROCABANA EM PRESIDENTE PRUDENTE | K54: Aline Fernanda de Jesus Souza | L54: protecaosocialespecial@votuporanga.sp.gov.br | M54: 45303 | N54: Reprovado | O54: Aquisição de Veiculo | Q54: 0 | R54: 188 | S54: 243 | T54: 0 | AF54: =AVERAGE(Q54:AD54) -> 107.75 | AG54: =IF(AF54>=$AG$1,"APROVADO","REPROVADO") -> REPROVADO
B55: 51 | C55: 051/23 | D55: Organização | E55: Abrigo de Idosos Recanto do Vovô de Presidente Epitácio-SP | F55: Adequações e melhorias dos banheiros feminino e masculino | G55: Eixo I: Promoção, Assistência e Desenvolvimento Social | H55: 345133.32 | I55: Presidente Epitácio/SP | J55: DRADS ALTA SOROCABANA EM PRESIDENTE PRUDENTE | K55: Virgínio Antonio Mechior | L55: financeiro@recantodovovo.org.br | M55: 45303 | N55: Pré-Classificado | O55: Documento Word (Pendrive) | Q55: 315 | R55: 242 | AD55: 289 | AE55: =COUNT(Q55:AD55) -> 3 | AF55: =AVERAGE(Q55:AD55) -> 282 | AG55: =IF(AF55>=$AG$1,"APROVADO","REPROVADO") -> APROVADO
B56: 52 | C56: 052/23 | D56: Organização | E56: Associação de pais e Amigos dos Excepicinais de São Paulo (Jô Clemente) | F56: Inclusão e Prevenção da Saúde da Pessoa Idosa com Deficiência Intelectual | G56: Eixo II: Sáude | H56: 1431815.8 | I56: São Paulo/SP | J56: DRADS CAPITAL EM SÃO PAULO | K56: Fabio Rubson | L56: projetos@ijc.org.br | M56: 45303 | N56: Classificado | Q56: 340 | S56: 272 | T56: 288 | AE56: =COUNT(Q56:AD56) -> 3 | AF56: =AVERAGE(Q56:AD56) -> 300 | AG56: =IF(AF56>=$AG$1,"APROVADO","REPROVADO") -> APROVADO
B57: 53 | C57: 053/23 | D57: Organização | E57: Movimento Organizacional Vencer, Educar e Realizar - MOVER HELIPA | F57: Projeto Gastronomia e Saberes da Pessoa Idosa | G57: Eixo IV: Trabalho e Previdência Social | H57: 1111410.1 | I57: São Paulo/SP | J57: DRADS CAPITAL EM SÃO PAULO | K57: Jose Renato | L57: moverhelipa@gmail.com | M57: 45303 | N57: Pré-Classificado | O57: Plano de Trabalho sem n° de páginas | Q57: 284 | S57: 246 | T57: 172 | AE57: =COUNT(Q57:AD57) -> 3 | AF57: =AVERAGE(Q57:AD57) -> 234 | AG57: =IF(AF57>=$AG$1,"APROVADO","REPROVADO") -> APROVADO
B58: 54 | C58: 054/23 | D58: Organização | E58: Sociedade São Vicentede Paulo Nossa Senhora das Dores | F58: Cuidar, um Ato de Amor | G58: Eixo I: Promoção, Assistência e Desenvolvimento Social | H58: 88952.51 | I58: São Caeteno/SP | J58: DRADS ABC EM SANTO ANDRÉ | K58: Marli Barreto Felício | L58: sovipansd@yahoo.com.br | M58: 45306 | N58: Classificado | Q58: 340 | S58: 246 | T58: 290 | AE58: =COUNT(Q58:AD58) -> 3 | AF58: =AVERAGE(Q58:AD58) -> 292 | AG58: =IF(AF58>=$AG$1,"APROVADO","REPROVADO") -> APROVADO
B59: 55 | C59: 055/23 | D59: Organização | E59: Lar São Vicente de Paulo | F59: Melhorias e Adequações das Condições de Habitabilidade | G59: Eixo V: Habitação e Urbanismo | H59: 388555.13 | I59: Descalvado/SP | J59: DRADS ARARAQUARA | K59: Vírginia Elaine da S. N. Guiguer | L59: larsao vicentepaulo@terra.com.br | M59: 45306 | N59: Pré-Classificado | O59: Documento Word (Pendrive) | R59: 111 | X59: 300 | Y59: 324 | AE59: =COUNT(Q59:AD59) -> 3 | AF59: =AVERAGE(Q59:AD59) -> 245 | AG59: =IF(AF59>=$AG$1,"APROVADO","REPROVADO") -> APROVADO
B60: 56 | C60: 056/23 | D60: Organização | E60: Lar São Vicente de Paulo | F60: Aquisição de camas motorizadas e colchões | G60: Eixo I: Promoção, Assistência e Desenvolvimento Social | H60: 259202 | I60: Descalvado/SP | J60: DRADS ARARAQUARA | K60: Vírginia Elaine da S. N. Guiguer | L60: larsao vicentepaulo@terra.com.br | M60: 45306 | N60: Pré-Classificado | O60: Documento Word (Pendrive) | R60: 108 | V60: 278 | W60: 39 | AE60: =COUNT(Q60:AD60) -> 3 | AF60: =AVERAGE(Q60:AD60) -> 141.66667 | AG60: =IF(AF60>=$AG$1,"APROVADO","REPROVADO") -> REPROVADO
B61: 57 | C61: 057/23 | D61: Prefeitura | E61: Municipal de Descalvado | F61: Idoso em Movimento | G61: Eixo VII: Cultura, Esporte, Turismo e Lazer | H61: 473200 | I61: Descalvado/SP | J61: DRADS ARARAQUARA | K61: Marly Colognesi Reschini | L61: social.apiai@gmail.com | M61: 45306 | N61: Classificado | Q61: 298 | R61: 82 | T61: 76 | AE61: =COUNT(Q61:AD61) -> 3 | AF61: =AVERAGE(Q61:AD61) -> 152 | AG61: =IF(AF61>=$AG$1,"APROVADO","REPROVADO") -> REPROVADO
B62: 58 | C62: 058/23 | D62: Prefeitura | E62: Municipal de Descalvado | F62: Sempre Sorrindo | G62: Eixo II: Sáude | H62: 39973 | I62: Descalvado/SP | J62: DRADS ARARAQUARA | K62: Marly Colognesi Reschini | L62: casadoidoso@descalvado.sp.gov.br | M62: 45306 | N62: Pré-Classificado | O62: Plano sem n° de páginas | Q62: 340 | R62: 103 | AC62: 340 | AE62: =COUNT(Q62:AD62) -> 3 | AF62: =AVERAGE(Q62:AD62) -> 261 | AG62: =IF(AF62>=$AG$1,"APROVADO","REPROVADO") -> APROVADO
B63: 59 | C63: 059/23 | D63: Prefeitura | E63: Municipal de Descalvado | F63: Ouvir Melhor | G63: Eixo II: Sáude | H63: 649980 | I63: Descalvado/SP | J63: DRADS ARARAQUARA | K63: Marly Colognesi Reschini | L63: casadoidoso@descalvado.sp.gov.br | M63: 45306 | N63: Pré-Classificado | O63: Plano sem n° de páginas | Q63: 340 | R63: 103 | V63: 340 | AE63: =COUNT(Q63:AD63) -> 3 | AF63: =AVERAGE(Q63:AD63) -> 261 | AG63: =IF(AF63>=$AG$1,"APROVADO","REPROVADO") -> APROVADO
B64: 60 | C64: 060/2 | D64: Prefeitura | E64: Municipal de Descalvado | F64: Plantando Semente da Longevidade | G64: Eixo II: Sáude | H64: 450000 | I64: Descalvado/SP | J64: DRADS ARARAQUARA | K64: Marly Colognesi Reschini | L64: casadoidoso@descalvado.sp.gov.br | M64: 45306 | N64: Pré-Classificado | O64: Plano sem n° de páginas | Q64: 324 | R64: 111 | W64: 340 | AE64: =COUNT(Q64:AD64) -> 3 | AF64: =AVERAGE(Q64:AD64) -> 258.33333 | AG64: =IF(AF64>=$AG$1,"APROVADO","REPROVADO") -> APROVADO
B65: 61 | C65: 061/23 | D65: Organização | E65: Lar São Vicente de Paulo | F65: Melhor Qualidade de Vida e Bem Estar dos Idosos Institucionalizados | G65: Eixo I: Promoção, Assistência e Desenvolvimento Social | H65: 50000 | I65: Barra Bonita/SP | J65: DRADS BAURU | K65: Adriana Vieira | L65: ispvbb@hotmail.com | M65: 45306 | N65: Pré-Classificado | O65: Plano de Trabalho sem rubricar | R65: 188 | X65: 340 | Y65: 340 | AE65: =COUNT(Q65:AD65) -> 3 | AF65: =AVERAGE(Q65:AD65) -> 289.33333 | AG65: =IF(AF65>=$AG$1,"APROVADO","REPROVADO") -> APROVADO
B66: 62 | C66: 062/23 | D66: Organização | E66: Centro Espírita Cristão (CEC)- Lar de Amparo a Velhice de Barra Bonita/SP | F66: CEC Bem Viver | G66: Eixo I: Promoção, Assistência e Desenvolvimento Social | H66: 34150 | I66: Barra Bonita/SP | J66: DRADS BAURU | K66: Luiz Pizzo | L66: ceclaramparo@gmail.com | M66: 45306 | N66: Pré-Classificado | O66: PDF sem assinar e rubricar | Q66: 340 | R66: 207 | AD66: 340 | AE66: =COUNT(Q66:AD66) -> 3 | AF66: =AVERAGE(Q66:AD66) -> 295.66667 | AG66: =IF(AF66>=$AG$1,"APROVADO","REPROVADO") -> APROVADO
B67: 63 | C67: 063/23 | D67: Organização | E67: Lar São Vicente de Paulo | F67: Investimento no Bem-Estar dos Idosos Institucionalizados | G67: Eixo I: Promoção, Assistência e Desenvolvimento Social | H67: 67450 | I67: Mineiros do Tietê/SP | J67: DRADS BAURU | K67: Vera Lúcia Giraldi Real | L67: asilosaovicente.mtiete@gmail.com | M67: 45306 | N67: Classificado | Q67: 340 | R67: 239 | T67: 237 | AE67: =COUNT(Q67:AD67) -> 3 | AF67: =AVERAGE(Q67:AD67) -> 272 | AG67: =IF(AF67>=$AG$1,"APROVADO","REPROVADO") -> APROVADO
B68: 64 | C68: 064/23 | D68: Organização | E68: Assistencia Vicentina do Senhor Jesus | F68: Lar Doce Lar de Matão | G68: Eixo I: Promoção, Assistência e Desenvolvimento Social | H68: 100000 | I68: Matão/SP | J68: DRADS ARARAQUARA | K68: Marisa Albino | L68: larsaovicente@process.com.br | M68: 45306 | N68: Classificado | Q68: 340 | R68: 272 | T68: 301 | AE68: =COUNT(Q68:AD68) -> 3 | AF68: =AVERAGE(Q68:AD68) -> 304.33333 | AG68: =IF(AF68>=$AG$1,"APROVADO","REPROVADO") -> APROVADO
B69: 65 | C69: 065/23 | D69: Organização | E69: Associação Social Comunidade de Amor | F69: Construindo Laços: Um Caminho para o Bem Estar dos Idosos | G69: Eixo VII: Cultura, Esporte, Turismo e Lazer | H69: 208890 | I69: Sorocaba/SP | J69: DRADS SOROCABA | K69: Mariangela Geraldi | L69: projetoacolhe2@gmail.com | M69: 45306 | N69: Classificado | Q69: 299 | R69: 272 | S69: 281 | AE69: =COUNT(Q69:AD69) -> 3 | AF69: =AVERAGE(Q69:AD69) -> 284 | AG69: =IF(AF69>=$AG$1,"APROVADO","REPROVADO") -> APROVADO
B70: 66 | C70: 066/23 | D70: Organização | E70: Casa do Vovô Feliz | F70: Velha história, Novos Retalhos – Resgatando Vidas | G70: Eixo VII: Cultura, Esporte, Turismo e Lazer | H70: 49800 | I70: Itapecerica da Serra/SP | J70: DRADS SPO EM OSASCO | K70: Teresa Takemura Kawasaki | L70: cvf@casadovovofeliz.or.br | M70: 45306 | N70: Pré-Classificado | O70: Documento Word (Pendrive) | R70: 191 | X70: 321 | Y70: 340 | AE70: =COUNT(Q70:AD70) -> 3 | AF70: =AVERAGE(Q70:AD70) -> 284 | AG70: =IF(AF70>=$AG$1,"APROVADO","REPROVADO") -> APROVADO
B71: 67 | C71: 067/23 | D71: Prefeitura | E71: Municipal de Cassia dos Coqueiros | F71: Saber Viver na Melhor Idade | G71: Eixo I: Promoção, Assistência e Desenvolvimento Social | H71: 188300 | I71: Cássia dos Coqueiros/SP | J71: DRADS RIBEIRÃO PRETO | K71: Silvio Santos dos Reis Faria | L71: casadoidoso@descalvado.sp.gov.br | M71: 45306 | N71: Pré-Classificado | O71: Falta de Informação do envelope | Q71: 235 | V71: 213 | W71: 212 | AE71: =COUNT(Q71:AD71) -> 3 | AF71: =AVERAGE(Q71:AD71) -> 220 | AG71: =IF(AF71>=$AG$1,"APROVADO","REPROVADO") -> APROVADO
B72: 68 | C72: 068/2 | D72: Organização | E72: Casa de Oração Amor Luz | F72: Serviço de Convivência e Fortalecimento de Vínculos — SCFV para Pessoas Idosas, com idade igual ou acima de 60 anos | G72: Eixo VII: Cultura, Esporte, Turismo e Lazer | H72: 68680 | I72: São José dos Campos/SP | J72: DRADS VALE DO PARAÍBA EM SÃO JOSÉ DOS CAMPOS | K72: Maria Cristina Sundfeld | L72: Coalsocial@gmail.com | M72: 45306 | N72: Classificado | Q72: 276 | R72: 188 | AB72: 269 | AE72: =COUNT(Q72:AD72) -> 3 | AF72: =AVERAGE(Q72:AD72) -> 244.33333 | AG72: =IF(AF72>=$AG$1,"APROVADO","REPROVADO") -> APROVADO
B73: 69 | C73: 069/23 | D73: Organização | E73: Lar dos Velhinhos São Vicente de Paulo | F73: Renovar | G73: Eixo I: Promoção, Assistência e Desenvolvimento Social | H73: 44934 | I73: Urânia/SP | J73: DRADS FERNANDÓPOLIS | K73: Zélia Souza Silva | L73: lardos velhinhos1@hotmail.com | M73: 45306 | N73: Pré-Classificado | O73: Documento Word (Pendrive) | P73: 3 planos de trabalho no mesmo pendrive | R73: 212 | X73: 307 | Y73: 298 | AE73: =COUNT(Q73:AD73) -> 3 | AF73: =AVERAGE(Q73:AD73) -> 272.33333 | AG73: =IF(AF73>=$AG$1,"APROVADO","REPROVADO") -> APROVADO
B74: 70 | C74: 070/23 | D74: Organização | E74: Lar dos Velhinhos São Vicente de Paulo | F74: Idoso Jovem | G74: Eixo I: Promoção, Assistência e Desenvolvimento Social | H74: 38337 | I74: Urânia/SP | J74: DRADS FERNANDÓPOLIS | K74: Zélia Souza Silva | L74: lardos velhinhos1@hotmail.com | M74: 45306 | N74: Desclassificado | O74: Sem Pendrive | AF74: =AVERAGE(Q74:AD74) -> #DIV/0! | AG74: =IF(AF74>=$AG$1,"APROVADO","REPROVADO") -> #DIV/0!
B75: 71 | C75: 071/23 | D75: Organização | E75: Lar dos Velhinhos São Vicente de Paulo | F75: Meu Quarto Meus Sonhos | G75: Eixo I: Promoção, Assistência e Desenvolvimento Social | H75: 78212 | I75: Urânia/SP | J75: DRADS FERNANDÓPOLIS | K75: Zélia Souza Silva | L75: lardos velhinhos1@hotmail.com | M75: 45306 | N75: Desclassificado | O75: Sem Pendrive | AF75: =AVERAGE(Q75:AD75) -> #DIV/0! | AG75: =IF(AF75>=$AG$1,"APROVADO","REPROVADO") -> #DIV/0!
B76: 72 | C76: 072/23 | D76: Organização | E76: Lar São Francisco de Assis Asilo | F76: Centro de Convivio da Pessoa Idosa | G76: Eixo I: Promoção, Assistência e Desenvolvimento Social | H76: 360000 | I76: Araraquara/SP | J76: DRADS ARARAQUARA | K76: Maria Elena Baptista | L76: azilo@uol.com.br | M76: 45306 | N76: Classificado | Q76: 324 | S76: 274 | T76: 230 | AE76: =COUNT(Q76:AD76) -> 3 | AF76: =AVERAGE(Q76:AD76) -> 276 | AG76: =IF(AF76>=$AG$1,"APROVADO","REPROVADO") -> APROVADO
B77: 73 | C77: 073/23 | D77: Organização | E77: Registro Conselho Municipal - ARTGYM - LTDA | F77: Estímulos da Sinapse Neurológica para a Saúde física e Mental, por meio da Dança e do Movimento Ginástico Sistematizados para a Melhor Idade de Araraquara-SP | G77: Eixo VII: Cultura, Esporte, Turismo e Lazer | H77: 390000 | I77: Araraquara/SP | J77: DRADS ARARAQUARA | K77: Henrique Sanioto | L77: professorsanioto@gmail.com | M77: 45306 | N77: Reprovado | O77: Nota 0 no item 1 - CNPJ de Sociedade Empresaria Limitada (Jeverson) e ideam ao item 1 obs da Erica | R77: 34 | AB77: 0 | AF77: =AVERAGE(Q77:AD77) -> 17 | AG77: =IF(AF77>=$AG$1,"APROVADO","REPROVADO") -> REPROVADO
B78: 74 | C78: 074/23 | D78: Prefeitura | E78: Municipal D'Oeste | F78: Bem Viver | G78: Eixo I: Promoção, Assistência e Desenvolvimento Social | H78: 133070 | I78: Aparecida D'Oeste/SP | J78: DRADS FERNANDÓPOLIS | K78: Sandra Regina Penariol | L78: adm@pmaparecidadoeste.sp.gov.br | M78: 45306 | N78: Classificado | Q78: 320 | S78: 252 | T78: 215 | AE78: =COUNT(Q78:AD78) -> 3 | AF78: =AVERAGE(Q78:AD78) -> 262.33333 | AG78: =IF(AF78>=$AG$1,"APROVADO","REPROVADO") -> APROVADO
B79: 75 | C79: 075/23 | D79: Organização | E79: Associação Centros Etievan | F79: Repórter 60+ | G79: Eixo III: Educação Eixo VII: (Cultura, Esporte, Turismo e Lazer | H79: 620100 | I79: Guapiaçu/SP | J79: DRADS SÃO JOSÉ DO RIO PRETO | K79: Isabel Dsávila | L79: coordenacao@centrosetievan.com.br | M79: 45306 | N79: Classificado | P79: Verificar Comissão: plano de trabalho com 2 eixos, no envelope consta apenas 1. | Q79: 330 | R79: 187 | S79: 281 | AE79: =COUNT(Q79:AD79) -> 3 | AF79: =AVERAGE(Q79:AD79) -> 266 | AG79: =IF(AF79>=$AG$1,"APROVADO","REPROVADO") -> APROVADO
B80: 76 | C80: 076/23 | D80: Organização | E80: Lar São Vicente Obra Padre Donizetti | F80: Qualificação de Equipamentos e Ambientes Lar São Vicente - Obra Padre Donizetti | G80: Eixo I: Promoção, Assistência e Desenvolvimento Social | H80: 14757 | I80: Tambáu/SP | J80: DRADS MOGIANA EM SÃO JOÃO DA BOA VISTA | K80: Urbano Antoninho Giorgetti | L80: obrapdonizetti@hotmail.com | M80: 45307 | N80: Pré-Classificado | O80: Plano e Pendrive OK | Q80: 340 | R80: 245 | AD80: 340 | AE80: =COUNT(Q80:AD80) -> 3 | AF80: =AVERAGE(Q80:AD80) -> 308.33333 | AG80: =IF(AF80>=$AG$1,"APROVADO","REPROVADO") -> APROVADO
B81: 77 | C81: 077/23 | D81: Organização | E81: Serviço de Obras Sociais de Tambáu-S.O.S | F81: Aconchego | G81: Eixo I: Promoção, Assistência e Desenvolvimento Social | H81: 240000 | I81: Tambáu/SP | J81: DRADS MOGIANA EM SÃO JOÃO DA BOA VISTA | K81: Jose Luiz Furtado | L81: sostambau@strnet.com.br | M81: 45307 | N81: Classificado | Q81: 325 | S81: 260 | T81: 263 | AE81: =COUNT(Q81:AD81) -> 3 | AF81: =AVERAGE(Q81:AD81) -> 282.66667 | AG81: =IF(AF81>=$AG$1,"APROVADO","REPROVADO") -> APROVADO
B82: 78 | C82: 078/23 | D82: Organização | E82: Associação Franciscana de Solidariedade | F82: Bem Viver - Envelhecer com Qualidade em São Paulo | G82: Eixo VII: Cultura, Esporte, Turismo e Lazer | H82: 764968.68 | I82: São Paulo/SP | J82: DRADS CAPITAL EM SÃO PAULO | K82: Regina Pessoa | L82: Projetos@sefras.org.br | M82: 45307 | N82: Pré-Classificado | O82: Plano sem rubricar | Q82: 324 | R82: 256 | AD82: 340 | AE82: =COUNT(Q82:AD82) -> 3 | AF82: =AVERAGE(Q82:AD82) -> 306.66667 | AG82: =IF(AF82>=$AG$1,"APROVADO","REPROVADO") -> APROVADO
B83: 79 | C83: 079/23 | D83: Organização | E83: Associação Franciscana de Solidariedade | F83: Vida Plena- Envelhecer com Qualidade | G83: Eixo VII: Cultura, Esporte, Turismo e Lazer | H83: 396760.14 | I83: Pindamonhangaba/SP | J83: DRADS VALE DO PARAÍBA EM SÃO JOSÉ DOS CAMPOS | K83: Regina Pessoa | L83: Projetos@sefras.org.br | M83: 45307 | N83: Pré-Classificado | O83: Plano sem rubricar | Q83: 308 | R83: 256 | AD83: 273 | AE83: =COUNT(Q83:AD83) -> 3 | AF83: =AVERAGE(Q83:AD83) -> 279 | AG83: =IF(AF83>=$AG$1,"APROVADO","REPROVADO") -> APROVADO
B84: 80 | C84: 080/23 | D84: Organização | E84: Associação Franciscana de Solidariedade | F84: Novos Tempos - Envelhecer com Qualidade em Mogi das Cruzes | G84: Eixo VII: Cultura, Esporte, Turismo e Lazer | H84: 579789.01 | I84: Pindamonhangaba/SP | J84: DRADS VALE DO PARAÍBA EM SÃO JOSÉ DOS CAMPOS | K84: Regina Pessoa | L84: Projetos@sefras.org.br | M84: 45307 | N84: Pré-Classificado | O84: Plano sem rubricar | Q84: 315 | R84: 225 | AD84: 340 | AE84: =COUNT(Q84:AD84) -> 3 | AF84: =AVERAGE(Q84:AD84) -> 293.33333 | AG84: =IF(AF84>=$AG$1,"APROVADO","REPROVADO") -> APROVADO
B85: 81 | C85: 081/23 | D85: Organização | E85: Vila Vicentina em Brotas | F85: Entreterimento aos Idosos (Televisor de 85") | G85: Eixo I: Promoção, Assistência e Desenvolvimento Social | H85: 10000 | I85: Brotas/SP | J85: DRADS PIRACICABA | K85: Neuza Maria Pascoalotti Berto | L85: vilavicentinoembrotas@outlook.com | M85: 45307 | N85: Classificado | P85: Pendrive com 3 Projetos | Q85: 340 | S85: 274 | T85: 287 | AE85: =COUNT(Q85:AD85) -> 3 | AF85: =AVERAGE(Q85:AD85) -> 300.33333 | AG85: =IF(AF85>=$AG$1,"APROVADO","REPROVADO") -> APROVADO
B86: 82 | C86: 082/23 | D86: Organização | E86: Vila Vicentina em Brotas | F86: Bem Estar Social aos Idosos (mesas e Cadeiras) | G86: Eixo I: Promoção, Assistência e Desenvolvimento Social | H86: 10000 | I86: Brotas/SP | J86: DRADS PIRACICABA | K86: Neuza Maria Pascoalotti Berto | L86: vilavicentinoembrotas@outlook.com | M86: 45307 | N86: Desclassificado | O86: Sem Pendrive | AF86: =AVERAGE(Q86:AD86) -> #DIV/0! | AG86: =IF(AF86>=$AG$1,"APROVADO","REPROVADO") -> #DIV/0!
B87: 83 | C87: 083/23 | D87: Organização | E87: Vila Vicentina em Brotas | F87: Aconchego aos Idosos (Poltrona do Papai Reclinável) | G87: Eixo I: Promoção, Assistência e Desenvolvimento Social | H87: 10000 | I87: Brotas/SP | J87: DRADS PIRACICABA | K87: Neuza Maria Pascoalotti Berto | L87: vilavicentinoembrotas@outlook.com | M87: 45307 | N87: Desclassificado | O87: Sem Pendrive | AF87: =AVERAGE(Q87:AD87) -> #DIV/0! | AG87: =IF(AF87>=$AG$1,"APROVADO","REPROVADO") -> #DIV/0!
B88: 84 | C88: 084/23 | D88: Organização | E88: Instituto Acorde | F88: Centro Dia – Um novo olhar | G88: Eixo IV: Trabalho e Previdência Social | H88: 180000 | I88: São Carlos/SP | J88: DRADS ARARAQUARA | K88: Cleonice Lavandoski Amato | L88: acorde@institutoacorde.org.br | M88: 45307 | N88: Pré-Classificado | O88: Documento Word (Pendrive) | R88: 175 | X88: 297 | Y88: 297 | AE88: =COUNT(Q88:AD88) -> 3 | AF88: =AVERAGE(Q88:AD88) -> 256.33333 | AG88: =IF(AF88>=$AG$1,"APROVADO","REPROVADO") -> APROVADO
B89: 85 | C89: 085/23 | D89: Organização | E89: Associação Cultural Artistica Cine favela | F89: Inclusão Digital de Pessoas Idosas no Cine Favela Heliópolis | G89: Eixo I: Promoção, Assistência e Desenvolvimento Social | H89: 1111410.1 | I89: São Paulo/SP | J89: DRADS CAPITAL EM SÃO PAULO | K89: Geneci Ledo de Tulio | L89: cinefavela@gmail.com | M89: 45307 | N89: Pré-Classificado | O89: Falta de Informação do envelope | P89: Plano de Trabalho sem n° de páginas | Q89: 317 | S89: 239 | T89: 266 | AE89: =COUNT(Q89:AD89) -> 3 | AF89: =AVERAGE(Q89:AD89) -> 274 | AG89: =IF(AF89>=$AG$1,"APROVADO","REPROVADO") -> APROVADO
B90: 86 | C90: 086/23 | D90: Organização | E90: Grupo de Apoio dona Benedita | F90: Mantendo Vivos Nossos Sorrisos | G90: Eixo I: Promoção, Assistência e Desenvolvimento Social | H90: 102600 | I90: Sete Barras | J90: DRADS VALE DO RIBEIRA EM REGISTRO | K90: Micaela Oliveira | L90: casaamigosdasb@gmail.com | M90: 45307 | N90: Classificado | Q90: 309 | R90: 203 | S90: 242 | AE90: =COUNT(Q90:AD90) -> 3 | AF90: =AVERAGE(Q90:AD90) -> 251.33333 | AG90: =IF(AF90>=$AG$1,"APROVADO","REPROVADO") -> APROVADO
B91: 87 | C91: 087/23 | D91: Organização | E91: Lar dos Velhinhos da Sociedade São Vicente de Paulo | F91: Vida Plena - Cuidando do Amanhã | G91: Eixo I: Promoção, Assistência e Desenvolvimento Social | H91: 48136.8 | I91: Santo Antonio da Alegria/SP | J91: DRADS RIBEIRÃO PRETO | K91: Luiz Ricardo dos Santos | L91: lardosvelhinhossssvp2015@hotmail.com | M91: 45307 | N91: Pré-Classificado | O91: Falta de Informação do envelope | P91: Plano e Pendrive OK (verificar o formato do Plano de Trabalho) | Q91: 305 | R91: 191 | AD91: 340 | AE91: =COUNT(Q91:AD91) -> 3 | AF91: =AVERAGE(Q91:AD91) -> 278.66667 | AG91: =IF(AF91>=$AG$1,"APROVADO","REPROVADO") -> APROVADO
B92: 88 | C92: 088/23 | D92: Prefeitura | E92: Municipal de Itapira | F92: Assistência Fisioterapêutica Domiciliar em Idosos Acamadoa | G92: - | H92: 394820 | I92: Itapira/SP | J92: DRADS MOGIANA EM SÃO JOÃO DA BOA VISTA | K92: Márcia de Jesus de Oliveira | L92: adm@pmaparecidadoeste.sp.gov.br | M92: 45307 | N92: Reprovado | O92: Aquisição de Veiculo | AF92: =AVERAGE(Q92:AD92) -> #DIV/0! | AG92: =IF(AF92>=$AG$1,"APROVADO","REPROVADO") -> #DIV/0!
B93: 89 | C93: 089/23 | D93: Prefeitura | E93: Municipal Santa Cruz da Esperança | F93: Trilhas das Memorias | G93: Eixo VII: Cultura, Esporte, Turismo e Lazer | H93: 434000 | I93: Santa Cruz da Esperança/SP | J93: DRADS RIBEIRÃO PRETO | K93: Celia Cristina Cestari | L93: gabinetedoprefeito@itapira.sp.gov.br | M93: 45307 | N93: Pré-Classificado | O93: PDF sem assinatura e rubrica | Q93: 259 | V93: 258 | W93: 220 | AE93: =COUNT(Q93:AD93) -> 3 | AF93: =AVERAGE(Q93:AD93) -> 245.66667 | AG93: =IF(AF93>=$AG$1,"APROVADO","REPROVADO") -> APROVADO
B94: 90 | C94: 090/23 | D94: Organização | E94: Associação Cultural e Social do Idoso Criança e Adolescente | F94: Exposição do Samba - Velha Guarda | G94: Eixo VII: Cultura, Esporte, Turismo e Lazer | H94: 630000 | I94: São Paulo/SP | J94: DRADS CAPITAL EM SÃO PAULO | K94: Emerson de Godoy Costas dos Santos | L94: coordenacaoacsica@hotmail.com | M94: 45307 | N94: Desclassificado | O94: Plano de Trabalho sem Rubricar | AF94: =AVERAGE(Q94:AD94) -> #DIV/0! | AG94: =IF(AF94>=$AG$1,"APROVADO","REPROVADO") -> #DIV/0!
B95: 91 | C95: 091/23 | D95: Organização | E95: Associação Beneficiente Bom Jesus | F95: Viver Bem | G95: Eixo VII: Cultura, Esporte, Turismo e Lazer | H95: 50000 | I95: Pilar do Sul/SP | J95: DRADS SOROCABA | K95: Sergio Luis Ribeiro | L95: larbomjesus.pilardosul@gmail.com | M95: 45307 | N95: Desclassificado | O95: Plano de Trabalho sem Rubricar | AF95: =AVERAGE(Q95:AD95) -> #DIV/0! | AG95: =IF(AF95>=$AG$1,"APROVADO","REPROVADO") -> #DIV/0!
B96: 92 | C96: 092/23 | D96: Organização | E96: Projeto Gente Nova | F96: Envelhecência: Envelhecer com Dignidade | G96: Eixo I: Promoção, Assistência e Desenvolvimento Social | H96: 500000 | I96: Campinas/SP | J96: DRADS CAMPINAS | K96: Claudio Raizaro | L96: progen@progen.gor.vbr | M96: 45307 | N96: Classificado | Q96: 295 | R96: 175 | S96: 241 | AE96: =COUNT(Q96:AD96) -> 3 | AF96: =AVERAGE(Q96:AD96) -> 237 | AG96: =IF(AF96>=$AG$1,"APROVADO","REPROVADO") -> APROVADO
B97: 93 | C97: 093/23 | D97: Organização | E97: Associação Comunidade em Ação êxodo | F97: Sênior healt: espaço de práticas integrativas | G97: Eixo VII: Cultura, Esporte, Turismo e Lazer | H97: 88496 | I97: Bauru/SP | J97: DRADS BAURU | K97: Arianni Pereira Milano | L97: instituicaoacae@yahoo.com.br | M97: 45307 | N97: Pré-Classificado | O97: PDF sem assinar e rubricar | Q97: 313 | R97: 239 | AD97: 340 | AE97: =COUNT(Q97:AD97) -> 3 | AF97: =AVERAGE(Q97:AD97) -> 297.33333 | AG97: =IF(AF97>=$AG$1,"APROVADO","REPROVADO") -> APROVADO
B98: 94 | C98: 094/23 | D98: Organização | E98: Caritas Diocesana de Bauru | F98: Saúde na Melhor Idade | G98: Eixo VII: Cultura, Esporte, Turismo e Lazer | H98: 60000 | I98: Bauru/SP | J98: DRADS BAURU | K98: Osvaldo Aparecido Hudinik | L98: coordenacao@caritasbauru.org.br | M98: 45307 | N98: Pré-Classificado | O98: Falta de Informação do envelope | P98: Plano de Trabalho sem n° de páginas | Q98: 310 | S98: 248 | T98: 262 | AE98: =COUNT(Q98:AD98) -> 3 | AF98: =AVERAGE(Q98:AD98) -> 273.33333 | AG98: =IF(AF98>=$AG$1,"APROVADO","REPROVADO") -> APROVADO
B99: 95 | C99: 095/23 | D99: Organização | E99: Associação Bauruense de Apoio e Assistência ao Renal Crônico - ABREC | F99: Apoio e Cuidado para Viver Melhor | G99: Eixo I: Promoção, Assistência e Desenvolvimento Social | H99: 40000 | I99: Bauru/SP | J99: DRADS BAURU | K99: Daiane Cordeiro de Mattos Souza | L99: abrec.seid@gmail.com | M99: 45307 | N99: Classificado | Q99: 273 | R99: 275 | S99: 270 | AE99: =COUNT(Q99:AD99) -> 3 | AF99: =AVERAGE(Q99:AD99) -> 272.66667 | AG99: =IF(AF99>=$AG$1,"APROVADO","REPROVADO") -> APROVADO
B100: 96 | C100: 096/23 | D100: Organização | E100: Rede do Câncer de Lençois Paulista | F100: Projetos que contemplem o fornecimento de próteses, órteses e outros recursos relativos ao tratamento, habilitação ou reabilitação de pessoas idosas, conforme artigo 15, 2º da lei federal nº 10.741/2003 e suas alterações | G100: Eixo II: Sáude | H100: 73150 | I100: Lençois Paulista/SP | J100: DRADS BAURU | K100: Angela Silvana Fermino | L100: rededocancerrlp@Gmail.com | M100: 45307 | N100: Classificado | Q100: 340 | R100: 265 | S100: 264 | AE100: =COUNT(Q100:AD100) -> 3 | AF100: =AVERAGE(Q100:AD100) -> 289.66667 | AG100: =IF(AF100>=$AG$1,"APROVADO","REPROVADO") -> APROVADO
...

Sheet Desclassificado
AF1: 204
B2: CONSELHO ESTADUAL DO IDOSO Rua Boa Vista, 170- CEP 01204-001 - São Paulo-SP Fone 11-2763-8122/2763-8035 cei@desenvolvimentosocial.sp.gov.br
B3: ORGANIZAÇÕES SOCIAIS
C4: Protocolo | D4: OSC/Prefeitura | E4: NOME DO PROPONENTE | F4: NOME DO PROJETO | G4: EIXO | H4: VALOR TOTAL DO PROJETO | I4: MUNICÍPIO | J4: DRADS | K4: Responsável - OSC | L4: EMAIL | M4: ENTREGUE DIA | N4: ETAPA da Análise | O4: PENDÊNCIA | P4: OBS | Q4: NOTA Gilberto | R4: NOTA Erica | S4: NOTA Enizal | T4: NOTA Walkyria | U4: NOTA Elisete | V4: NOTA Adriano | W4: NOTA Paulo Albano | X4: NOTA Alexandra | Y4: NOTA Priscila | Z4: NOTA Leila | AA4: NOTA Vanise | AB4: NOTA Jeverson | AC4: NOTA Cristiane | AD4: NOTA Márcio | AE4: Média | AF4: RESULTADO FINAL
B5: 6 | C5: 006/23 | D5: Organização | E5: Congregação Israelita Paulista | F5: Núcleo de Convivência da Maturidade | G5: Eixo I: Promoção, Assistência e Desenvolvimento Social | H5: 523070 | I5: São Paulo/SP | J5: DRADS CAPITAL EM SÃO PAULO | K5: Laura Feldman | L5: acaosocial@cip.org.br | M5: 45288 | N5: Desclassificado | O5: Plano de Trabalho não está Rubricado | AE5: =AVERAGE(Q5:AD5) -> #DIV/0! | AF5: =IF(AE5>=$AF$1,"APROVADO","REPROVADO") -> #DIV/0!
B6: 21 | C6: 021/23 | D6: Organização | E6: Lar São Vicente de Paulo | F6: Revitalizar Para Melhor Viver | G6: Eixo V: Habitação e Urbanismo | H6: 192880.29 | I6: Santa Cruz do Rio Pardo/SP | J6: DRADS AVARÉ | K6: Acácio Henrique de Lima | L6: s.v.paulo@hotmail.com | M6: 45302 | N6: Desclassificado | O6: Plano de Trabalho não está Rubricado | AE6: =AVERAGE(Q6:AD6) -> #DIV/0! | AF6: =IF(AE6>=$AF$1,"APROVADO","REPROVADO") -> #DIV/0!
B7: 32 | C7: 032/23 | D7: Prefeitura | E7: Municipal São Cetano | F7: Terceira Idade em Movimento | G7: Eixo VII: Cultura, Esporte, Turismo e Lazer | H7: 344990 | I7: São Caetano do Sul/SP | J7: DRADS ABC EM SANTO ANDRÉ | K7: Tatiana | L7: pmbab@Bastos.sp.gov.br | M7: 45303 | N7: Desclassificado | O7: Plano de Trabalho não está Rubricado | AE7: =AVERAGE(Q7:AD7) -> #DIV/0! | AF7: =IF(AE7>=$AF$1,"APROVADO","REPROVADO") -> #DIV/0!
B8: 70 | C8: 070/23 | D8: Organização | E8: Lar dos Velhinhos São Vicente de Paulo | F8: Idoso Jovem | G8: Eixo I: Promoção, Assistência e Desenvolvimento Social | H8: 38337 | I8: Urânia/SP | J8: DRADS FERNANDÓPOLIS | K8: Zélia Souza Silva | L8: lardos velhinhos1@hotmail.com | M8: 45306 | N8: Desclassificado | O8: Sem Pendrive | AE8: =AVERAGE(Q8:AD8) -> #DIV/0! | AF8: =IF(AE8>=$AF$1,"APROVADO","REPROVADO") -> #DIV/0!
B9: 71 | C9: 071/23 | D9: Organização | E9: Lar dos Velhinhos São Vicente de Paulo | F9: Meu Quarto Meus Sonhos | G9: Eixo I: Promoção, Assistência e Desenvolvimento Social | H9: 78212 | I9: Urânia/SP | J9: DRADS FERNANDÓPOLIS | K9: Zélia Souza Silva | L9: lardos velhinhos1@hotmail.com | M9: 45306 | N9: Desclassificado | O9: Sem Pendrive | AE9: =AVERAGE(Q9:AD9) -> #DIV/0! | AF9: =IF(AE9>=$AF$1,"APROVADO","REPROVADO") -> #DIV/0!
B10: 82 | C10: 082/23 | D10: Organização | E10: Vila Vicentina em Brotas | F10: Bem Estar Social aos Idosos (mesas e Cadeiras) | G10: Eixo I: Promoção, Assistência e Desenvolvimento Social | H10: 10000 | I10: Brotas/SP | J10: DRADS PIRACICABA | K10: Neuza Maria Pascoalotti Berto | L10: vilavicentinoembrotas@outlook.com | M10: 45307 | N10: Desclassificado | O10: Sem Pendrive | AE10: =AVERAGE(Q10:AD10) -> #DIV/0! | AF10: =IF(AE10>=$AF$1,"APROVADO","REPROVADO") -> #DIV/0!
B11: 83 | C11: 083/23 | D11: Organização | E11: Vila Vicentina em Brotas | F11: Aconchego aos Idosos (Poltrona do Papai Reclinável) | G11: Eixo I: Promoção, Assistência e Desenvolvimento Social | H11: 10000 | I11: Brotas/SP | J11: DRADS PIRACICABA | K11: Neuza Maria Pascoalotti Berto | L11: vilavicentinoembrotas@outlook.com | M11: 45307 | N11: Desclassificado | O11: Sem Pendrive | AE11: =AVERAGE(Q11:AD11) -> #DIV/0! | AF11: =IF(AE11>=$AF$1,"APROVADO","REPROVADO") -> #DIV/0!
B12: 90 | C12: 090/23 | D12: Organização | E12: Associação Cultural e Social do Idoso Criança e Adolescente | F12: Exposição do Samba - Velha Guarda | G12: Eixo VII: Cultura, Esporte, Turismo e Lazer | H12: 630000 | I12: São Paulo/SP | J12: DRADS CAPITAL EM SÃO PAULO | K12: Emerson de Godoy Costas dos Santos | L12: coordenacaoacsica@hotmail.com | M12: 45307 | N12: Desclassificado | O12: Plano de Trabalho não está Rubricado | AE12: =AVERAGE(Q12:AD12) -> #DIV/0! | AF12: =IF(AE12>=$AF$1,"APROVADO","REPROVADO") -> #DIV/0!
B13: 91 | C13: 091/23 | D13: Organização | E13: Associação Beneficiente Bom Jesus | F13: Viver Bem | G13: Eixo VII: Cultura, Esporte, Turismo e Lazer | H13: 50000 | I13: Pilar do Sul/SP | J13: DRADS SOROCABA | K13: Sergio Luis Ribeiro | L13: larbomjesus.pilardosul@gmail.com | M13: 45307 | N13: Desclassificado | O13: Plano de Trabalho não está Rubricado | AE13: =AVERAGE(Q13:AD13) -> #DIV/0! | AF13: =IF(AE13>=$AF$1,"APROVADO","REPROVADO") -> #DIV/0!
B14: 102 | C14: 102/23 | D14: Organização | E14: Vila Vicentina AraraquaraObra Unida á Sociedade de São Vicente de Paulo | F14: Alimentação Fundamental | G14: Eixo I: Promoção, Assistência e Desenvolvimento Social | H14: 120000 | I14: Araraquara/SP | J14: DRADS ARARAQUARA | K14: Nathan Reinaldo Carvalho Silva | L14: servicosocial@vilavicentinaararaquara.org.br | M14: 45307 | N14: Desclassificado | O14: Sem Pendrive | AE14: =AVERAGE(Q14:AD14) -> #DIV/0! | AF14: =IF(AE14>=$AF$1,"APROVADO","REPROVADO") -> #DIV/0!
B15: 123 | C15: 123/23 | D15: Organização | E15: Associação União Beneficiente das Irmãs de São Vicente de Paulo de Gysegem | F15: Projeto Bem Estar das Instalações da Pessoa Idosa em ILPI | G15: Eixo I: Promoção, Assistência e Desenvolvimento Social | H15: 2241683 | I15: Jundiaí/SP | J15: DRADS CAMPINAS | K15: Neide Calandrin | L15: ssocial.lar@vicentinas.com.br | M15: 45308 | N15: Desclassificado | O15: Sem Pendrive | AE15: =AVERAGE(Q15:AD15) -> #DIV/0! | AF15: =IF(AE15>=$AF$1,"APROVADO","REPROVADO") -> #DIV/0!
B16: 124 | C16: 124/23 | D16: Organização | E16: Instituto Reviver de Biritiba Mirim | F16: Vida Ativa com Saúde | G16: Eixo I: Promoção, Assistência e Desenvolvimento Social | H16: 373709.52 | I16: Biritiba Mirim/SP | J16: DRADS SPL EM MOGI DAS CRUZES | K16: Beatriz | L16: reviverbm@gmail.com | M16: 45308 | N16: Desclassificado | O16: Plano de Trabalho não está Rubricado | AE16: =AVERAGE(Q16:AD16) -> #DIV/0! | AF16: =IF(AE16>=$AF$1,"APROVADO","REPROVADO") -> #DIV/0!
... B67: 543 | C67: 543/23 | D67: Organização | E67: Cáritas Paroquial Nossa Mãe dos Homens e Santo Antônio de Pádua | F67: Ser Pleno | G67: Eixo I: Promoção, Assistência e Desenvolvimento Social | H67: 500000 | I67: Louveira/SP | J67: DRADS CAMPINAS | K67: Fabiana Cristina | L67: coordenacaocaritasparoquial@gmail.com | M67: 45322 | N67: Desclassificado | O67: Plano de Trabalho não está Rubricado | AE67: =AVERAGE(Q67:AD67) -> #DIV/0! | AF67: =IF(AE67>=$AF$1,"APROVADO","REPROVADO") -> #DIV/0!
B68: 559 | C68: 559/23 | D68: Organização | E68: Coordenação Regional das Obras de Promoção Humanas - CROPH | F68: - | G68: - | H68: 0 | I68: São Paulo/SP | J68: DRADS CAPITAL EM SÃO PAULO | K68: Carlota Cardoso da Silva | L68: contato@croph.org.br | M68: 45322 | N68: Desclassificado | O68: Plano de Trabalho não está Rubricado | P68: Sem Pendrive e faltando várias informaçãoes no Plano de Trabalho | AE68: =AVERAGE(Q68:AD68) -> #DIV/0! | AF68: =IF(AE68>=$AF$1,"APROVADO","REPROVADO") -> #DIV/0!
B69: 560 | C69: 560/23 | D69: Organização | E69: Associação Cuidado ao Próximo | F69: - | G69: - | H69: - | I69: São Paulo/SP | J69: DRADS CAPITAL EM SÃO PAULO | K69: Marcos Antônio Bamban Pereira | L69: cuidadoaoproximo@gmail.com | M69: 45322 | N69: Desclassificado | O69: Plano de Trabalho não está Rubricado | AE69: =AVERAGE(Q69:AD69) -> #DIV/0! | AF69: =IF(AE69>=$AF$1,"APROVADO","REPROVADO") -> #DIV/0!
B70: 573 | C70: 571/23 | D70: Organização | E70: Instituto Futuro | F70: Cultura e Ação | G70: Eixo VII: Cultura, Esporte, Turismo e Lazer | H70: 1214351.3 | I70: São Paulo/SP | J70: DRADS CAPITAL EM SÃO PAULO | K70: Maria Lúcia dos Santos Correia | L70: institutofuturo@uol.com.br | M70: 45322 | N70: Desclassificado | O70: Sem Pendrive | AE70: =AVERAGE(Q70:AD70) -> #DIV/0! | AF70: =IF(AE70>=$AF$1,"APROVADO","REPROVADO") -> #DIV/0!
B71: 574 | C71: 572/23 | D71: Organização | E71: Associação Beneficente da Comunidade Nossa Senhora de Fátima de Bertioga | F71: Nossa Senhora de Fátima - II | G71: Eixo VII: Cultura, Esporte, Turismo e Lazer | H71: 388400 | I71: Bertioga/SP | J71: DRADS BAIXADA SANTISTA EM SANTOS | K71: Protocolo 572/23 | L71: associacao.bertioga@gmail.com | M71: 45322 | N71: Desclassificado | O71: Plano de Trabalho não está Rubricado | AE71: =AVERAGE(Q71:AD71) -> #DIV/0! | AF71: =IF(AE71>=$AF$1,"APROVADO","REPROVADO") -> #DIV/0!
B72: 575 | C72: 573/23 | D72: Organização | E72: Associação Beneficente da Comunidade Nossa Senhora de Fátima de Bertioga | F72: Nossa Senhora de Fátima - I | G72: Eixo VII: Cultura, Esporte, Turismo e Lazer | H72: 342980 | I72: Bertioga/SP | J72: DRADS BAIXADA SANTISTA EM SANTOS | K72: Expedito Antônio dos Santos | L72: associacao.bertioga@gmail.com | M72: 45322 | N72: Desclassificado | O72: Plano de Trabalho não está Rubricado | AE72: =AVERAGE(Q72:AD72) -> #DIV/0! | AF72: =IF(AE72>=$AF$1,"APROVADO","REPROVADO") -> #DIV/0!
B73: 576 | C73: 574/23 | D73: Organização | E73: Instituto Luz do Amanhã | F73: Casa Azul | G73: Eixo I: Promoção, Assistência e Desenvolvimento Social | H73: 161302.98 | I73: São Paulo/SP | J73: DRADS CAPITAL EM SÃO PAULO | K73: Roberto Rodrigues | L73: contato@luzdoamanhã.org | M73: 45322 | N73: Desclassificado | O73: Plano de Trabalho não está Rubricado | AE73: =AVERAGE(Q73:AD73) -> #DIV/0! | AF73: =IF(AE73>=$AF$1,"APROVADO","REPROVADO") -> #DIV/0!
B74: 578 | C74: 576/23 | D74: Organização | E74: Associação Beneficente da Comunidade Nossa Senhora de Fátima de Bertioga | F74: Nossa Senhora de Fátima - III | G74: Eixo VII: Cultura, Esporte, Turismo e Lazer | H74: 356288 | I74: Bertioga/SP | J74: DRADS BAIXADA SANTISTA EM SANTOS | K74: Protocolo 573/23 | L74: associacao.bertioga@gmail.com | M74: 45322 | N74: Desclassificado | O74: Plano de Trabalho não está Rubricado | P74: Plano sem Valor Total | AE74: =AVERAGE(Q74:AD74) -> #DIV/0! | AF74: =IF(AE74>=$AF$1,"APROVADO","REPROVADO") -> #DIV/0!
B75: 579 | C75: 577/23 | D75: Organização | E75: Associação Beneficente Esperança Viva | F75: Reviver - III | G75: Eixo VII: Cultura, Esporte, Turismo e Lazer | H75: 517300 | I75: São Paulo/SP | J75: DRADS CAPITAL EM SÃO PAULO | K75: Anderson Aparecido dos Santos | L75: abeviva@gmail.com | M75: 45322 | N75: Desclassificado | O75: Plano de Trabalho não está Rubricado | AE75: =AVERAGE(Q75:AD75) -> #DIV/0! | AF75: =IF(AE75>=$AF$1,"APROVADO","REPROVADO") -> #DIV/0!
B76: 580 | C76: 578/23 | D76: Organização | E76: Associação Beneficente Esperança Viva | F76: Reviver - II | G76: Eixo VII: Cultura, Esporte, Turismo e Lazer | H76: 472580 | I76: São Paulo/SP | J76: DRADS CAPITAL EM SÃO PAULO | K76: Anderson Aparecido dos Santos | L76: abeviva@gmail.com | M76: 45322 | N76: Desclassificado | O76: Plano de Trabalho não está Rubricado | P76: Divergência no nome do Projeto | AE76: =AVERAGE(Q76:AD76) -> #DIV/0! | AF76: =IF(AE76>=$AF$1,"APROVADO","REPROVADO") -> #DIV/0!
B77: 581 | C77: 579/23 | D77: Organização | E77: Associação Cultural Toca da Onça | F77: Vida é Movimento e Movimento é Vida | G77: Eixo VII: Cultura, Esporte, Turismo e Lazer | H77: 811992.39 | I77: São Paulo/SP | J77: DRADS CAPITAL EM SÃO PAULO | K77: Antonio Luiz de Almeida Francisco | L77: associacaotocadaonca@gmail.com | M77: 45322 | N77: Desclassificado | O77: Plano de Trabalho não está Rubricado | AE77: =AVERAGE(Q77:AD77) -> #DIV/0! | AF77: =IF(AE77>=$AF$1,"APROVADO","REPROVADO") -> #DIV/0!
B78: 582 | C78: 580/23 | D78: Organização | E78: Negritute Futebol Clube | F78: Copa Negritude Master 60 Mais | G78: Eixo VII: Cultura, Esporte, Turismo e Lazer | H78: 780717.03 | I78: São Paulo/SP | J78: DRADS CAPITAL EM SÃO PAULO | K78: José Roberto de Andrade | L78: joser.andrade8@gmail.com | M78: 45322 | N78: Desclassificado | O78: Plano de Trabalho não está Rubricado | AE78: =AVERAGE(Q78:AD78) -> #DIV/0! | AF78: =IF(AE78>=$AF$1,"APROVADO","REPROVADO") -> #DIV/0!
B79: 583 | C79: 581/23 | D79: Organização | E79: Negritute Futebol Clube | F79: Esporte para Todos | G79: Eixo VII: Cultura, Esporte, Turismo e Lazer | H79: 780717.03 | I79: São Paulo/SP | J79: DRADS CAPITAL EM SÃO PAULO | K79: José Roberto de Andrade | L79: joser.andrade8@gmail.com | M79: 45322 | N79: Desclassificado | O79: Plano de Trabalho não está Rubricado | AE79: =AVERAGE(Q79:AD79) -> #DIV/0! | AF79: =IF(AE79>=$AF$1,"APROVADO","REPROVADO") -> #DIV/0!
B80: 584 | C80: 582/23 | D80: Organização | E80: Instituto Mãos e Gratidão | F80: Projeto Mais vida | G80: Eixo II: Sáude | H80: 845957.38 | I80: São Paulo/SP | J80: DRADS CAPITAL EM SÃO PAULO | K80: Wagner de Souza Silva | L80: institutomaosegratidao@gmail.com | M80: 45322 | N80: Desclassificado | O80: Plano de Trabalho não está Rubricado | P80: Divergência de Eixo | AE80: =AVERAGE(Q80:AD80) -> #DIV/0! | AF80: =IF(AE80>=$AF$1,"APROVADO","REPROVADO") -> #DIV/0!
B81: 595 | C81: 593/23 | D81: Organização | E81: Instituto Nelf Ruah | F81: Caminhos da Longevidade III | G81: Eixo VII: Cultura, Esporte, Turismo e Lazer | H81: 367680 | I81: São Paulo/SP | J81: DRADS CAPITAL EM SÃO PAULO | K81: Luiciana Nascimento Tagliari | L81: institutonelfruah@gmail.com | M81: 45322 | N81: Desclassificado | O81: Plano de Trabalho não está Rubricado | AE81: =AVERAGE(Q81:AD81) -> #DIV/0! | AF81: =IF(AE81>=$AF$1,"APROVADO","REPROVADO") -> #DIV/0!
B82: 596 | C82: 594/23 | D82: Prefeitura | E82: Municipal de Guaira | F82: Viver com Qualidade de Vida na Melhor Idade | G82: - | H82: 265000 | I82: Guairá/SP | J82: DRADS BARRETOS | K82: Silmara Aparecida dos Reis Cipriano | L82: dadis@guaira.sp.gov.br | M82: 45322 | N82: Desclassificado | O82: Plano de Trabalho não está Rubricado | AE82: =AVERAGE(Q82:AD82) -> #DIV/0! | AF82: =IF(AE82>=$AF$1,"APROVADO","REPROVADO") -> #DIV/0!
B83: 597 | C83: 595/23 | D83: Organização | E83: União da Fé | F83: Arte em Movimento | G83: Eixo VII: Cultura, Esporte, Turismo e Lazer | H83: 1819351.3 | I83: São Paulo/SP | J83: DRADS CAPITAL EM SÃO PAULO | K83: Felipe Pereira Bruno | L83: prfelipepereira87@gmail.com | M83: 45322 | N83: Desclassificado | O83: Sem Pendrive | AE83: =AVERAGE(Q83:AD83) -> #DIV/0! | AF83: =IF(AE83>=$AF$1,"APROVADO","REPROVADO") -> #DIV/0!
B84: 598 | C84: 596/23 | D84: Organização | E84: Instituto Social Maris | F84: O Tempo não para, vamos Viver a Melhor Idade | G84: Eixo VII: Cultura, Esporte, Turismo e Lazer | H84: 1134197.6 | I84: São Paulo/SP | J84: DRADS CAPITAL EM SÃO PAULO | K84: Izimares | L84: institutosocial.maris@gmail.com | M84: 45322 | N84: Desclassificado | O84: Plano de Trabalho não está Rubricado | AE84: =AVERAGE(Q84:AD84) -> #DIV/0! | AF84: =IF(AE84>=$AF$1,"APROVADO","REPROVADO") -> #DIV/0!
B85: 599 | C85: 597/23 | D85: Organização | E85: Agape | F85: Terceira Idade Cultura e Ação | G85: Eixo VII: Cultura, Esporte, Turismo e Lazer | H85: 1214351.3 | I85: São Paulo/SP | J85: DRADS CAPITAL EM SÃO PAULO | K85: Ricardo Pereira | L85: admagape1@gmail.com | M85: 45322 | N85: Desclassificado | O85: Sem Pendrive | AE85: =AVERAGE(Q85:AD85) -> #DIV/0! | AF85: =IF(AE85>=$AF$1,"APROVADO","REPROVADO") -> #DIV/0!
B86: 600 | C86: 598/23 | D86: Organização | E86: Clube de mães | F86: Cultuta e Arte | G86: Eixo VII: Cultura, Esporte, Turismo e Lazer | H86: 1819351.3 | I86: São Paulo/SP | J86: DRADS CAPITAL EM SÃO PAULO | K86: Maria de Fatima de Sousa dos Santos | L86: correialsantos@gmail.com | M86: 45322 | N86: Desclassificado | O86: Sem Pendrive | AE86: =AVERAGE(Q86:AD86) -> #DIV/0! | AF86: =IF(AE86>=$AF$1,"APROVADO","REPROVADO") -> #DIV/0!
B87: 601 | C87: 599/23 | D87: Organização | E87: Projeto Missão Amar em Cristo | F87: Terceira Idade em Movimento | G87: Eixo VII: Cultura, Esporte, Turismo e Lazer | H87: 1214351.3 | I87: São Paulo/SP | J87: DRADS CAPITAL EM SÃO PAULO | K87: Andre Aparecida Santos Quintiliano Oliveira | L87: acmeireli@gmail.com | M87: 45322 | N87: Desclassificado | O87: Sem Pendrive | AE87: =AVERAGE(Q87:AD87) -> #DIV/0! | AF87: =IF(AE87>=$AF$1,"APROVADO","REPROVADO") -> #DIV/0!
B88: 602 | C88: 600/23 | D88: Organização | E88: União Popular de Moradia Adão Manoel da Silva | F88: Nucleo de Convivio Social para Idosos "Carpe Diem" | G88: Eixo I: Promoção, Assistência e Desenvolvimento Social | H88: 2500000 | I88: São Paulo/SP | J88: DRADS CAPITAL EM SÃO PAULO | K88: Vera Lucia Alves | L88: recursoshumanosadaomanoel@hotmail.com | M88: 45322 | N88: Desclassificado | O88: Plano de Trabalho não está Rubricado | AE88: =AVERAGE(Q88:AD88) -> #DIV/0! | AF88: =IF(AE88>=$AF$1,"APROVADO","REPROVADO") -> #DIV/0!
B89: 606 | C89: 604/23 | D89: Prefeitura | E89: Municipal de Osasco | F89: Projeto: Fala Musical | G89: Eixo I: Promoção, Assistência e Desenvolvimento Social | H89: 91992 | I89: Osasco/SP | J89: DRADS SPO EM OSASCO | K89: Rogério Lins Wanderley | L89: gabinete.sas@osasco.sp.gov.br | M89: 45322 | N89: Desclassificado | O89: Plano de Trabalho não está Rubricado | AE89: =AVERAGE(Q89:AD89) -> #DIV/0! | AF89: =IF(AE89>=$AF$1,"APROVADO","REPROVADO") -> #DIV/0!
B90: 607 | C90: 605/23 | D90: Prefeitura | E90: Municipal de Osasco | F90: Aprender para Melhor Cuidar | G90: Eixo III: Educação | H90: 184320 | I90: Osasco/SP | J90: DRADS SPO EM OSASCO | K90: Rogério Lins Wanderley | L90: gabinete.sas@osasco.sp.gov.br | M90: 45322 | N90: Desclassificado | O90: Plano de Trabalho não está Rubricado | AE90: =AVERAGE(Q90:AD90) -> #DIV/0! | AF90: =IF(AE90>=$AF$1,"APROVADO","REPROVADO") -> #DIV/0!
B91: 608 | C91: 606/23 | D91: Prefeitura | E91: Municipal de Osasco | F91: Aquisição de Transporte Adaptado | G91: Eixo I: Promoção, Assistência e Desenvolvimento Social | H91: 303333.33 | I91: Osasco/SP | J91: DRADS SPO EM OSASCO | K91: Rogério Lins Wanderley | L91: gabinete.sas@osasco.sp.gov.br | M91: 45322 | N91: Desclassificado | O91: Plano de Trabalho não está Rubricado | AE91: =AVERAGE(Q91:AD91) -> #DIV/0! | AF91: =IF(AE91>=$AF$1,"APROVADO","REPROVADO") -> #DIV/0!
B92: 610 | C92: 608/23 | D92: Organização | E92: Associação Cultural e social do Idoso Criança e Adolescente | F92: Exposição do Samba - Velha Guarda | G92: Eixo VII: Cultura, Esporte, Turismo e Lazer | H92: 630000 | I92: São Paulo/SP | J92: DRADS CAPITAL EM SÃO PAULO | K92: Emerson de Godoy Costas dos Santos | L92: coordenacaoacsica@hotmail.com | M92: 45322 | N92: Desclassificado | O92: Plano de Trabalho não está Rubricado Sem Pendrive | P92: Projeto igual ao Protocolo n° 090/23 | AE92: =AVERAGE(Q92:AD92) -> #DIV/0! | AF92: =IF(AE92>=$AF$1,"APROVADO","REPROVADO") -> #DIV/0!
B93: 611 | C93: 609/23 | D93: Organização | E93: Associação Cultural e social do Idoso Criança e Adolescente | F93: Lugar da Melhor Idade | G93: Eixo I: Promoção, Assistência e Desenvolvimento Social | H93: 950000 | I93: São Paulo/SP | J93: DRADS CAPITAL EM SÃO PAULO | K93: Emerson de Godoy Costas dos Santos | L93: coordenacaoacsica@hotmail.com | M93: 45322 | N93: Desclassificado | O93: Plano de Trabalho não está Rubricado | AE93: =AVERAGE(Q93:AD93) -> #DIV/0! | AF93: =IF(AE93>=$AF$1,"APROVADO","REPROVADO") -> #DIV/0!
B94: 612 | C94: 610/23 | D94: Organização | E94: ASSOCIAÇÃO Viver Bem no Centro | F94: Projeto CDC – Cuidando de quem cuidou – Centro de Convivencia de Fortalecimento de Vínculos para Idosos | G94: Eixo I: Promoção, Assistência e Desenvolvimento Social | H94: 0 | I94: São Paulo/SP | J94: DRADS CAPITAL EM SÃO PAULO | K94: Fabiula | L94: avbc2013@gmail.com | M94: 45322 | N94: Desclassificado | O94: Plano de Trabalho não está Rubricado | P94: Sem valor no plano de trabalho | AE94: =AVERAGE(Q94:AD94) -> #DIV/0! | AF94: =IF(AE94>=$AF$1,"APROVADO","REPROVADO") -> #DIV/0!
B95: 392 | C95: 392/23 | D95: Prefeitura | E95: Municipal de Ourinhos | F95: CCI: Centro de Convivência do Idoso | G95: Eixo I: Promoção, Assistência e Desenvolvimento Social | H95: 132794.13 | I95: Ourinhos/SP | J95: DRADS AVARÉ | K95: Ana Caroline Ferreira Olanda | L95: protecaobasicasmads@gmail.com | M95: 45322 | N95: Desclassificado | O95: Enviou 4 Propostas | Q95: 230 | R95: 220 | T95: 207 | AE95: =AVERAGE(Q95:AD95) -> 219 | AF95: =IF(AE95>='Aprovados CAC'!$AR$1,"APROVADO","REPROVADO") -> APROVADO
D109: Tudo OK
D110: Desclassificado e Reprovado
D111: Aguardando Correção (classificado)
D112: Pré-Classicado (falta 1 nota)
D113: Classificado falta nota para fechar

Sheet Reprovados
AF1: 204
B2: CONSELHO ESTADUAL DO IDOSO Rua Boa Vista, 170- CEP 01204-001 - São Paulo-SP Fone 11-2763-8122/2763-8035 cei@desenvolvimentosocial.sp.gov.br
B3: ORGANIZAÇÕES SOCIAIS
C4: Protocolo | D4: OSC/Prefeitura | E4: NOME DO PROPONENTE | F4: NOME DO PROJETO | G4: EIXO | H4: VALOR TOTAL DO PROJETO | I4: MUNICÍPIO | J4: DRADS | K4: Responsável - OSC | L4: EMAIL | M4: ENTREGUE DIA | N4: ETAPA da Análise | O4: PENDÊNCIA | P4: OBS | Q4: NOTA Gilberto | R4: NOTA Erica | S4: NOTA Enizal | T4: NOTA Walkyria | U4: NOTA Elisete | V4: NOTA Adriano | W4: NOTA Paulo Albano | X4: NOTA Alexandra | Y4: NOTA Priscila | Z4: NOTA Leila | AA4: NOTA Vanise | AB4: NOTA Jeverson | AC4: NOTA Cristiane | AD4: NOTA Márcio | AE4: Média | AF4: RESULTADO FINAL
B5: 30 | C5: 030/23 | D5: Prefeitura | E5: Municipal de Bastos | F5: Idoso em Movimento | G5: Eixo I: Promoção, Assistência e Desenvolvimento Social | H5: 610060.4 | I5: Bastos/SP | J5: DRADS MARÍLIA | K5: Luzia Kiyoko Honda | L5: semas@riopreto.sp.gov.br | M5: 45303 | N5: Reprovado | O5: Edital não Contempla Aquisição de Veiculo | Q5: 0 | R5: 29 | S5: 44 | AE5: =AVERAGE(Q5:AD5) -> 24.333333 | AF5: =IF(AE5>=$AF$1,"APROVADO","REPROVADO") -> REPROVADO
B6: 31 | C6: 031/23 | D6: Prefeitura | E6: Municipal de Bastos | F6: Longevidade Ativa e Protegida | G6: Eixo I: Promoção, Assistência e Desenvolvimento Social | H6: 160528.4 | I6: Bastos/SP | J6: DRADS MARÍLIA | K6: Luzia Kiyoko Honda | L6: pmbab@Bastos.sp.gov.br | M6: 45303 | N6: Reprovado | O6: Edital não Contempla Aquisição de Veiculo | Q6: 0 | R6: 169 | S6: 195 | T6: 206 | AE6: =AVERAGE(Q6:AD6) -> 142.5 | AF6: =IF(AE6>=$AF$1,"APROVADO","REPROVADO") -> REPROVADO
B7: 38 | C7: 038/23 | D7: Organização | E7: Lar Fraterno São Vicente de Apiaí | F7: Mais conforto | G7: Eixo II: Sáude | H7: 180000 | I7: Apiaí/SP | J7: DRADS ITAPEVA | K7: Alaíme Yuki monteiro Takiguchi Correa | L7: asiloapiai@hotmail.com | M7: 45303 | N7: Reprovado | O7: Faltou Preencher os Itens ns° 6, 10,11 e 12 do Plano de Trabalho | Q7: 332 | S7: 200 | T7: 0 | AE7: =AVERAGE(Q7:AD7) -> 177.33333 | AF7: =IF(AE7>=$AF$1,"APROVADO","REPROVADO") -> REPROVADO
B8: 50 | C8: 050/23 | D8: Prefeitura | E8: Municipal de Nantes | F8: Bem Estar na Melhor Idade | G8: Eixo I: Promoção, Assistência e Desenvolvimento Social | H8: 331000 | I8: Nantes/SP | J8: DRADS ALTA SOROCABANA EM PRESIDENTE PRUDENTE | K8: Aline Fernanda de Jesus Souza | L8: protecaosocialespecial@votuporanga.sp.gov.br | M8: 45303 | N8: Reprovado | O8: Edital não Contempla Aquisição de Veiculo | Q8: 0 | R8: 188 | S8: 243 | T8: 0 | AE8: =AVERAGE(Q8:AD8) -> 107.75 | AF8: =IF(AE8>=$AF$1,"APROVADO","REPROVADO") -> REPROVADO
B9: 73 | C9: 073/23 | D9: Organização | E9: Registro Conselho Municipal - ARTGYM - LTDA | F9: Estímulos da Sinapse Neurológica para a Saúde física e Mental, por meio da Dança e do Movimento Ginástico Sistematizados para a Melhor Idade de Araraquara-SP | G9: Eixo VII: Cultura, Esporte, Turismo e Lazer | H9: 390000 | I9: Araraquara/SP | J9: DRADS ARARAQUARA | K9: Henrique Sanioto | L9: professorsanioto@gmail.com | M9: 45306 | N9: Reprovado | O9: Nota 0 no item 1 Formulário de Avaliação de Projeto (Edital) - CNPJ de Sociedade Empresaria Limitada | R9: 34 | AB9: 0 | AE9: =AVERAGE(Q9:AD9) -> 17 | AF9: =IF(AE9>=$AF$1,"APROVADO","REPROVADO") -> REPROVADO
B10: 88 | C10: 088/23 | D10: Prefeitura | E10: Municipal de Itapira | F10: Assistência Fisioterapêutica Domiciliar em Idosos Acamadoa | G10: - | H10: 394820 | I10: Itapira/SP | J10: DRADS MOGIANA EM SÃO JOÃO DA BOA VISTA | K10: Márcia de Jesus de Oliveira | L10: adm@pmaparecidadoeste.sp.gov.br | M10: 45307 | N10: Reprovado | O10: Edital não Contempla Aquisição de Veiculo | AE10: =AVERAGE(Q10:AD10) -> #DIV/0! | AF10: =IF(AE10>=$AF$1,"APROVADO","REPROVADO") -> #DIV/0!
B11: 105 | C11: 105/23 | D11: Prefeitura | E11: Municipal de Birigui | F11: Projeto Criação Do Centro Inovador De Referência Para Idosos – Grau De Dependência I | G11: Eixo VII: Cultura, Esporte, Turismo e Lazer | H11: 3700000 | I11: Birigui/SP | J11: DRADS ALTA NOROESTE EM ARAÇATUBA | K11: Maria Regina Doná Celestino | L11: centrodia.idoso@birigui.sp.gov.br | M11: 45307 | N11: Reprovado | O11: Edital não Contempla Construção | Q11: 0 | R11: 146 | AE11: =AVERAGE(Q11:AD11) -> 73 | AF11: =IF(AE11>=$AF$1,"APROVADO","REPROVADO") -> REPROVADO
B12: 110 | C12: 110/23 | D12: Organização | E12: Abrigo Vó Tereza | F12: Centro Dia | G12: Eixo I: Promoção, Assistência e Desenvolvimento Social | H12: 2596552.2 | I12: Birigui/SP | J12: DRADS ALTA NOROESTE EM ARAÇATUBA | K12: Rogerio | L12: abrigo_vo_tereza@hotmail.com | M12: 45307 | N12: Reprovado | O12: Edital não Contempla Aquisição de Veiculo | P12: Documento Word (Pendrive) | Q12: 0 | R12: 120 | AE12: =AVERAGE(Q12:AD12) -> 60 | AF12: =IF(AE12>=$AF$1,"APROVADO","REPROVADO") -> REPROVADO
B13: 122 | C13: 122/23 | D13: Organização | E13: Sociedade Beneficiente Rosalia de Castro | F13: Obras de Melhoria das Condições de Habitabilidade e de Suresão de Barreiras Arquitetônicas | G13: Eixo V: Habitação e Urbanismo | H13: 752776.94 | I13: São Paulo/SP | J13: DRADS CAPITAL EM SÃO PAULO | K13: Pablo Valldecabres Polop | L13: presidente@rosaliadecastro.org.br | M13: 45308 | N13: Reprovado | O13: Vários projetos dentro de um Único Plano de Trabalho | Q13: 0 | R13: 187 | AB13: 0 | AE13: =AVERAGE(Q13:AD13) -> 62.333333 | AF13: =IF(AE13>=$AF$1,"APROVADO","REPROVADO") -> REPROVADO
B14: 162 | C14: 162/23 | D14: Organização | E14: Casade Convivencia DR".Mariano Dias" | F14: Projeto Revivendo - Aquisição de Van Adaptada | G14: Eixo I: Promoção, Assistência e Desenvolvimento Social | H14: 328228.66 | I14: Barretos/SP | J14: DRADS BARRETOS | K14: Cristiane Machado Borges Baldúino | L14: abrigomarianodias@yahoo.com.br | M14: 45309 | N14: Reprovado | O14: Edital não Contempla Aquisição de Veiculo | P14: PDF sem rubricas | Q14: 0 | R14: 53 | AE14: =AVERAGE(Q14:AD14) -> 26.5 | AF14: =IF(AE14>=$AF$1,"APROVADO","REPROVADO") -> REPROVADO
B15: 168 | C15: 168/23 | D15: Prefeitura | E15: Municipal de Itararé | F15: Centro de Convivência do Idoso Novo Horizonte | G15: Eixo I: Promoção, Assistência e Desenvolvimento Social | H15: 431920.31 | I15: Itararé/SP | J15: DRADS ITAPEVA | K15: Maria Paula de Nigris Favier | L15: assistencialtejupa@yahoo.com.br | M15: 45310 | N15: Reprovado | O15: Edital não Contempla Construção | Q15: 0 | AE15: =AVERAGE(Q15:AD15) -> 0 | AF15: =IF(AE15>=$AF$1,"APROVADO","REPROVADO") -> REPROVADO
B16: 175 | C16: 175/23 | D16: Organização | E16: Lar São Vicente de Paulo | F16: Construir para Cuidar | G16: Eixo I: Promoção, Assistência e Desenvolvimento Social | H16: 1211418 | I16: Manduri/SP | J16: DRADS AVARÉ | K16: Alessandra Aparecida Vaz de Moraes | L16: Isvp.manduri@hotmail.com | M16: 45310 | N16: Reprovado | O16: Edital não Contempla Construção | Q16: 0 | AE16: =AVERAGE(Q16:AD16) -> 0 | AF16: =IF(AE16>=$AF$1,"APROVADO","REPROVADO") -> REPROVADO
B17: 178 | C17: 178/23 | D17: Prefeitura | E17: Municipal de Igaraçu do Tietê | F17: "Feliz Idade" no Esporte e Lazer: Sem Barreiras para Vencer | G17: Eixo VII: Cultura, Esporte, Turismo e Lazer | H17: 164270 | I17: Igaraçu do Tietê/SP | J17: DRADS BAURU | K17: Gleize Merlím Ovídio | L17: assistencialsocial@paraiso.sp.gov.br | M17: 45314 | N17: Reprovado | O17: Proponete: Conselho Municipal, e não podemos ter parceias com Conselho, apenas OSC ou PM | Q17: 0 | R17: 153 | AB17: 0 | AE17: =AVERAGE(Q17:AD17) -> 51 | AF17: =IF(AE17>=$AF$1,"APROVADO","REPROVADO") -> REPROVADO
B18: 179 | C18: 179/23 | D18: Organização | E18: Associação da APAE de Igaraçu do Tietê | F18: AMOR - Alegria - Movimento - Oportunidade - Respeito | G18: Eixo VII: Cultura, Esporte, Turismo e Lazer | H18: 0 | I18: Igaraçu do Tietê/SP | J18: DRADS BAURU | K18: Anaisa Vinche Vieira | L18: apaeigaracu@hotmail.com | M18: 45314 | N18: Reprovado | O18: Sem Valor Total do Projeto | Q18: 0 | R18: 153 | AB18: 0 | AE18: =AVERAGE(Q18:AD18) -> 51 | AF18: =IF(AE18>=$AF$1,"APROVADO","REPROVADO") -> REPROVADO
B19: 192 | C19: 193/23 | D19: Organização | E19: Associação de Assistência São Vicente de Paulo (Vila São Vicente) | F19: Centro de Cultura Recreação e Lazer (Redescobrir) | G19: Eixo VII: Cultura, Esporte, Turismo e Lazer | H19: 984524.16 | I19: Catanduva/SP | J19: DRADS SÃO JOSÉ DO RIO PRETO | K19: Edson Ferraz | L19: lubaferraz@gmail.com | M19: 45315 | N19: Reprovado | O19: Edital não Contempla Aquisição de Veiculo | Q19: 0 | R19: 145 | AE19: =AVERAGE(Q19:AD19) -> 72.5 | AF19: =IF(AE19>=$AF$1,"APROVADO","REPROVADO") -> REPROVADO
B20: 213 | C20: 214/23 | D20: Organização | E20: Lar dos Velhinhos de Regente Feijó | F20: Bem Estar na Melhor Idade | G20: Eixo I: Promoção, Assistência e Desenvolvimento Social | H20: 300000 | I20: Regente Feijó/SP | J20: DRADS ALTA SOROCABANA EM PRESIDENTE PRUDENTE | K20: Soellyn Omodei Fontes Monção | L20: aidosos@hotmail.com | M20: 45320 | N20: Reprovado | O20: Edital não Contempla Construção | Q20: 0 | R20: 121 | AE20: =AVERAGE(Q20:AD20) -> 60.5 | AF20: =IF(AE20>=$AF$1,"APROVADO","REPROVADO") -> REPROVADO
B21: 216 | C21: 217/23 | D21: Organização | F21: Felicidade não tem idade | G21: Eixo I: Promoção, Assistência e Desenvolvimento Social | H21: 293916.67 | I21: Barretos/SP | J21: DRADS BARRETOS | K21: Marcela Correa de Souza | L21: abavin@hotmail.com | M21: 45320 | N21: Reprovado | O21: Edital não Contempla Aquisição de Veiculo | Q21: 0 | AE21: =AVERAGE(Q21:AD21) -> 0 | AF21: =IF(AE21>=$AF$1,"APROVADO","REPROVADO") -> REPROVADO
B22: 221 | C22: 222/23 | D22: Organização | E22: União Espírita Cachoerense | F22: Lar Nova Era | G22: Eixo I: Promoção, Assistência e Desenvolvimento Social | H22: 2142000 | I22: Cachoeira Paulista/SP | J22: DRADS VALE DO PARAÍBA EM SÃO JOSÉ DOS CAMPOS | K22: Débora Ferreira Comonian | L22: u.e.c.1918@gmail.com | M22: 45320 | N22: Reprovado | O22: Edital não Contempla Construção | Q22: 0 | R22: 34 | AE22: =AVERAGE(Q22:AD22) -> 17 | AF22: =IF(AE22>=$AF$1,"APROVADO","REPROVADO") -> REPROVADO
B23: 223 | C23: 224/23 | D23: Organização | E23: Lar Presbiteriano Lili Ribeiro | F23: Geração de Renda - Acolher e Amparar | G23: Eixo I: Promoção, Assistência e Desenvolvimento Social | H23: 800000 | I23: Ribeirão Preto/SP | J23: DRADS RIBEIRÃO PRETO | K23: Rosangela Aparecida Bellomo Minuti | L23: coordenacao@lardosvelhos.com.br / assitenciasocial@lardosvelhos.com.br | M23: 45320 | N23: Reprovado | O23: Edital não Contempla Construção | Q23: 0 | R23: 0 | AE23: =AVERAGE(Q23:AD23) -> 0 | AF23: =IF(AE23>=$AF$1,"APROVADO","REPROVADO") -> REPROVADO
B24: 226 | C24: 227/23 | D24: Organização | E24: Instituto Pró+Vida São Sebastião | F24: Espaço Pró-Vida | G24: Eixo V: Habitação e Urbanismo | H24: 2500000 | I24: São Sebastião/SP | J24: DRADS VALE DO PARAÍBA EM SÃO JOSÉ DOS CAMPOS | K24: Cristiane Nogueira de Melo | L24: institutopromaisvida@ipvss.org.br | M24: 45320 | N24: Reprovado | O24: Edital não Contempla Construção | Q24: 0 | R24: 0 | AE24: =AVERAGE(Q24:AD24) -> 0 | AF24: =IF(AE24>=$AF$1,"APROVADO","REPROVADO") -> REPROVADO
B25: 236 | C25: 237/23 | D25: Prefeitura | E25: Municipal de Itatinga | F25: Aquisição de Veiculo Automotor (ônibus) | G25: Eixo I: Promoção, Assistência e Desenvolvimento Social | H25: 500000 | I25: Itatinga/SP | J25: DRADS BOTUCATU | K25: João Bosco Borges | L25: secretatia@itatinga.sp.gov.br | M25: 45320 | N25: Reprovado | O25: Edital não Contempla Aquisição de Veiculo | AE25: =AVERAGE(Q25:AD25) -> #DIV/0! | AF25: =IF(AE25>=$AF$1,"APROVADO","REPROVADO") -> #DIV/0!
B26: 237 | C26: 238/23 | D26: Prefeitura | E26: Municipal de Itatinga | F26: Ampliação do Prédio | G26: Eixo I: Promoção, Assistência e Desenvolvimento Social | H26: 900000 | I26: Itatinga/SP | J26: DRADS BOTUCATU | K26: João Bosco Borges | L26: secretatia@itatinga.sp.gov.br | M26: 45320 | N26: Reprovado | O26: Edital não Contempla Construção | Q26: 0 | R26: 40 | AE26: =AVERAGE(Q26:AD26) -> 20 | AF26: =IF(AE26>=$AF$1,"APROVADO","REPROVADO") -> REPROVADO
B27: 247 | C27: 247/23 | D27: Prefeitura | E27: Municipal Cravinhos/SP | F27: Viver | G27: - | H27: 400000 | I27: Cravinhos/SP | J27: DRADS RIBEIRÃO PRETO | K27: Márcio Luís de Lima Barroso | L27: gabinete@dumont.sp.gov.br ou socialdumont@gmail.com | M27: 45320 | N27: Reprovado | O27: Nota 0 nos itens 2 e 5 Formulário de Avaliação de Projeto (Edital) | Q27: 0 | R27: 130 | AE27: =AVERAGE(Q27:AD27) -> 65 | AF27: =IF(AE27>=$AF$1,"APROVADO","REPROVADO") -> REPROVADO
B28: 252 | C28: 252/23 | D28: Prefeitura | E28: Municipal de Barbosa | F28: Aquisição de Veiculo Automotor | G28: Eixo I: Promoção, Assistência e Desenvolvimento Social | H28: 500000 | I28: Barbosa/SP | J28: DRADS ALTA NOROESTE EM ARAÇATUBA | K28: Rodrigo Primo Antunes | L28: social@brodowslki.sp.gov.br | M28: 45320 | N28: Reprovado | O28: Edital não Contempla Aquisição de Veiculo | AE28: =AVERAGE(Q28:AD28) -> #DIV/0! | AF28: =IF(AE28>=$AF$1,"APROVADO","REPROVADO") -> #DIV/0!
B29: 253 | C29: 253/23 | D29: Prefeitura | E29: Municipal de Jaborandi | F29: Centro de Saúde Preventiva do Idoso - Casa Pajé | G29: Eixo II: Sáude | H29: 1050000 | I29: Jaborandi/SP | J29: DRADS BARRETOS | K29: Ana Helena Miranda Marsai Cestaro ou André Yooiti Muramoto | L29: social1321@gmail.com | M29: 45320 | N29: Reprovado | O29: Nota 0 no item 2 Formulário de Avaliação de Projeto (Edital) | Q29: 302 | V29: 0 | AE29: =AVERAGE(Q29:AD29) -> 151 | AF29: =IF(AE29>=$AF$1,"APROVADO","REPROVADO") -> REPROVADO
B30: 255 | C30: 255/23 | D30: Prefeitura | E30: Municipal de Barbosa | F30: Centro de Convivência do Idoso | G30: Eixo I: Promoção, Assistência e Desenvolvimento Social | H30: 1350000 | I30: Barbosa/SP | J30: DRADS ALTA NOROESTE EM ARAÇATUBA | K30: Rodrigo Primo Antunes | L30: gabinete@barbosa.sp.gov.br | M30: 45320 | N30: Reprovado | O30: Edital não Contempla Construção | AE30: =AVERAGE(Q30:AD30) -> #DIV/0! | AF30: =IF(AE30>=$AF$1,"APROVADO","REPROVADO") -> #DIV/0!
B31: 259 | C31: 259/23 | D31: Organização | E31: Vila Vicentina de Lorena | F31: O Bem-Estar da Pessoa Idosa | G31: Eixo I: Promoção, Assistência e Desenvolvimento Social | H31: 382200 | I31: Lorena/SP | J31: DRADS VALE DO PARAÍBA EM SÃO JOSÉ DOS CAMPOS | K31: Arina Domingues Moreira | L31: sercicosocialvvl@outlook.com | M31: 45320 | N31: Reprovado | O31: Edital não Contempla Aquisição de Veiculo | Q31: 0 | R31: 0 | AE31: =AVERAGE(Q31:AD31) -> 0 | AF31: =IF(AE31>=$AF$1,"APROVADO","REPROVADO") -> REPROVADO
B32: 275 | C32: 275/23 | D32: Organização | E32: Lar e Escola José Olintho Fortes Junqueira | F32: Aconchego | G32: Eixo I: Promoção, Assistência e Desenvolvimento Social | H32: 1720000 | I32: São Joaquim da Barra/SP | J32: DRADS FRANCA | K32: Bianca | L32: larescola1@hotmail.com | M32: 45320 | N32: Reprovado | O32: Edital não Contempla Construção | Q32: 0 | R32: 0 | AE32: =AVERAGE(Q32:AD32) -> 0 | AF32: =IF(AE32>=$AF$1,"APROVADO","REPROVADO") -> REPROVADO
B33: 316 | C33: 316/23 | D33: Prefeitura | E33: Municipal Santa Cruz do Rio Pardo | F33: Aquisição de equipamentos para o Condomínio Prefeito Doutor Clóvis Guimarães Teixeira Coelho | G33: Eixo I: Promoção, Assistência e Desenvolvimento Social | H33: 100000 | I33: Santa Cruz do Rio Pardo/SP | J33: DRADS AVARÉ | K33: Diego Henrique Singolani Costa | L33: gabinete@pradopolis.sp.gov.br | M33: 45321 | N33: Reprovado | O33: Edital não Contempla Aquisição de Veiculo | AE33: =AVERAGE(Q33:AD33) -> #DIV/0! | AF33: =IF(AE33>=$AF$1,"APROVADO","REPROVADO") -> #DIV/0!
B34: 330 | C34: 330/23 | D34: Organização | E34: Lar São Vicente de Paulo de São José do Rio Preto | F34: Aquisição de Veiculo: Assegurar e Acessar | G34: Eixo I: Promoção, Assistência e Desenvolvimento Social | H34: 314834.19 | I34: São José do Rio Preto/SP | J34: DRADS SÃO JOSÉ DO RIO PRETO | K34: Maraise Cristina Siqueira | L34: adm@larsaovicente.org.br | M34: 45321 | N34: Reprovado | O34: Edital não Contempla Aquisição de Veiculo | Q34: 0 | R34: 0 | AE34: =AVERAGE(Q34:AD34) -> 0 | AF34: =IF(AE34>=$AF$1,"APROVADO","REPROVADO") -> REPROVADO
B35: 333 | C35: 333/23 | D35: Prefeitura | E35: Municipal de Taciba | F35: Maturidade Ativa | G35: Eixo I: Promoção, Assistência e Desenvolvimento Social | H35: 335000 | I35: Taciba/SP | J35: DRADS ALTA SOROCABANA EM PRESIDENTE PRUDENTE | K35: Leandra Tomaz Santos Soares | L35: suas@saosimao.sp.gov.br | M35: 45321 | N35: Reprovado | O35: Edital não Contempla Aquisição de Veiculo | Q35: 0 | R35: 0 | AE35: =AVERAGE(Q35:AD35) -> 0 | AF35: =IF(AE35>=$AF$1,"APROVADO","REPROVADO") -> REPROVADO
B36: 357 | C36: 357/23 | D36: Prefeitura | E36: Municipal de Bebedouro | F36: Vida em movimento | G36: Eixo I: Promoção, Assistência e Desenvolvimento Social | H36: 1000000 | I36: Bebedouro/SP | J36: DRADS BARRETOS | K36: Lucas Seren Gibin | L36: gabinete.prefeito@bebebedouro.sp.gov.br | M36: 45321 | N36: Reprovado | O36: Edital não Contempla Aquisição de Veiculo | AE36: =AVERAGE(Q36:AD36) -> #DIV/0! | AF36: =IF(AE36>=$AF$1,"APROVADO","REPROVADO") -> #DIV/0!
B37: 363 | C37: 363/23 | D37: Prefeitura | E37: Municipal de Barretos | F37: Van Adaptada | G37: Eixo VII: Cultura, Esporte, Turismo e Lazer | H37: 318990 | I37: Barretos/SP | J37: DRADS BARRETOS | K37: Vitória de Lourdes Toledo Saretta de Oliveira | L37: gabinete@charqueada.sp.gov.br / saude@charqueada.sp.gov.br / cras@charqueada.sp.gov.br | M37: 45321 | N37: Reprovado | O37: Edital não Contempla Aquisição de Veiculo | Q37: 0 | R37: 0 | AE37: =AVERAGE(Q37:AD37) -> 0 | AF37: =IF(AE37>=$AF$1,"APROVADO","REPROVADO") -> REPROVADO
B38: 364 | C38: 364/23 | D38: Prefeitura | E38: Municipal de Barretos | F38: Hidro 60 Mais | G38: Eixo VII: Cultura, Esporte, Turismo e Lazer | H38: 1000000 | I38: Barretos/SP | J38: DRADS BARRETOS | K38: Vitória de Lourdes Toledo Saretta de Oliveira | L38: assistenciasocial@barretos.sp.gov.br | M38: 45321 | N38: Reprovado | O38: Edital não Contempla Construção | Q38: 0 | AE38: =AVERAGE(Q38:AD38) -> 0 | AF38: =IF(AE38>=$AF$1,"APROVADO","REPROVADO") -> REPROVADO
B39: 369 | C39: 369/23 | D39: Organização | E39: Vila Vicentina Abrigo para Velhos | F39: Corpo em Movimento: a água como forma de prevenção e reabilitação de idosos | G39: Eixo I: Promoção, Assistência e Desenvolvimento Social | H39: 1410121.6 | I39: Bauru/SP | J39: DRADS BAURU | K39: Marcia Aparecida Chelim | L39: diretoria@vilavicentinabauru.com.br | M39: 45321 | N39: Reprovado | O39: Edital não Contempla Construção | Q39: 0 | R39: 0 | AE39: =AVERAGE(Q39:AD39) -> 0 | AF39: =IF(AE39>=$AF$1,"APROVADO","REPROVADO") -> REPROVADO
B40: 374 | C40: 374/23 | D40: Organização | E40: Asilo São Vicente de Paulo de Piraju | F40: Terapia Assistida por Animais | G40: Eixo I: Promoção, Assistência e Desenvolvimento Social | H40: 105500 | I40: Assis/SP | J40: DRADS MARÍLIA | K40: Ana Carolina Leite Machado | L40: adm@asilosaovicentepauloassis.com.br | M40: 45322 | N40: Reprovado | O40: Edital não Contempla Construção | Q40: 0 | R40: 0 | AE40: =AVERAGE(Q40:AD40) -> 0 | AF40: =IF(AE40>=$AF$1,"APROVADO","REPROVADO") -> REPROVADO
B41: 379 | C41: 379/23 | D41: Prefeitura | E41: Municipal de Tabatinga | F41: Viver em Movimento na Melhor Idade | G41: Eixo V: Habitação e Urbanismo | H41: 180000 | I41: Tabatinga/SP | J41: DRADS ARARAQUARA | K41: Rosemara dos Santos Fermino | L41: gabinete@tabatinga.sp.gov.br | M41: 45322 | N41: Reprovado | O41: Edital não Contempla Aquisição de Veiculo | Q41: 0 | R41: 0 | AE41: =AVERAGE(Q41:AD41) -> 0 | AF41: =IF(AE41>=$AF$1,"APROVADO","REPROVADO") -> REPROVADO
B42: 384 | C42: 384/23 | D42: Prefeitura | E42: Municipal de Cafelândia | F42: Transporte Segruro CCI | G42: Eixo I: Promoção, Assistência e Desenvolvimento Social | H42: 350000 | I42: Cafelândia/SP | J42: DRADS BAURU | K42: Fábio Arrotheia | L42: secsocial@cafelandia.sp.gov.br | M42: 45322 | N42: Reprovado | O42: Edital não Contempla Aquisição de Veiculo | AE42: =AVERAGE(Q42:AD42) -> #DIV/0! | AF42: =IF(AE42>=$AF$1,"APROVADO","REPROVADO") -> #DIV/0!
B43: 394 | C43: 394/23 | D43: Organização | E43: Lar e Internato Otoniel de Camargo | F43: Crescer para Melhor Atender | G43: Eixo I: Promoção, Assistência e Desenvolvimento Social | H43: 1489280 | I43: Araraquara/SP | J43: DRADS ARARAQUARA | K43: Leandro José Oliveira | L43: larotoniel@outlook.com | M43: 45322 | N43: Reprovado | O43: Edital não Contempla Construção | Q43: 0 | R43: 0 | AE43: =AVERAGE(Q43:AD43) -> 0 | AF43: =IF(AE43>=$AF$1,"APROVADO","REPROVADO") -> REPROVADO
B44: 412 | C44: 412/23 | D44: Organização | E44: Batuira Serviços de Promoçao Familia | F44: Vida Plena | G44: Eixo I: Promoção, Assistência e Desenvolvimento Social | H44: 430300 | I44: São Paulo/SP | J44: DRADS CAPITAL EM SÃO PAULO | K44: Athur Sinnhofer | L44: nucleobatuira2@gmail.com | M44: 45322 | N44: Reprovado | O44: Edital não Contempla Aquisição de Veiculo | Q44: 0 | R44: 51 | T44: 68 | AE44: =AVERAGE(Q44:AD44) -> 39.666667 | AF44: =IF(AE44>=$AF$1,"APROVADO","REPROVADO") -> REPROVADO
B45: 413 | C45: 413/23 | D45: Organização | E45: Batuira Serviços de Promoçao Familia | F45: Experiencia e Vida | G45: Eixo I: Promoção, Assistência e Desenvolvimento Social | H45: 242400 | I45: São Paulo/SP | J45: DRADS CAPITAL EM SÃO PAULO | K45: Athur Sinnhofer | L45: nucleobatuira2@gmail.com | M45: 45322 | N45: Reprovado | O45: Edital não Contempla Aquisição de Veiculo | Q45: 0 | R45: 51 | T45: 56 | AE45: =AVERAGE(Q45:AD45) -> 35.666667 | AF45: =IF(AE45>=$AF$1,"APROVADO","REPROVADO") -> REPROVADO
B46: 414 | C46: 414/23 | D46: Organização | E46: Batuira Serviços de Promoçao Familia | F46: Nosso Lar | G46: Eixo I: Promoção, Assistência e Desenvolvimento Social | H46: 375800 | I46: São Paulo/SP | J46: DRADS CAPITAL EM SÃO PAULO | K46: Athur Sinnhofer | L46: nucleobatuira2@gmail.com | M46: 45322 | N46: Reprovado | O46: Edital não Contempla Aquisição de Veiculo | Q46: 0 | R46: 0 | T46: 58 | AE46: =AVERAGE(Q46:AD46) -> 19.333333 | AF46: =IF(AE46>=$AF$1,"APROVADO","REPROVADO") -> REPROVADO
B47: 466 | C47: 466/23 | D47: Prefeitura | E47: Municipal de Areiopolis | F47: Saúde na Mulher Idade | G47: Eixo VII: Cultura, Esporte, Turismo e Lazer | H47: 594499.12 | I47: Areiópolis/SP | J47: DRADS BOTUCATU | K47: Antônio Marcos dos Santos | L47: prefeitira@areiopolis.sp.gov.br | M47: 45322 | N47: Reprovado | O47: Edital não Contempla Construção | AE47: =AVERAGE(Q47:AD47) -> #DIV/0! | AF47: =IF(AE47>=$AF$1,"APROVADO","REPROVADO") -> #DIV/0!
B48: 471 | C48: 471/23 | D48: Prefeitura | E48: Municipal Taquarituba | F48: AmpliAÇÃO – CCI espaço que transforma vidas | G48: Eixo I: Promoção, Assistência e Desenvolvimento Social | H48: 800000 | I48: Taquarituba/SP | J48: DRADS AVARÉ | K48: Carolina Maria Aparecida Vieira | L48: taquarituba@taquarituba.sp.gov.br | M48: 45322 | N48: Reprovado | O48: Edital não Contempla Construção | AE48: =AVERAGE(Q48:AD48) -> #DIV/0! | AF48: =IF(AE48>=$AF$1,"APROVADO","REPROVADO") -> #DIV/0!
B49: 474 | C49: 474/23 | D49: Prefeitura | E49: Municipal de Viradouro | F49: CCI Hélio Guerreiro - Idoso, Vida Feliz! | G49: Eixo I: Promoção, Assistência e Desenvolvimento Social | H49: 450000 | I49: Viradouro/SP | J49: DRADS BARRETOS | K49: Vânia Eduarda bocalete Pontes Gestal | L49: social@viradouro.sp.gov.br | M49: 45322 | N49: Reprovado | O49: Edital não Contempla Aquisição de Veiculo | AE49: =AVERAGE(Q49:AD49) -> #DIV/0! | AF49: =IF(AE49>=$AF$1,"APROVADO","REPROVADO") -> #DIV/0!
B50: 480 | C50: 480/23 | D50: Organização | E50: Centro Educacional Efraim | F50: Creche para a Melhor Idade | G50: Eixo I: Promoção, Assistência e Desenvolvimento Social | H50: 568400 | I50: São Paulo/SP | J50: DRADS CAPITAL EM SÃO PAULO | K50: Vilma Silva | L50: entroedefraim@gmail.com | M50: 45322 | N50: Reprovado | O50: Projeto enviado em Duplicidade | P50: (documentos no Pendrive está misturado e a capa do envolope repetida 480/23 e 481/23) | Q50: 0 | AE50: =AVERAGE(Q50:AD50) -> 0 | AF50: =IF(AE50>=$AF$1,"APROVADO","REPROVADO") -> REPROVADO
B51: 486 | C51: 486/2 | D51: Prefeitura | E51: Municipal de Juquitiba | F51: Promovendo a Autonomia do Idoso | G51: Eixo I: Promoção, Assistência e Desenvolvimento Social | H51: 633863.52 | I51: Juquitiba/SP | J51: DRADS SPO EM OSASCO | K51: Ayres Scorsatto | L51: comunicacao@juquitiba.sp.gov.br | M51: 45322 | N51: Reprovado | O51: Nota 0 nos itens 2 e 5 Formulário de Avaliação de Projeto (Edital) | Q51: 0 | AE51: =AVERAGE(Q51:AD51) -> 0 | AF51: =IF(AE51>=$AF$1,"APROVADO","REPROVADO") -> REPROVADO
B52: 492 | C52: 492/23 | D52: Organização | E52: Instituto Ecoanima | F52: Centro Dia para Idosos em Bairro Sustentável - Desenvolvimento Urbano Sustentável - São Bernardo do Campo 2030 | G52: Eixo V: Habitação e Urbanismo | H52: 3500000 | I52: São Paulo/SP | J52: DRADS CAPITAL EM SÃO PAULO | K52: Luiz Alexandre Mucerino | L52: luiz.alexandre@ecoplano.com.br | M52: 45322 | N52: Reprovado | O52: Edital não Contempla Construção | AE52: =AVERAGE(Q52:AD52) -> #DIV/0! | AF52: =IF(AE52>=$AF$1,"APROVADO","REPROVADO") -> #DIV/0!
B53: 500 | C53: 500/23 | D53: Prefeitura | E53: Municipal de Santa Rita d'Oeste | F53: Conviver - Construção de Espaço | G53: Eixo I: Promoção, Assistência e Desenvolvimento Social | H53: 160000 | I53: Santa Rita d' Oeste/SP | J53: DRADS FERNANDÓPOLIS | K53: Fernanda Leme | L53: social@severinia.sp.gov.br | M53: 45322 | N53: Reprovado | O53: Edital não Contempla Construção | Q53: 0 | R53: 0 | AE53: =AVERAGE(Q53:AD53) -> 0 | AF53: =IF(AE53>=$AF$1,"APROVADO","REPROVADO") -> REPROVADO
B54: 540 | C54: 540/23 | D54: Organização | E54: Asilo São Vicente de Paulo | F54: Casa Acolhedora | G54: Eixo I: Promoção, Assistência e Desenvolvimento Social | H54: 262359 | I54: Cruzeiro/SP | J54: DRADS VALE DO PARAÍBA EM SÃO JOSÉ DOS CAMPOS | K54: Maressa Francine de Aquino Dias | L54: asilocrz@gmail.com | M54: 45322 | N54: Reprovado | O54: Edital não Contempla Construção | AE54: =AVERAGE(Q54:AD54) -> #DIV/0! | AF54: =IF(AE54>=$AF$1,"APROVADO","REPROVADO") -> #DIV/0!
B55: 567 | C55: 567/23 | D55: Organização | E55: Associação Ação Vida | F55: Vivendo com Sabedoria | G55: Eixo VII: Cultura, Esporte, Turismo e Lazer | H55: 3082071.1 | I55: Guarulhos/SP | J55: DRADS SPN EM GUARULHOS | K55: Arnaldo Sousa de Oliveira | L55: ongacaovida_presidencia@hotmail.com | M55: 45322 | N55: Reprovado | O55: Nota 0 no item 5 Formulário de Avaliação de Projeto (Edital) | P55: Plano de Trabalho sem n° de páginas | Q55: 0 | AD55: 54 | AE55: =AVERAGE(Q55:AD55) -> 27 | AF55: =IF(AE55>=$AF$1,"APROVADO","REPROVADO") -> REPROVADO
B56: 594 | C56: 592/23 | D56: Organização | E56: Associação Star Clube Esporte e Lazer | F56: Ativos na Maturidade - II | G56: Eixo VII: Cultura, Esporte, Turismo e Lazer | H56: 428520 | I56: Franca/SP | J56: DRADS FRANCA | K56: Desdedith Morais da Silva | L56: starfutebolclube@hotmail.com | M56: 45322 | N56: Reprovado | O56: Projeto enviado em Duplicidade | P56: PDF sem n° de páginas e rubricar | Q56: 0 | AE56: =AVERAGE(Q56:AD56) -> 0 | AF56: =IF(AE56>=$AF$1,"APROVADO","REPROVADO") -> REPROVADO
B57: 604 | C57: 602/23 | D57: Organização | E57: Real e Benemérita Associação Portuguesa de Beneficiência | F57: Terceira Idade Ativa | G57: Eixo VII: Cultura, Esporte, Turismo e Lazer | H57: 2034120 | I57: São Paulo/SP | J57: DRADS CAPITAL EM SÃO PAULO | K57: Juliana de Carvalho Opipari | L57: parcerias@bp.org.br | M57: 45322 | N57: Reprovado | O57: Nota 0 nos itens 2 Formulário de Avaliação de Projeto (Edital) | P57: Recurso n°029/24 | Z57: 0 | AE57: =AVERAGE(Q57:AD57) -> 0 | AF57: =IF(AE57>=$AF$1,"APROVADO","REPROVADO") -> REPROVADO

Sheet Sem Pontuação Minima
AG1: 204
B2: CONSELHO ESTADUAL DO IDOSO Rua Boa Vista, 170- CEP 01204-001 - São Paulo-SP Fone 11-2763-8122/2763-8035 cei@desenvolvimentosocial.sp.gov.br
B3: ORGANIZAÇÕES SOCIAIS
C4: Protocolo | D4: OSC/Prefeitura | E4: NOME DO PROPONENTE | F4: NOME DO PROJETO | G4: EIXO | H4: VALOR TOTAL DO PROJETO | I4: MUNICÍPIO | J4: DRADS | K4: Responsável - OSC | L4: EMAIL | M4: ENTREGUE DIA | N4: ETAPA da Análise | O4: PENDÊNCIA | P4: OBS | Q4: NOTA Gilberto | R4: NOTA Erica | S4: NOTA Enizal | T4: NOTA Walkyria | U4: NOTA Elisete | V4: NOTA Adriano | W4: NOTA Paulo Albano | X4: NOTA Alexandra | Y4: NOTA Priscila | Z4: NOTA Leila | AA4: NOTA Vanise | AB4: NOTA Jeverson | AC4: NOTA Cristiane | AD4: NOTA Márcio | AF4: Média | AG4: RESULTADO FINAL
B5: 14 | C5: 014/23 | D5: Organização | E5: Lar do Velhinhos Papa João XXIII | F5: Lavanderia | G5: Eixo I: Promoção, Assistência e Desenvolvimento Social | H5: 275400 | I5: Salto Grande/SP | J5: DRADS AVARÉ | K5: Bruna Fernandes Araujo | L5: asiloaltogrande@hotmail.com | M5: 45321 | N5: Classificado | P5: Verificar se não são repetidos (Protocolo 014 e 348/23) | Q5: 288 | R5: 118 | T5: 177 | AE5: =COUNTA(Q5:AD5) -> 3 | AF5: =AVERAGE(Q5:AD5) -> 194.33333 | AG5: =IF(AF5>=$AG$1,"APROVADO","REPROVADO") -> REPROVADO
B6: 19 | C6: 019/23 | D6: Prefeitura | E6: Municipal de Pratânia | F6: Grupo Melhor Idade | G6: Eixo I: Promoção, Assistência e Desenvolvimento Social | H6: 120000 | I6: Pratânia/SP | J6: DRADS BOTUCATU | K6: Elaine Cristina Rodrigues Honorato | L6: cras@boraceia.sp.gov.br | M6: 45302 | N6: Classificado | Q6: 297 | S6: 180 | T6: 112 | AE6: =COUNTA(Q6:AD6) -> 3 | AF6: =AVERAGE(Q6:AD6) -> 196.33333 | AG6: =IF(AF6>=$AG$1,"APROVADO","REPROVADO") -> REPROVADO
B7: 27 | C7: 027/23 | D7: Organização | E7: Lar São Vicente de Paulo de Taquarituba | F7: Acessibilidade | G7: Eixo V: Habitação e Urbanismo | H7: 150000 | I7: Taquarituba/SP | J7: DRADS AVARÉ | K7: Isabela Steinert Gabriel | L7: larsaovicente-taquarituba@hotmail.com | M7: 45303 | N7: Classificado | Q7: 306 | R7: 55 | T7: 66 | AE7: =COUNTA(Q7:AD7) -> 3 | AF7: =AVERAGE(Q7:AD7) -> 142.33333 | AG7: =IF(AF7>=$AG$1,"APROVADO","REPROVADO") -> REPROVADO
B8: 28 | C8: 028/23 | D8: Organização | E8: Lar São Vicente de Paulo de Taquarituba | F8: Garantia de Bem Estar | G8: Eixo I: Promoção, Assistência e Desenvolvimento Social | H8: 120000 | I8: Taquarituba/SP | J8: DRADS AVARÉ | K8: Isabela Steinert Gabriel | L8: larsaovicente-taquarituba@hotmail.com | M8: 45303 | N8: Classificado | Q8: 340 | S8: 60 | T8: 79 | AE8: =COUNTA(Q8:AD8) -> 3 | AF8: =AVERAGE(Q8:AD8) -> 159.66667 | AG8: =IF(AF8>=$AG$1,"APROVADO","REPROVADO") -> REPROVADO
B9: 40 | C9: 040/23 | D9: Prefeitura | E9: Municipal de Apiaí | F9: Conhecendo População de Pessoas Idosas | G9: Eixo I: Promoção, Assistência e Desenvolvimento Social | H9: 80000 | I9: Apiaí/SP | J9: DRADS ITAPEVA | K9: Sergio Victor Borges Barbosa | L9: deptosocial@nantes.sp.gov.br | M9: 45303 | N9: Pré-Classificado | Q9: 200 | R9: 133 | AB9: 157 | AE9: =COUNTA(Q9:AD9) -> 3 | AF9: =AVERAGE(Q9:AD9) -> 163.33333 | AG9: =IF(AF9>=$AG$1,"APROVADO","REPROVADO") -> REPROVADO
B10: 41 | C10: 041/23 | D10: Organização | E10: Lar Fraterno São Vicente de Apiaí | F10: Em busca de um sonho | G10: VII –Turismo | H10: 50000 | I10: Apiaí/SP | J10: DRADS ITAPEVA | K10: Alaíme Yuki monteiro Takiguchi Correa | L10: asiloapiai@hotmail.com | M10: 45303 | N10: Pré-Classificado | R10: 75 | V10: 189 | W10: 164 | AE10: =COUNTA(Q10:AD10) -> 3 | AF10: =AVERAGE(Q10:AD10) -> 142.66667 | AG10: =IF(AF10>=$AG$1,"APROVADO","REPROVADO") -> REPROVADO
B11: 56 | C11: 056/23 | D11: Organização | E11: Lar São Vicente de Paulo | F11: Aquisição de camas motorizadas e colchões | G11: Eixo I: Promoção, Assistência e Desenvolvimento Social | H11: 259202 | I11: Descalvado/SP | J11: DRADS ARARAQUARA | K11: Vírginia Elaine da S. N. Guiguer | L11: larsao vicentepaulo@terra.com.br | M11: 45306 | N11: Pré-Classificado | O11: Documento Word (Pendrive) | R11: 108 | V11: 278 | W11: 39 | AE11: =COUNTA(Q11:AD11) -> 3 | AF11: =AVERAGE(Q11:AD11) -> 141.66667 | AG11: =IF(AF11>=$AG$1,"APROVADO","REPROVADO") -> REPROVADO
B12: 57 | C12: 057/23 | D12: Prefeitura | E12: Municipal de Descalvado | F12: Idoso em Movimento | G12: Eixo VII: Cultura, Esporte, Turismo e Lazer | H12: 473200 | I12: Descalvado/SP | J12: DRADS ARARAQUARA | K12: Marly Colognesi Reschini | L12: social.apiai@gmail.com | M12: 45306 | N12: Classificado | Q12: 298 | R12: 82 | T12: 76 | AE12: =COUNTA(Q12:AD12) -> 3 | AF12: =AVERAGE(Q12:AD12) -> 152 | AG12: =IF(AF12>=$AG$1,"APROVADO","REPROVADO") -> REPROVADO
B13: 108 | C13: 108/23 | D13: Organização | E13: Recanto do Vovô | F13: Revitalização da Osc | G13: Eixo I: Promoção, Assistência e Desenvolvimento Social | H13: 800000 | I13: Birigui/SP | J13: DRADS ALTA NOROESTE EM ARAÇATUBA | K13: Maria Lucia Crispim | L13: recantodovovo@hotmail.com | M13: 45307 | N13: Pré-Classificado | P13: Não Atende aos criterios do Edital | Q13: 307 | R13: 52 | S13: 82 | AE13: =COUNTA(Q13:AD13) -> 3 | AF13: =AVERAGE(Q13:AD13) -> 147 | AG13: =IF(AF13>=$AG$1,"APROVADO","REPROVADO") -> REPROVADO
B14: 127 | C14: 127/23 | D14: Organização | E14: Abrigo da Velhice São Vicente de Paulo | F14: Valorizando a Vida | G14: Eixo I: Promoção, Assistência e Desenvolvimento Social | H14: 1212370 | I14: São Paulo/SP | J14: DRADS CAPITAL EM SÃO PAULO | K14: João Felipe Egídio | L14: Abrigo@abrigosaovicenterc.com.br | M14: 45308 | N14: Classificado | Q14: 302 | R14: 103 | U14: 99 | AE14: =COUNTA(Q14:AD14) -> 3 | AF14: =AVERAGE(Q14:AD14) -> 168 | AG14: =IF(AF14>=$AG$1,"APROVADO","REPROVADO") -> REPROVADO
B15: 129 | C15: 129/23 | D15: Organização | E15: Vila Vicentina de Caraguatatuba | F15: A nova trajetória no resgate dos direitos e bem estar dos idosos | G15: Eixo I: Promoção, Assistência e Desenvolvimento Social | H15: 49990 | I15: Caraguatatuba/SP | J15: DRADS VALE DO PARAÍBA EM SÃO JOSÉ DOS CAMPOS | K15: Luiz Otávio Paes | L15: vicentinasocial@gmail.com | M15: 45308 | N15: Classificado | Q15: 254 | R15: 144 | U15: 151 | AE15: =COUNTA(Q15:AD15) -> 3 | AF15: =AVERAGE(Q15:AD15) -> 183 | AG15: =IF(AF15>=$AG$1,"APROVADO","REPROVADO") -> REPROVADO
B16: 144 | C16: 144/23 | D16: Prefeitura | E16: Municipal de Francisco Morato/SP | F16: Vitalidade - Atividade e Saúde | G16: Eixo VII: Cultura, Esporte, Turismo e Lazer | H16: 137325.73 | I16: Francisco Morato/SP | J16: DRADS SPN EM GUARULHOS | K16: Maria Aparecida Bisetto | L16: secretaria@miraestrela.sp.gov.br | M16: 45308 | N16: Classificado | Q16: 324 | R16: 123 | U16: 128 | AE16: =COUNTA(Q16:AD16) -> 3 | AF16: =AVERAGE(Q16:AD16) -> 191.66667 | AG16: =IF(AF16>=$AG$1,"APROVADO","REPROVADO") -> REPROVADO
B17: 148 | C17: 148/23 | D17: Organização | E17: Fundação de Apoio á Pesquisa, Ensino, Tecnologia e Cultura - FAPETEC | F17: Prolonge - Planejamento Estratégico de Aposentadoria Sustentável | G17: Eixo III: Educação Eixo VI: Justiça | H17: 3027360 | I17: Santos/SP | J17: DRADS BAIXADA SANTISTA EM SANTOS | K17: Prof. Antonio Carlos Kobori | L17: fapetec@fapetec.org.br | M17: 45308 | N17: Classificado | Q17: 179 | Z17: 174 | AA17: 217 | AE17: =COUNTA(Q17:AD17) -> 3 | AF17: =AVERAGE(Q17:AD17) -> 190 | AG17: =IF(AF17>=$AG$1,"APROVADO","REPROVADO") -> REPROVADO
B18: 238 | C18: 239/23 | D18: Organização | E18: Lar Vicentino Padre Pio de Itatinga | F18: Bem Vindo ao Lar | G18: - | H18: 300000 | I18: Itatinga/SP | J18: DRADS BOTUCATU | K18: Antônio Edurado Barbosa | L18: ou.larpadrepio@hotmail.com | M18: 45320 | N18: Pré-Classificado | O18: Envelope | Q18: 214 | R18: 173 | S18: 208 | AE18: =COUNTA(Q18:AD18) -> 3 | AF18: =AVERAGE(Q18:AD18) -> 198.33333 | AG18: =IF(AF18>=$AG$1,"APROVADO","REPROVADO") -> REPROVADO
B19: 248 | C19: 248/23 | D19: Prefeitura | E19: Municipal do Cajuru | F19: Feliz Idade | G19: Eixo VII: Cultura, Esporte, Turismo e Lazer | H19: 200000 | I19: Cajuru/SP | J19: DRADS RIBEIRÃO PRETO | K19: Katia Regina Lippi | L19: gabinetedoprefeito@altinopolis.sp.gov.br | M19: 45320 | N19: Pré-Classificado | Q19: 241 | R19: 106 | AC19: 247 | AE19: =COUNTA(Q19:AD19) -> 3 | AF19: =AVERAGE(Q19:AD19) -> 198 | AG19: =IF(AF19>=$AG$1,"APROVADO","REPROVADO") -> REPROVADO
B20: 276 | C20: 276/23 | D20: Prefeitura | E20: Municiapal de Sud Menucci | F20: Idosos Conectados | G20: Eixo II: Sáude | H20: 310000 | I20: Sud Menucci/SP | J20: DRADS ALTA NOROESTE EM ARAÇATUBA | K20: José Urbino dos Santos Neto | L20: social@sudmenucci.sp.gov.br | M20: 45320 | N20: Pré-Classificado | Q20: 164 | V20: 204 | W20: 190 | AE20: =COUNTA(Q20:AD20) -> 3 | AF20: =AVERAGE(Q20:AD20) -> 186 | AG20: =IF(AF20>=$AG$1,"APROVADO","REPROVADO") -> REPROVADO
B21: 336 | C21: 336/23 | D21: Organização | E21: Instituto Educacional Toque para o Futuro | F21: Projeto Saúde e Cidadania na Melhor Idade | G21: - | H21: 693592.44 | I21: São Paulo/SP | J21: DRADS CAPITAL EM SÃO PAULO | K21: Sara Brahiana de Medeiros | L21: toqueparaofuturo@yahoo.com.br | M21: 45321 | N21: Pré-Classificado | O21: Não consta Plano de Trabalho no Pendrive | Q21: 241 | R21: 80 | AC21: 251 | AE21: =COUNTA(Q21:AD21) -> 3 | AF21: =AVERAGE(Q21:AD21) -> 190.66667 | AG21: =IF(AF21>=$AG$1,"APROVADO","REPROVADO") -> REPROVADO
B22: 382 | C22: 382/23 | D22: Prefeitura | E22: Municipal de Itápolis | F22: Idoso em Movimento | G22: Eixo I: Promoção, Assistência e Desenvolvimento Social | H22: 85449.78 | I22: Itápolis/SP | J22: DRADS ARARAQUARA | K22: Héllen Cristina Motta Vizotto | L22: d.gabinete@itapolis.sp.gov.br | M22: 45322 | N22: Classificado | Q22: 139 | R22: 180 | T22: 183 | AE22: =COUNTA(Q22:AD22) -> 3 | AF22: =AVERAGE(Q22:AD22) -> 167.33333 | AG22: =IF(AF22>=$AG$1,"APROVADO","REPROVADO") -> REPROVADO
B23: 404 | C23: 404/23 | D23: Organização | E23: Instituto Floravida | F23: Programa Coletivo 60+ | G23: Eixo I: Promoção, Assistência e Desenvolvimento Social | H23: 337705.54 | I23: Botucatu/SP | J23: DRADS BOTUCATU | K23: Valquíria B. Moraes dos Santos | L23: administracao@floravida.org.br | M23: 45322 | N23: Classificado | O23: Construção | Q23: 327 | R23: 64 | T23: 97 | AE23: =COUNTA(Q23:AD23) -> 3 | AF23: =AVERAGE(Q23:AD23) -> 162.66667 | AG23: =IF(AF23>=$AG$1,"APROVADO","REPROVADO") -> REPROVADO
B24: 415 | C24: 415/23 | D24: Organização | E24: Lar Evangélico Alice de Oliveira | F24: Projeto de Inovação e qualificação do Serviço de Acolhimento Lar Alice de Oliveira. | G24: Eixo I: Promoção, Assistência e Desenvolvimento Social | H24: 236635.08 | I24: Campinas/SP | J24: DRADS CAMPINAS | K24: Alessandra A. Bueno | L24: lar.alice.oliveira@hotmail.com | M24: 45322 | N24: Classificado | Q24: 338 | R24: 98 | T24: 125 | AE24: =COUNTA(Q24:AD24) -> 3 | AF24: =AVERAGE(Q24:AD24) -> 187 | AG24: =IF(AF24>=$AG$1,"APROVADO","REPROVADO") -> REPROVADO
B25: 421 | C25: 421/23 | D25: Organização | E25: Recanto dos Idosos Luz Divina | F25: Um olhar para o Amanhã na Terceira Idade | G25: Eixo I: Promoção, Assistência e Desenvolvimento Social | H25: 1370825 | I25: Suzano/SP | J25: DRADS SPL EM MOGI DAS CRUZES | K25: Naiara Santos Pinho | L25: luzdivina-financeiro@hotmail.com | M25: 45322 | N25: Classificado | Q25: 311 | R25: 112 | T25: 137 | AE25: =COUNTA(Q25:AD25) -> 3 | AF25: =AVERAGE(Q25:AD25) -> 186.66667 | AG25: =IF(AF25>=$AG$1,"APROVADO","REPROVADO") -> REPROVADO
B26: 483 | C26: 483/23 | D26: Prefeitura | E26: Municipal de Mesópolis | F26: Mais Atividade Física menos Doenças | G26: Eixo VII: Cultura, Esporte, Turismo e Lazer | H26: 254600 | I26: Mesópolis/SP | J26: DRADS FERNANDÓPOLIS | K26: Éder William Barboza Domingos (Projeto: Mais atividade Física, menos doença) | L26: esporte@mesopolis.sp.gov.br | M26: 45322 | N26: Pré-Classificado | Q26: 167 | V26: 212 | Y26: 223 | AE26: =COUNTA(Q26:AD26) -> 3 | AF26: =AVERAGE(Q26:AD26) -> 200.66667 | AG26: =IF(AF26>=$AG$1,"APROVADO","REPROVADO") -> REPROVADO
B27: 508 | C27: 508/23 | D27: Prefeitura | E27: Municipal de Sorocaba | F27: Qualifica Sorocaba “Melhor Idade” | G27: Eixo IV – Trabalho e Previdência Social | H27: 200000 | I27: Sorocaba/SP | J27: DRADS SOROCABA | K27: Rodrigo Cesar Oliveira | L27: municipio@indiapora.sp.gov.br | M27: 45322 | N27: Classificado | Q27: 306 | R27: 129 | T27: 98 | AE27: =COUNTA(Q27:AD27) -> 3 | AF27: =AVERAGE(Q27:AD27) -> 177.66667 | AG27: =IF(AF27>=$AG$1,"APROVADO","REPROVADO") -> REPROVADO
D44: Tudo OK
D45: Desclassificado e Reprovado
D46: Aguardando Correção (classificado)
D47: Pré-Classicado (falta 1 nota)
D48: Classificado falta nota para fechar

Sheet Aprovados Recursos do Fundo
AQ1: 204
B2: CONSELHO ESTADUAL DO IDOSO Rua Boa Vista, 170- CEP 01204-001 - São Paulo-SP Fone 11-2763-8122/2763-8035 cei@desenvolvimentosocial.sp.gov.br | BJ2: 46100
B3: ,
C5: Protocolo | D5: OSC/Prefeitura | E5: NOME DO PROPONENTE | F5: NOME DO PROJETO | G5: EIXO | H5: VALOR TOTAL DO PROJETO | I5: CUSTEIO | J5: AQUISIÇÃO | K5: N° DE BENEFICIÁRIO | L5: CNPJ | M5: ENDEREÇO | N5: BAIRRO | O5: CEP | P5: MUNICÍPIO | Q5: CODIGO IBGE | R5: TELEFONE | S5: DRADS | T5: SOMA | U5: Responsável - OSC | V5: EMAIL | W5: ENTREGUE DIA | X5: ETAPA da Análise | Y5: PENDÊNCIA | Z5: OBS | AA5: NOTA Gilberto | AB5: NOTA Erica | AC5: NOTA Enizal | AD5: NOTA Walkyria | AE5: NOTA Elisete | AF5: NOTA Adriano | AG5: NOTA Paulo Albano | AH5: NOTA Alexandra | AI5: NOTA Priscila | AJ5: NOTA Leila | AK5: NOTA Vanise | AL5: NOTA Jeverson | AM5: NOTA Cristiane | AN5: NOTA Márcio | AP5: Média | AQ5: RESULTADO FINAL | AR5: Documentação | AS5: 1° contato correção | AT5: PROCESSO SEI | AU5: TCE | AV5: Prazo Notificação | AW5: Localização | AZ5: Etapa | BA5: Data da Assinatura do TERMO | BB5: Aditamento | BC5: Vigência do Termo (12 meses) | BD5: Data da Publicação em Diário Oficial | BE5: Data do Pagamento 1° parcela | BF5: Data do Pagamento 2° parcela | BG5: Gestor | BH5: SimPPA | BI5: DATA | BJ5: Dias
B6: 135 | C6: 135/23 | D6: Prefeitura | E6: Municipal de Ourinhos | F6: Voltando a Sorrir na Terceira Idade | G6: Eixo II: Sáude | H6: 465571.15 | I6: 403684.25 | J6: 61886.9 | K6: 100 | L6: 53.415.717 0001-60 | M6: Rua Antônio de Almeida Leite, 649 | N6: Jardim Paulista | O6: 19900-000 | P6: Ourinhos | Q6: 3534708 | R6: 3302-6000 | S6: DRADS AVARÉ | T6: 1 | U6: Raquel Borges Spada | V6: smmf.ourinhos@gmail.com | W6: 45308 | X6: Pré-Classificado | Y6: PDF sem assinatura e rubrica | AA6: 340 | AF6: 340 | AG6: 340 | AO6: 3 | AP6: 340 | AQ6: APROVADO | AR6: Atualizar o oficio, faltou ANEXO VII e os 03 orçamentos | AS6: falta terminar o processo | AT6: 012.00004181/2024-35 | AV6: 28.05.2024 | AW6: SES-GS-ATA8 | AX6: Sec. Saúde | AY6: Sec. Saúde | AZ6: Parecer Técnico | BI6: 46083 | BJ6: =_xlfn.DAYS($BJ$2,BI6) -> 17 | BK6: Email enviado aos Conselheiros da Pasta de atuação do eixo em 11/11.
B7: 181 | C7: 181/23 | D7: Prefeitura | E7: Municipal de Orindiúva | F7: Espaço ConViver | G7: Eixo I: Promoção, Assistência e Desenvolvimento Social | H7: 79666.17 | I7: 0 | J7: 79666.17 | K7: 50 | L7: 45.148.970/0001-77 | M7: Praça Maria Dias, 614 | N7: Centro | O7: 15480-000 | P7: Orindiúva | Q7: 3534203 | R7: (17)3816-9600 | S7: DRADS: SÃO JOSÉ DO RIO PRETO | T7: 1 | U7: Mireli Cristina Leite Ruvieri Martins | V7: prefeitura@orindiuva.sp.gov.br Assistencia@orindiuva.sp.gov.br | W7: 45314 | X7: Pré-Classificado | Y7: Plano de Tralaho sem n° de páginas | AA7: 340 | AF7: 340 | AG7: 340 | AO7: 3 | AP7: 340 | AQ7: APROVADO | AR7: faltou 3 orçamentos | AS7: Notificado por e-mail 09.05.2024 ás 17h10 | AT7: 012.00004267/2024-68 | AV7: 30.05.2024 | AW7: SEDS-CEI-PRESTCONTAS | AZ7: Prestação de Contas - CEI | BA7: 45915 | BB7: 45951 | BC7: =EDATE(BA7,12) -> 46280 | BD7: 45916 | BE7: 45994 | BI7: 46002 | BJ7: =_xlfn.DAYS($BJ$2,BI7) -> 98 | BK7: Manual de prestação de contas enviado
B8: 199 | C8: 200/23 | D8: Prefeitura | E8: Municipal de Bady Bassitt | F8: Florescer 60 + | G8: Eixo I: Promoção, Assistência e Desenvolvimento Social | H8: 70311.8 | I8: 0 | J8: 70311.8 | K8: 330 | L8: 45.093.267/0001-09 | M8: Rua Camilo de Moraes,75 | N8: Centro | O8: 15115-000 | P8: Bady Bassitt | Q8: 3504602 | R8: (17) 3818-5100 | S8: DRADS: SÃO JOSÉ DO RIO PRETO | T8: 1 | U8: Luiz Antonio Tobardini | V8: prefeitura@badybassitt.sp.gov.br | W8: 45315 | X8: Pré-Classificado | AA8: 340 | AF8: 340 | AG8: 340 | AO8: 3 | AP8: 340 | AQ8: APROVADO | AR8: faltou 3 orçamentos | AS8: Notificação enviada dia 09.05.24 ás 13h29 | AT8: 012.00004110/2024-32 | AV8: 30.05.2024 | AW8: SEDS-CEI-PRESTCONTAS | AZ8: Prestação de Contas - CEI | BA8: 45643 | BC8: =EDATE(BA8,12) -> 46008 | BD8: 45646 | BE8: 45734 | BG8: Não Tem | BH8: Setembro á dezembro 2024 | BI8: 45735 | BJ8: =_xlfn.DAYS($BJ$2,BI8) -> 365 | BK8: Sem prestação de Contas - Não foi executado - Notificação reenviada 09/03/26 E-mail enviado dia 29.01.2026 solicitando envio do oficio para execução
B9: 265 | C9: 265/23 | D9: Organização | E9: Lar dos Velhinhos DR. Adolpho Barreto | F9: Promovendo Acessibilidade para a Terceira Idade | G9: Eixo I: Promoção, Assistência e Desenvolvimento Social | H9: 253465 | I9: =H9/2 -> 126732.5 | J9: 126732.5 | K9: 50 | L9: 52.506.110/0001-23 | M9: Coronel José Pereira Lima,1274 | N9: Centro | O9: 13730-220 | P9: Mococa | Q9: 3530508 | R9: (19) 36560203 | S9: DRADS MOGIANA EM SÃO JOÃO DA BOA VISTA | T9: 1 | U9: Daiane Cristina Satilio Pereira | V9: velhinhosdemococa@uol.com.br | W9: 45320 | X9: Pré-Classificado | AA9: 340 | AF9: 340 | AG9: 340 | AO9: 3 | AP9: 340 | AQ9: DESCLASSIFICADO | AR9: Notificado dia 03.06.2024 | AS9: Atalizar oficio declaração Dirigente máximo Falta o CCM Valores não batem Confirmar os Orçamentos e planilha | AT9: 012.00005167/2024-59 | AV9: 24.06.2024 | AW9: SEDS-CEI | AZ9: Parecer Técnico | BI9: 45643 | BJ9: =_xlfn.DAYS($BJ$2,BI9) -> 457 | BK9: Declassificado - OBRA E-mail enviado dia 17.12.2024
B10: 285 | C10: 285/23 | D10: Organização | E10: Lar Vicentino de Itapeva | F10: Aquisição de Máquina de Lavar Roupas | G10: Eixo I: Promoção, Assistência e Desenvolvimento Social | H10: 141000 | I10: 0 | J10: 141000 | K10: 133 | L10: 49.802.762/0001-09 | M10: Praça Dom Sílvio Maria Dário, 126 | N10: Itapeva | O10: 18.400-004 | P10: Itapeva | Q10: 3522406 | R10: (15) 3522-03481 | S10: DRADS ITAPEVA | T10: 1 | U10: Renê de castro Silva | V10: larvicentinodeitapeva@gmail.com | W10: 45321 | X10: Pré-Classificado | AA10: 340 | AF10: 340 | AG10: 340 | AO10: 3 | AP10: 340 | AQ10: APROVADO | AR10: Notificado 28.05.2024 | AS10: Atualizar oficio Declaração Dirigente Planilha Orçamento | AT10: 012.00004301/2024-02 | AU10: 0000038851 | AV10: 20.06.2024 | AW10: SEDS-SPP-CAR-ITA | AZ10: Prestação de Contas Final | BA10: 46042 | BC10: =EDATE(BA10,12) -> 46407 | BD10: 45646 | BE10: 45674 | BG10: Priscilla Domingues | BH10: Setembro á dezembro 2024 | BI10: 46036 | BJ10: =_xlfn.DAYS($BJ$2,BI10) -> 64 | BK10: Processo enviado para DRADS emitir o parecer conclusivo. Processo em finalização e sem vigência
B11: 297 | C11: 297/2 | D11: Prefeitura | E11: Municipal de Taiaçu | F11: Uma História para Vida | G11: Eixo VII: Cultura, Esporte, Turismo e Lazer | H11: 35000 | I11: 35000 | J11: 0 | K11: 400 | L11: 44.544.690/0001-15 | M11: Rua Raul Maçone, 306 | N11: Centro | O11: 14.725-000 | P11: Taiaçu | Q11: 3553104 | R11: (16) 3275-6400 | S11: DRADS BARRETOS | T11: 1 | U11: Mauricio Lofrano Geraldo | V11: assistenciasocial@taiacu.sp.gov.br contas@taiacu.sp.gov.br | W11: 45321 | X11: Pré-Classificado | AA11: 340 | AF11: 340 | AG11: 340 | AO11: 3 | AP11: 340 | AQ11: APROVADO | AR11: Atualizar Oficio Orçamentos Planilha | AS11: Notificado por e-mail dia 16.05.2024 às 16h20 | AT11: 012.00004907/2024-30 | AV11: 10.05.2024 | AW11: SEDS-CEI PARCERIAS | AX11: Sec. Cultura, Economia | AZ11: Execução 1° Parcela | BA11: 45868 | BB11: 46239 | BC11: =EDATE(BA11,12) -> 46233 | BD11: 45870 | BE11: 45874 | BG11: Não Tem | BH11: maio à agosto 2025 | BI11: 46098 | BJ11: =_xlfn.DAYS($BJ$2,BI11) -> 2
B12: 335 | C12: 335/23 | D12: Prefeitura | E12: Municipal de Itapura | F12: O Som da Vida – um projeto de música, conversa, intercâmbio intergeracional e movimento com os idosos de Itapura | G12: Eixo VII: Cultura, Esporte, Turismo e Lazer | H12: 217379.4 | I12: 217379.4 | J12: =H12-I12 -> 0 | K12: 80 | L12: 44.447.126/0001-84 | M12: Rua Getúlio Vargas,1.087 | N12: Centro | O12: 15.390-000 | P12: Itapura | Q12: 3523008 | R12: (18) 3742-9020. | S12: DRADS ALTA NOROESTE EM ARAÇATUBA | T12: 1 | U12: Célia Regina dq Silva Dourado | V12: secretaria@itapura.sp.gov.br lpgitapura@gmail.com | W12: 45321 | X12: Pré-Classificado | AA12: 340 | AG12: 340 | AI12: 340 | AO12: 3 | AP12: 340 | AQ12: APROVADO | AR12: Ajuste oficio e planilha | AS12: Notificação por e-mail dia 09.05.2024 às 17h51 | AT12: 012.00003922/2024-61 | AV12: 30.05.2024 | AW12: SEDS-SGC-DA-CCP | AX12: Sec. Cultura, Economia | AZ12: Aditamento | BA12: 45793 | BC12: =EDATE(BA12,12) -> 46158 | BD12: 45800 | BE12: 45805 | BG12: Não tem | BH12: maio à agosto 2025 | BI12: 46099 | BJ12: =_xlfn.DAYS($BJ$2,BI12) -> 1 | BK12: Prestação de contas não analisada e o processo perderá a vigência em 16/05/26. Processo encaminhado para aditamento e posterior envio para analise da prestação de contas.
B13: 355 | C13: 355/23 | D13: Prefeitura | E13: Municipal de Manduri | F13: Vovós Ativas, Arteiras e Cantantes | G13: Eixo I: Promoção, Assistência e Desenvolvimento Social | H13: 35000 | I13: 24272 | J13: 10728 | L13: 46.223.749/0001-07 | M13: Rua Bahia nº 233 | N13: Centro | O13: 18780-000 | P13: Manduri | Q13: 3528601 | R13: (14) 3356-9200 | S13: DRADS AVARÉ | T13: 1 | U13: José Onivaldo Justi | V13: secretaria@manduri.sp.gov.br | W13: 45321 | X13: Pré-Classificado | AA13: 340 | AF13: 340 | AG13: 340 | AO13: 3 | AP13: 340 | AQ13: DESCLASSIFICADO | AR13: Soma do total não bate com o valor do plano de trabalho | AS13: Não consegui contato por telefone, e-mail enviado dia 08.05 ás 12h52 | AT13: 012.00003837/2024-01 | AV13: 23.05.2024 | AW13: SEDS-CEI-PROJETOS | AZ13: Prestação de Contas | BA13: 45638 | BD13: 45642 | BE13: 45674 | BG13: Não Tem | BH13: Setembro á dezembro 2024 | BI13: 45933 | BJ13: =_xlfn.DAYS($BJ$2,BI13) -> 167 | BK13: 03/10 enviada orientações para devolução do valor e encerramento do processo..
B14: 361 | C14: 361/23 | D14: Prefeitura | E14: Municipal de Monte Azul Paulista | F14: Semeando Autores | G14: Eixo VII: Cultura, Esporte, Turismo e Lazer | H14: 40000 | I14: 40000 | J14: 0 | K14: 20 | L14: 52.942.380/0001-87 | M14: Praça Rio Branco, 86 | N14: Centro | O14: 14730-000 | P14: Monte Azul Paulista | Q14: 3531506 | R14: (17) 3361-2210 | S14: DRADS BARRETOS | T14: 1 | U14: Marcelo Otaviano dos Santos | V14: prefeito@monteazulpaulista.sp.gov.br | W14: 45321 | X14: Pré-Classificado | AA14: 340 | AH14: 340 | AI14: 340 | AO14: 3 | AP14: 340 | AQ14: APROVADO | AR14: faltou 3 orçamentos, ajustar oficio, PT e os anexos | AS14: Notificação enviada por e-mail 09.05.2024 ás 17h28 | AT14: 012.00003851/2024-04 | AV14: 30.05.2024 | AW14: SEDS-CEI-PRESTCONTAS | AX14: Sec. Cultura, Economia | AZ14: Prestação de Contas - CEI | BA14: 45799 | BC14: =EDATE(BA14,12) -> 46164 | BD14: 45800 | BE14: 45805 | BG14: Não Tem | BH14: maio à agosto 2025 | BI14: 45806 | BJ14: =_xlfn.DAYS($BJ$2,BI14) -> 294 | BK14: Notificação enviada 26/02
B15: 378 | C15: 378/23 | D15: Prefeitura | E15: Municipal de Tabatinga | F15: Visão do Bem | G15: Eixo II: Sáude | H15: 124800 | I15: =H15 -> 124800 | J15: 0 | K15: 60 | L15: 71.989.685/0001-99 | M15: Rua Dario Rodrigues Louzada,338 | N15: Centro | O15: 14910-000 | P15: Tabatinga | Q15: 3552700 | R15: (16) 3321-9500 | S15: DRADS ARARAQUARA | T15: 1 | U15: Rosemara dos Santos Fermino | V15: gabinete@tabatinga.sp.gov.br social@tabatinga.sp.gov.br | W15: 45322 | X15: Pré-Classificado | AA15: 340 | AF15: 340 | AG15: 340 | AO15: 3 | AP15: 340 | AQ15: APROVADO | AR15: (16) 9 9790-5724 | AS15: Tudo OK | AT15: 012.00003525/2024-99 | AV15: - | AW15: SEDS-SGC-DA-CCP-DIVPC | AZ15: Prestação de Contas - DPC | BA15: 45748 | BC15: =EDATE(BA15,12) -> 46113 | BD15: 45751 | BE15: 45761 | BG15: Não Tem | BH15: janeiro à abril 2025 | BI15: 46084 | BJ15: =_xlfn.DAYS($BJ$2,BI15) -> 16 | BK15: Processo encaminhado a Coordenadoria de Convênios e Parcerias 03/03/2026
B16: 388 | C16: 388/23 | D16: Organização | E16: Sociedade São Vicente de Paula de Andradina | F16: Viabilização da assistencia integral aos idosos através de adequação das instalações da instituição | G16: Eixo I: Promoção, Assistência e Desenvolvimento Social | H16: 40500 | I16: 40500 | J16: 0 | K16: 50 | L16: 43.542.505/0001-90 | M16: Rua São Sebastião s/n | N16: Pereira Jordão | O16: 16900-160 | P16: Andradina | Q16: 3502101 | R16: (18)3722-1318 | S16: DRADS ALTA NOROESTE EM ARAÇATUBA | T16: 1 | U16: Gercino Jose da Silva | V16: asilo.andradina@hotmail.com | W16: 45322 | X16: Pré-Classificado | Z16: sem informação no envelope | AA16: 340 | AH16: 340 | AI16: 340 | AO16: 3 | AP16: 340 | AQ16: APROVADO | AR16: Notificado dia 28.05.2024 | AS16: Oficio Digirente máximo Cetidão de improbidade planilha | AT16: 012.00004591/2024-86 | AV16: 20.06.2024 | AW16: SEDS-SGC-DA-CCP-DIVGCP | AZ16: Pagamento 2° parcela | BA16: 45643 | BC16: =EDATE(BA16,12) -> 46008 | BD16: 45646 | BE16: 45674 | BG16: Thiago Agenor Dos Santos De Lima - DRADS-ANO | BH16: Setembro á dezembro 2024 | BI16: 46079 | BJ16: =_xlfn.DAYS($BJ$2,BI16) -> 21 | BK16: Processo encaminhado para aditamento e ressarcimento
B17: 420 | C17: 420/23 | D17: Prefeitura | E17: Municipal de Americana | F17: EnvelheSer | G17: Eixo I: Promoção, Assistência e Desenvolvimento Social | H17: 515500 | I17: 419700 | J17: 95800 | K17: 140 | L17: 45.781.176/0001-66 | M17: Rua das Poncianas, 1225 | N17: Jardim Glória | O17: 13468-180 | P17: Americana | Q17: 3501608 | R17: (19) 3471-6770 | S17: DRADS CAMPINAS | T17: 1 | U17: Janainade Freitas de Oliveira | V17: janainafreitas.sasdh@americana.sp.gov.br | W17: 45322 | X17: Pré-Classificado | AA17: 340 | AF17: 340 | AI17: 340 | AO17: 3 | AP17: 340 | AQ17: APROVADO | AR17: ajuste oficio, planilha e dúvida nos orçamentos | AS17: Notificação enviada para Janaína por e-mail e no dia 09.05 às 12h08 | AT17: 012.00004175/2024-88 | AV17: 30.05.2024 | AW17: SEDS-CEI-PRESTCONTAS | AX17: DRADS CAMPINAS | AY17: DRADS Campinas | AZ17: Prestação de Contas - CEI | BA17: 45784 | BC17: =EDATE(BA17,12) -> 46149 | BD17: 45790 | BE17: 45811 | BG17: Não Tem | BH17: maio à agosto 2025 | BI17: 45930 | BJ17: =_xlfn.DAYS($BJ$2,BI17) -> 170 | BK17: Notificação enviada 26/02
B18: 448 | C18: 448/2 | D18: Organização | E18: Lar Vicentino | F18: Aquisição de Equipamento para Fisioterapia | G18: Eixo II: Sáude | H18: 16476.17 | I18: 4446.39 | J18: 12029.78 | K18: 32 | L18: 49.862.493/0001-68 | M18: Rua Guilherme Francisco da Silva, 256 | N18: Bocaina | O18: 1240-017 | P18: Bocaina | Q18: 3506805 | R18: :(14) 3666-1500 | S18: DRADS BAURU | T18: 1 | U18: Anaina Patricia Violla | V18: larvicentinobocaina@uol.com.br | W18: 45322 | X18: Pré-Classificado | AA18: 340 | AF18: 340 | AG18: 340 | AO18: 3 | AP18: 340 | AQ18: APROVADO | AR18: Notificado dia 27.05.2024 | AS18: Soma do total não bate com o valor do plano de trabalho | AT18: 012.00004721/2024-81 | AV18: 19.06.2024 | AW18: SEDS-SGC-DA-CCP-DIVPC | AX18: Sec. Saúde | AZ18: Prestação de Contas - DPC | BA18: 45762 | BC18: =EDATE(BA18,12) -> 46127 | BD18: 45770 | BE18: 45800 | BG18: Daniele Ribeiro da Silva | BH18: janeiro à abril 2025 | BI18: 26/02/2026 | BJ18: 0 | BK18: Processo enviado para análise da prestação de contas ( Divisão de prestação de contas)
B19: 449 | C19: 449/23 | D19: Organização | E19: Abrigo São Lourenço de Jaú | F19: Promover a melhoria da qualidade de vida e bem-estar físico e social da pessoa idosa acolhida no Abrigo São Lourenço de Jaú | G19: Eixo I: Promoção, Assistência e Desenvolvimento Social | H19: 89104 | I19: 0 | J19: 89104 | K19: 50 | L19: 50.759.091/0001-11 | M19: Avenida do Café,131 | N19: Vila Ivan | O19: 17207-202 | P19: Jaú | Q19: 3525300 | R19: (14) 3622-2624 | S19: DRADS BAURU | T19: 1 | U19: Renato Hilst Ribeiro | V19: abrigosaolourenco@gmail.com marahilst19@gmail.com | W19: 45322 | X19: Pré-Classificado | AA19: 340 | AF19: 340 | AG19: 340 | AO19: 3 | AP19: 340 | AQ19: APROVADO | AR19: Notificado dia 27.05.2024 | AS19: Tudo Ok (ver apenas os 03 orçamentos de aceitos) | AT19: 012.00004515/2024-71 | AV19: 19.06.2024 | AW19: SEDS-SGC-DA-CCP | AZ19: Prestação de Contas - CEI | BA19: 45643 | BC19: =EDATE(BA19,12) -> 46008 | BD19: 45646 | BE19: 45674 | BG19: Angelita Maria DRADS Bauru | BH19: Setembro á dezembro 2024 | BI19: 46097 | BJ19: =_xlfn.DAYS($BJ$2,BI19) -> 3 | BK19: Projeto executado, encaminhado a Divisão de Prestação de Contas
B20: 461 | C20: 461/23 | D20: Organização | E20: Lar dos Velhinhos de Souza Spinola | F20: Projeto Piso Novo | G20: Eixo V: Habitação e Urbanismo | H20: 213318.26 | I20: =H20 -> 213318.26 | J20: 0 | K20: 50 | L20: 51.347.540/0001-87 | M20: Rua lacanga, 374 | N20: Jardim Santa Clara | O20: 14.962-202 | P20: Novo Horizonte | Q20: 3533502 | R20: (17) 3542 1935 | S20: DRADS SÃO JOSÉ DO RIO PRETO | T20: 1 | U20: Maria Lourenço Prado da Silva | V20: lardevelhicemss@hotmail.com | W20: 45322 | X20: Pré-Classificado | Y20: Plano fora do padrão | AA20: 340 | AF20: 340 | AG20: 340 | AO20: 3 | AP20: 340 | AQ20: APROVADO | AR20: Notificado dia 27.05.2024 | AS20: Atualizar Oficio plano de Trabalho ajustar (modelo, execução e itens 11 e 12) planilha | AT20: 012.00004678/2024-53 | AV20: 19.06.2024 | AW20: SEDS-SGC-DA-CCP-DIVPC | AZ20: Prestação de Contas - DPC | BA20: 45643 | BC20: =EDATE(BA20,12) -> 46008 | BD20: 45646 | BE20: 45674 | BF20: 45994 | BG20: Patricia Cecilio Domingues Azevedo | BH20: Setembro á dezembro 2024 | BI20: 46090 | BJ20: =_xlfn.DAYS($BJ$2,BI20) -> 10 | BK20: Lucimara (17) 9 9748-2189 Encaminhado para Coordenadoria de Convênios e Parceria 09/03/26
B21: 476 | C21: 476/23 | D21: Prefeitura | E21: Municipal Julio Mesquita | F21: Aquisição de Equipamentos e Mobiliários para Centro de Convivência do Idoso | G21: Eixo I: Promoção, Assistência e Desenvolvimento Social | H21: 50000 | I21: 7532.83 | J21: =H21-I21 -> 42467.17 | K21: 450 | L21: 44.518.496/0001-65 | M21: Rua Francisco da Fonseca, 213 | N21: Centro | O21: 17550-000 | P21: Júlio Mesquita | Q21: 3525805 | R21: (14) 3487-9090 | S21: DRADS MARÍLIA | T21: 1 | U21: Elton Francisco de Brito | V21: prefeitura@juliomesquita.sp.gov.br | W21: 45322 | X21: Pré-Classificado | AA21: 340 | AF21: 340 | AG21: 340 | AO21: 3 | AP21: 340 | AQ21: APROVADO | AR21: Sona não bate, ajustar oficio, PT, planilha e anexos 0 Falta o novo plano de trabalaho | AS21: Notificação enviada por e-mail dia 09.05.2024 às 17h39 03.06.2024 às 15h44 | AT21: 012.00004269/2024-57 | AV21: 30.05.2024 | AW21: SEDS-SGC-DA-CCP-DIVGCP | AZ21: Aditamento | BA21: 45762 | BC21: =EDATE(BA21,12) -> 46127 | BD21: 45770 | BE21: 45800 | BG21: Não tem | BH21: janeiro à abril 2025 | BI21: 46087 | BJ21: =_xlfn.DAYS($BJ$2,BI21) -> 13 | BK21: Processo enviado para Aditamento (sem prestação de contas)
B22: 509 | C22: 509/23 | D22: Prefeitura | E22: Municipal de Sorocaba | F22: Sempre Sorrindo | G22: Eixo II: Sáude | H22: 1882430 | I22: 1882430 | J22: 0 | K22: 1570 | L22: 46.634.044/0001-74 | M22: Avenida Engenheiro Carlos Reinaldo Mendes, 3041 | N22: Parque da Boa ista | O22: 18013-280 | P22: Sorocaba | Q22: 3552205 | R22: (15) 3238-2422 | S22: DRADS SOROCABA | T22: 1 | U22: Silmar Rogério Abdala | V22: captacaoderecursos@sorocaba.sp.gov.br | W22: 45322 | X22: Pré-Classificado | Y22: Plano sem rubrica | AA22: 340 | AF22: 340 | AG22: 340 | AO22: 3 | AP22: 340 | AQ22: APROVADO | AR22: Oficio Planilha PT esta diferente usar da rede | AS22: Notificação enviada por e-mail dia 16.05.2024 às 16h46 | AT22: 012.00004347/2024-13 | AV22: 10.05.2024 | AW22: SEDS-CEI-PRESTCONTAS | AX22: Sec. Saúde | AZ22: Prestação de Contas - CEI | BA22: 45826 | BC22: =EDATE(BA22,12) -> 46191 | BD22: 45833 | BE22: 45839 | BG22: Não Tem | BH22: maio à agosto 2025 | BI22: 45840 | BJ22: =_xlfn.DAYS($BJ$2,BI22) -> 260 | BK22: Notificação enviada 09/03/26
B23: 541 | C23: 541/23 | D23: Organização | E23: Asilo São Vicente de Paulo | F23: Casa Nova | G23: Eixo I: Promoção, Assistência e Desenvolvimento Social | H23: 101246.7 | I23: 101246.7 | J23: 0 | K23: 22 | L23: 47.437.751/0001-33 | M23: Rua Dom bosco, 567 | N23: Centro | O23: 12701-250 | P23: Cruzeiro | Q23: 3513405 | R23: (12) 31441257 | S23: DRADS VALE DO PARAÍBA EM SÃO JOSÉ DOS CAMPOS | T23: 1 | U23: Maressa Francine de Aquino Dias | V23: asilocrz@gmail.com | W23: 45322 | X23: Pré-Classificado | Y23: Plano de Trabalho sem n° de páginas | AA23: 340 | AF23: 340 | AG23: 340 | AO23: 3 | AP23: 340 | AQ23: DESCLASSIFICADO | AR23: Notificado dia 27.05.2024 | AS23: Decl. Diririgente máximo Experiencia previa Os valores do PT não batem (11 e 12) valor total Planilha de orç. | AT23: 012.00005101/2024-69 | AV23: 19.06.2024 | AW23: SEDS-CEI | AZ23: Parecer Técnico | BI23: 45628 | BJ23: =_xlfn.DAYS($BJ$2,BI23) -> 472 | BK23: A OSC não retornar os e-mail Enviar e-mail de desclassificação
B24: 562 | C24: 562/23 | D24: Organização | E24: Centro Promocional "Nossa Senhora da Visitação" | F24: Bordando no Território | G24: Eixo VII: Cultura, Esporte, Turismo e Lazer | H24: 261889.72 | I24: 198114.65 | J24: 63775.07 | K24: 30 | L24: 46.044-467/0001-34 | M24: Avenida Márcio Egídio de Souza Aranha, 143 | N24: Jardim Ipaussurama | O24: 13060-840 | P24: Campinas | Q24: 3509502 | R24: (19) 3227-81ZI | S24: DRADS CAMPINAS | T24: 1 | U24: Luis Carlos Martins Pereira | V24: visitacao@cpvisitacao.org.br | W24: 45322 | X24: Pré-Classificado | Y24: PDF sem assinatura | AA24: 340 | AF24: 340 | AG24: 340 | AO24: 3 | AP24: 340 | AQ24: APROVADO | AR24: Analisada, falta notificar | AS24: Faltou Oficio CMA Decl. Dirigente máximo Inegebilidade Planilha dos orç. | AT24: 012.00005074/2024-24 | AW24: SEDS-SGC-DA-CCP-DIVPC | AZ24: Prestação de Contas - DPC | BA24: 45840 | BC24: =EDATE(BA24,12) -> 46205 | BD24: 45841 | BE24: 45867 | BG24: Daniele Ribeiro da Silva | BH24: maio à agosto 2025 | BI24: 46084 | BJ24: =_xlfn.DAYS($BJ$2,BI24) -> 16 | BK24: Processo encaminhado para Coordenadora de Convênios e Parceria 03/03/26
B25: 243 | C25: 243/23 | D25: Prefeitura | E25: Municipal de Altinópolis | F25: Serviço de Convivência e Fortalecimento de Vínculos Terceira Idade | G25: Eixo I: Promoção, Assistência e Desenvolvimento Social | H25: 100000 | I25: 10086.4 | J25: 89913.6 | K25: 80 | L25: 45.298.569.0001-13 | M25: Rua Major Garcia, 144 | N25: Centro | O25: 14350-000 | P25: Altinópolis | Q25: 3501004 | R25: (16) 3665-9500 | S25: DRADS RIBEIRÃO PRETO | T25: 1 | U25: Adriana Shirley Gonçalves | V25: gestorsocial@altinopolis.sp.gov.br | W25: 45320 | X25: Pré-Classificado | Y25: Falta de Informação do envelope | Z25: 012.00004330/2024-66, foi encerrado porque estava com a documentação de outra PM. Novo Processo aberto | AA25: 337 | AF25: 340 | AG25: 340 | AO25: 3 | AP25: 339 | AQ25: APROVADO | AR25: Oficio Justificativa CNPJ Anexo PL Eixo PT Orçamentos e planilha ajustes PT item 12 | AS25: Notificado por e-mail dia 16.05.2024 às 16h07 | AT25: 012.00007184/2024-21 | AV25: 10.05.2024 | AW25: SEDS-SGC-DA-CCP | AZ25: Aditamento | BA25: 45764 | BC25: =EDATE(BA25,12) -> 46129 | BD25: 45771 | BE25: 45800 | BG25: Não Tem | BH25: janeiro à abril 2025 | BI25: 46077 | BJ25: =_xlfn.DAYS($BJ$2,BI25) -> 23
B26: 434 | C26: 434/23 | D26: Organização | E26: Mater Dei Cam - Casa de Apoio a Menina | F26: Renovarte | G26: Eixo IV: Trabalho e Previdência Social | H26: 306290 | I26: =H26-J26 -> 281510 | J26: 24780 | K26: 984 | L26: 03.951.901/0001-57 | M26: Praça Papa João Paulo I, 65 | N26: Atibaia Jardim | O26: 12940-230 | P26: Atibaia | Q26: 3504107 | R26: (11) 4413 - 2938 | S26: DRADS CAMPINAS | T26: 1 | U26: Ginmarco Bisaglia | V26: cadastro@materdeicam.org.br | W26: 45322 | X26: Pré-Classificado | AA26: 336 | AF26: 340 | AG26: 340 | AO26: 3 | AP26: 338.66667 | AQ26: APROVADO | AR26: Notificado dia 27.05.2024 | AS26: Ajustar o Plano de trabalho e o plano de aplicação | AT26: 012.00004681/2024-77 | AV26: 19.06.2024 | AW26: SEDS-GSPOFP | AZ26: Instrução para Assinatura | BI26: 46091 | BJ26: =_xlfn.DAYS($BJ$2,BI26) -> 9
B27: 565 | C27: 565/23 | D27: Prefeitura | E27: Municipal Álvares Machado | F27: Feliz Idade | G27: Eixo I: Promoção, Assistência e Desenvolvimento Social | H27: 40275 | I27: 15000 | J27: =H27-I27 -> 25275 | K27: 70 | L27: 43.206.424/0001-10 | M27: Praça da Bandeira, s in 0 | N27: Centro | O27: 19160-000 | P27: Álvares Machado | Q27: 3501301 | R27: (18) 3273-9300 | S27: DRADS ALTA SOROCABANA EM PRESIDENTE PRUDENTE | T27: 1 | U27: Jovelina de Souza Monteiro | V27: assistencia@alvaresmachado.sp.gov.br | W27: 45322 | X27: Pré-Classificado | Y27: Documentos Word (Pendrive) | AA27: 334 | AH27: 340 | AI27: 340 | AO27: 3 | AP27: 338 | AQ27: APROVADO | AR27: Tudo Ok (ver apenas os 03 orçamentos de aceitos) | AS27: E-mail com os apontamentos enviados dia 08.05 | AT27: 012.00003839/2024-91 | AV27: 23.05.2024 | AW27: SEDS-SGC-DA-CCP | AZ27: Pagamento 2° parcela | BA27: 45638 | BB27: 13/09/2026 | BC27: =EDATE(BA27,12) -> 46003 | BD27: 45642 | BE27: 45733 | BG27: Não Tem | BH27: Setembro á dezembro 2024 | BI27: 46092 | BJ27: =_xlfn.DAYS($BJ$2,BI27) -> 8 | BK27: Processo paralizado a execução pendencia da 2° parcela Processo enviado para análise da prestação de contas 06.02.2026 Processo encaminhado para Roseli verificar se podemos pagar 17.03.2026
B28: 185 | C28: 186/23 | D28: Prefeitura | E28: Municipio de São Bernado do Campo | F28: Campeões e Vitória para Vida | G28: Eixo VII: Cultura, Esporte, Turismo e Lazer | H28: =I28+J28 -> 515262.2 | I28: 512664.2 | J28: 2598 | K28: 500 | L28: 46.523.239/0001-47 | M28: Praça Samuel Sabatini, 50 | N28: Centro | O28: 09750-700 | P28: São Bernardo do Campo | Q28: 3548708 | R28: (11) 2630-7445 | S28: DRADS ABC EM SANTO ANDRÉ | T28: 1 | U28: Tamara Vicente | V28: tamara.vicente@saobernardo.sp.gov.br orlando.morando@saobernardodocampo.sp.gov.br | W28: 45315 | X28: Pré-Classificado | Y28: PDF sem assinatura e rubrica | AA28: 338 | AF28: 340 | AG28: 335 | AO28: 3 | AP28: 337.66667 | AQ28: APROVADO | AR28: Atualizar o oficio, periodo de execução do PL e enviar as planilhas | AS28: E-mail enviado dia 07.05.2024 às 15h42 Rafael | AT28: 012.00003606/2024-99 | AV28: - | AW28: SEDS-CEI | AZ28: Aditamento | BA28: 45740 | BC28: =EDATE(BA28,12) -> 46105 | BD28: 31/04/2025 | BE28: 45800 | BG28: Não tem | BH28: janeiro à abril 2025 | BI28: 46078 | BJ28: =_xlfn.DAYS($BJ$2,BI28) -> 22 | BK28: Notificação enviada 04/03/2026
B29: 455 | C29: 455/23 | D29: Organização | E29: Assistência Social Santo Antônio | F29: Xô Bengala | G29: Eixo VII: Cultura, Esporte, Turismo e Lazer | H29: 821100 | I29: 786683.5 | J29: 34416.5 | K29: 200 | L29: 49.871.700/0001-40 | M29: Rua Santo Antônio, 406 | N29: Granja Viana Cotia | O29: 06708-370 | P29: Cotia | Q29: 3513009 | R29: (11) 4702-2580 | S29: DRADS SPO EM OSASCO | T29: 1 | U29: Kelen Garcia | V29: info@assa.org.br | W29: 45322 | X29: Classificado | AA29: 332 | AL29: 340 | AN29: 340 | AO29: 3 | AP29: 337.33333 | AQ29: APROVADO | AR29: Valor esta diferente do plano inicial, dúvidas nas certidões, cronohtama confuso. | AT29: 012.00005270/2024-07 | AW29: SEDS-CEI-PRESTCONTAS | AZ29: Prestação de Contas - CEI | BA29: 45874 | BC29: =EDATE(BA29,12) -> 46239 | BD29: 45875 | BE29: 45881 | BG29: Daniele Ribeiro da Silva | BH29: maio à agosto 2025 | BI29: 45939 | BJ29: =_xlfn.DAYS($BJ$2,BI29) -> 161 | BK29: Notificação enviada 09/03/26
B30: 164 | C30: 164/23 | D30: Organização | E30: Sociedade Beneficiente de Amparo a Velhice de Macatuba | F30: Projeto Energia Voltaica - Autossustentabilidade em Consumo de Energia | G30: Eixo I: Promoção, Assistência e Desenvolvimento Social | H30: 90060.26 | I30: 0 | J30: 90060.26 | L30: 50.849.033/0001-89 | M30: Rua Rio Branco, 60 A | N30: Jardim Veneza | O30: 17290-390 | P30: Macatuba | Q30: 3528007 | R30: (14) 3268-1316 | S30: DRADS BAURU | T30: 1 | U30: Carmem Aparecida Gonçalves Pafetti | V30: sobavem@gmail.com | W30: 45310 | X30: Classificado | AA30: 340 | AJ30: 340 | AM30: 328 | AO30: 3 | AP30: 336 | AQ30: APROVADO | AR30: Notificado dia 03.06.2024 | AS30: Falta os anexos do plano de trabalho declaração Dirigente | AT30: 012.00004394/2024-67 | AV30: 24.06.2024 | AW30: SEDS-SGC-DA-CCP-DIVPC | AZ30: Prestação de Contas - DPC | BA30: 45643 | BC30: =EDATE(BA30,12) -> 46008 | BD30: 45646 | BE30: 45674 | BG30: Angelita Maria DRADS Bauru | BH30: Setembro á dezembro 2024 | BI30: 46056 | BJ30: =_xlfn.DAYS($BJ$2,BI30) -> 44 | BK30: Processo encaminhado para Coordenação de Convênio e parceria para análise da prestação - Aquisição. 02/03/2026
B31: 295 | C31: 295/23 | D31: Organização | E31: Lar Vicentino de Caçapava | F31: Só Lar - Aquisição e Instalação de Sistema de Energia Fotovoltaica | G31: Eixo I: Promoção, Assistência e Desenvolvimento Social | H31: 85411.67 | I31: 0 | J31: 85411.67 | K31: 40 | L31: 47.541.040/0001-04 | M31: Rua Doutor Pedro Moreira da Costa, 249 | N31: Vila Antôrio Augusto | O31: 12287-170 | P31: Caçapava | Q31: 3508504 | R31: (12) 3653-0954 | S31: DRADS VALE DO PARAÍBA EM SÃO JOSÉ DOS CAMPOS | T31: 1 | U31: Marta Rovida Cardoso | V31: larviccacapava@gmail.com | W31: 45321 | X31: Pré-Classificado | AA31: 335 | AI31: 335 | AM31: 338 | AO31: 3 | AP31: 336 | AQ31: APROVADO | AR31: Notificado dia 28.05.2024 | AS31: Experiência Prévia Decl. Dirigênte máximo Planilha Orç. | AT31: 012.00004606/2024-14 | AV31: 20.06.2024 | AW31: SEDS-CEI-PRESTCONTAS | AZ31: Prestação de Contas - CEI | BA31: 45775 | BC31: =EDATE(BA31,12) -> 46140 | BD31: 45785 | BE31: 45800 | BG31: Sueli Leite da Silva | BH31: janeiro à abril 2025 | BI31: 45926 | BJ31: =_xlfn.DAYS($BJ$2,BI31) -> 174 | BK31: Notificação enviada 09/03/26
B32: 459 | C32: 459/23 | D32: Prefeitura | E32: Municipal de Santa Adélia | F32: Vivendo o Turismo | G32: Eixo VII: Cultura, Esporte, Turismo e Lazer | H32: 75600 | I32: 75600 | J32: 0 | K32: 200 | L32: 46.599.270/0001-61 | M32: Avenida Duque de Caxias, 303 | N32: Centro | O32: 15950-000 | P32: Santa Adélia | Q32: 3545605 | R32: (17) 3511-8800 | S32: DRADS SÃO JOSÉ DO RIO PRETO | T32: 1 | U32: Cristiane M.J Raydan | V32: social@santaadelia.sp.gov.br | W32: 45322 | X32: Pré-Classificado | AA32: 330 | AF32: 340 | AG32: 338 | AO32: 3 | AP32: 336 | AQ32: APROVADO | AR32: ajustes Oficio, faltou os 3 orçamentos e faltou anexo VI | AS32: Não consegui contato por telefone notificação enviada 09.05.2024 ás 11h25 | AT32: 012.00004319/2024-04 | AV32: 03.06.2024 | AW32: SEDS-CEI-PRESTCONTAS | AX32: Sec. Turismo | AY32: Sec. Turismo | AZ32: Prestação de Contas - CEI | BA32: 45986 | BC32: =EDATE(BA32,12) -> 46351 | BD32: 45988 | BE32: 45995 | BH32: Setembro a dezembro 2025 | BI32: 45996 | BJ32: =_xlfn.DAYS($BJ$2,BI32) -> 104 | BK32: Manual de prestação de contas enviado
B33: 166 | C33: 166/23 | D33: Prefeitura | E33: Municipal de Tejupá | F33: Reforma do CCI Centro de Convivência do Idoso | G33: Eixo I: Promoção, Assistência e Desenvolvimento Social | H33: 123093.54 | I33: 123093.54 | K33: 50 | L33: 46.223.756/0001-09 | M33: Rua Alexandre Absy,326 | N33: Centro | O33: 18830-003 | P33: Tejupá | Q33: 3554201 | R33: (14) 3385-3200 | S33: DRADS AVARÉ | T33: 1 | U33: Graziela Catarina de Moraes Tantini | V33: gabinete@tejupa.sp.gov.br | W33: 45310 | X33: Pré-Classificado | Y33: Documentos Word (Pendrive) | AA33: 337 | AJ33: 333 | AM33: 336 | AO33: 3 | AP33: 335.33333 | AQ33: DESCLASSIFICADO | AR33: Reforma: verificar os orçamentos se necessários e o cronograma financeiro | AS33: Não ocnsegui contato por telefone, e-mail enviado dia 08.05 ás 12h23 | AT33: 012.00004205/2024-56 | AV33: 28.05.2024 | AW33: SEDS-CEI | AZ33: Parecer Técnico | BI33: 45643 | BJ33: =_xlfn.DAYS($BJ$2,BI33) -> 457 | BK33: Declassificado - OBRA E-mail enviado dia 17.12.2024
B34: 296 | C34: 296/23 | D34: Organização | E34: Vila Vicentina de Cachoeira Paulista | F34: Proteção e Segurança | G34: Eixo I: Promoção, Assistência e Desenvolvimento Social | H34: 150000 | I34: 150000 | K34: 30 | L34: 50.015.916/0001-93 | M34: Rua António Hummel, 204 | N34: Pitéu | O34: 12630-000 | P34: Cachoeira Paulista | Q34: 3508603 | R34: (12) 3103-1149 | S34: DRADS VALE DO PARAÍBA EM SÃO JOSÉ DOS CAMPOS | T34: 1 | U34: Juliana Marinho Lopes | V34: vilavicentina@gmail.com | W34: 45321 | X34: Pré-Classificado | AA34: 324 | AF34: 340 | AG34: 340 | AO34: 3 | AP34: 334.66667 | AQ34: DESCLASSIFICADO | AR34: Notificado dia 28.05.2024 | AS34: Experiência Prévia assinada pela OSC Decl. Dirigênte máximo Falta os anexos do plano de trabalho Planilha Orç | AT34: 012.00004659/2024-27 | AV34: 20.06.2024 | AW34: SEDS-CEI | AZ34: Parecer Técnico | BI34: 45670 | BJ34: =_xlfn.DAYS($BJ$2,BI34) -> 430 | BK34: Declassificado - OBRA E-mail enviado dia 13.01.2025
B35: 443 | C35: 443/23 | D35: Organização | E35: Instituto Divina Luz | F35: Amor a Vida | G35: Eixo I: Promoção, Assistência e Desenvolvimento Social | H35: 220000 | I35: 207000 | J35: 13000 | K35: 120 | L35: 31.635.351/0001-00 | M35: Rua Prudente de Morais, 1173 | N35: Centro | O35: 14015-100 | P35: Ribeirão Preto | Q35: 3543402 | R35: (16) 98850-1519 | S35: DRADS RIBEIRÃO PRETO | T35: 1 | U35: Kayo Melo | V35: ongdivinaluz@bol.com.br | W35: 45322 | X35: Pré-Classificado | Y35: tudo OK apenas o pendrive não abre | AA35: 329 | AF35: 340 | AG35: 335 | AO35: 3 | AP35: 334.66667 | AQ35: APROVADO | AR35: Notificada dia 27.05.2024 | AS35: Valores do PT não bate com o total e ajustar item 11 e 12 Ajustar periodo de execução Decl. Dirigente Justificativa não enviou os orç. Só a planilha (verificar o RH e demais itens serv. De terceiro) | AT35: 012.00004724/2024-14 | AU35: 58537 0000058539 0000058541 | AV35: 19.06.2024 | AW35: SEDS-CEI-PRESTCONTAS | AX35: Sec. Saúde | AZ35: Execução 2° Parcela | BA35: 45782 | BC35: =EDATE(BA35,12) -> 46147 | BD35: 45791 | BE35: 45800 | BF35: 46091 | BG35: Renan Paulo Quirino Lopes | BH35: maio à agosto 2025 | BI35: 46091 | BJ35: =_xlfn.DAYS($BJ$2,BI35) -> 9 | BK35: Processo pago a 2° parcela - Execução
B36: 470 | C36: 470/23 | D36: Prefeitura | E36: Municipal Taboão da Serra | F36: No Meu Tempo: A Participação e Cidadania com Garatia de Direito da Pessoa Idosa | G36: Eixo I: Promoção, Assistência e Desenvolvimento Social | H36: 100000 | P36: Taboão da Serra/SP | S36: DRADS SPO EM OSASCO | U36: Pedro Soares | V36: sas@taboaodaserra.sp.gov.br | W36: 45322 | X36: Reprovado | AA36: 333 | AF36: 340 | AG36: 330 | AO36: 3 | AP36: 334.33333 | AQ36: APROVADO | AR36: NÃO ENTREGOU OS DOCUMENTO NO PRAZO (10 DIAS ÚTEIS) | AS36: Não respondeu e-mail e não consigo telefone Mandou por e-mail responta dando o prazo até 09.05 | BI36: INST INICIAL-CFC | BJ36: =_xlfn.DAYS($BJ$2,BI36) -> #VALUE!
B37: 165 | C37: 165/23 | D37: Prefeitura | E37: Municipal de Mogi Guaçu | F37: Conviver em Geração | G37: Eixo I: Promoção, Assistência e Desenvolvimento Social | H37: 564876.92 | I37: =H37-J37 -> 514076.92 | J37: 50800 | L37: 45.301.264/0001-13 | M37: Rua Henrique Coppi,200 | N37: Centro | O37: 13820-641 | P37: Mogi Guaçu | Q37: 3530706 | R37: (19) 3851-7000 | S37: DRADS MOGIANA EM SÃO JOÃO DA BOA VISTA | T37: 1 | U37: Rodrigo Falsetti | V37: sps-secretario@mogiguacu.sp.gov.br rodrigofalsetti@mogiguacu.sp.gob.br | W37: 45310 | X37: Pré-Classificado | Y37: Falta de Informação do envelope | AA37: 327 | AF37: 340 | AG37: 335 | AO37: 3 | AP37: 334 | AQ37: APROVADO | AR37: Ajustar Oficio Faltou 03 orçamentos Planilha | AS37: E-mail enviado dia 16.05.2024 às 15h42 | AT37: 012.00004511/2024-92 | AV37: 10.05.2024 | AW37: SEDS-CEI | AY37: DRADS Mogiana | AZ37: Parecer Técnico | BI37: 46030 | BJ37: =_xlfn.DAYS($BJ$2,BI37) -> 70 | BK37: Aguardando a PMC atender a informação da Divisão de formalização. Prazo: 23.03.2026
B38: 169 | C38: 169/23 | D38: Prefeitura | E38: Municipal de Piraju | F38: Cuidado para Quem já Cuidou | G38: Eixo I: Promoção, Assistência e Desenvolvimento Social | H38: 188427.72 | I38: =H38-J38 -> 180384.86 | J38: 8042.86 | K38: 12 | L38: 46.223,699/0001-50 | M38: Praça Ataliba Leonel, 173 | N38: Centro | O38: 18800-020 | P38: Piraju | Q38: 3538808 | R38: (14) 3305-90Ú0 | S38: DRADS AVARÉ | T38: 1 | U38: José Maria Costa | V38: deasoadm@estanciadepiraju.sp.gov.br gabinete@estanciadepiraju.sp.gov.br | W38: 45310 | X38: Pré-Classificado | AA38: 334 | AF38: 335 | AM38: 330 | AO38: 3 | AP38: 333 | AQ38: APROVADO | AR38: Falta os orçamentos (aquisição e serviços de terceiro) | AS38: Sem contato telefonico e-mail enviado dia 08.05 as 13h20 | AT38: 012.00004177/2024-77 | AV38: 29.05.2024 | AW38: SEDS-CEI-PRESTCONTAS | AZ38: Prestação de Contas - CEI | BA38: 45791 | BC38: =EDATE(BA38,12) -> 46156 | BD38: 45796 | BE38: 45804 | BG38: Não tem | BH38: maio à agosto 2025 | BI38: 45805 | BJ38: =_xlfn.DAYS($BJ$2,BI38) -> 295 | BK38: Notificação enviada 06/03/26
